Workbook

Sheet README
A1: QA Quality Evaluation — BI single-page QA (InternVL vs Qwen2.5-VL)
A3: Scope | B3: 987 QA pairs verified against their page image (495 InternVL, 492 Qwen2.5-VL) across 165 page images. 24 QA excluded (4 images missing from the folder) and 1 Qwen page produced no QA — see Not_Verified.
A4: Method | B4: Every page image was opened and each QA checked value-by-value (numbers, entity, period, unit, direction) with small labels zoomed in. Each QA got one verdict, a severity, error types, category check, evidence from the page and, for REVISE, a corrected answer.
A5: PASS | B5: Answer fully correct as written and category label fits. Needs no change.
A6: REVISE | B6: The QA is based on the page (the data/topic exists) but needs a fix: misread/misattributed number, wrong period, unit, trend direction, calculation, incomplete answer, garbled wording, or wrong category label.
A7: DISCARD | B7: Hallucinated: the question asks about something not on the page (metric, entity, period) or is unintelligible, so neither question nor answer exists in the document. A valid question with a wrong answer is REVISE-Major, not DISCARD.
A8: Severity | B8: Minor = REVISE with small fix (core fact right). Major = REVISE with a wrong key fact. Critical = DISCARD.
A9: QA Accuracy | B9: % QA whose answer is factually correct from the start. Only category-label, typo/grammar or format issues are tolerated. (Content-level view.)
A10: First Pass Yield | B10: % QA that pass with no revision at all (strict: also requires correct category label and clean wording) = PASS / N.
A11: Revision / Discard Rate | B11: REVISE / N and DISCARD / N.
A12: Error Rate | B12: % QA with at least one error = (REVISE + DISCARD) / N = 1 − FPY. Factual Error Rate = 1 − Accuracy.
A13: Error types | B13: Hallucination, Factual/Numerical (wrong or misattributed value), Calculation, Reasoning (direction/comparison/causal), Temporal (period), Unit, Incomplete, Instruction-following (category label does not fit the QA), Format, Typo/Grammar. Primary = main reason; "any" = all errors present.
A14: Categories | B14: Text-Text Inference | Chart-Information Extraction, Chart-Numerical Calculation, Chart-Time-Sensitive | Table-Numerical Calculation, Table-Comparison and Sorting. Metrics are grouped by the category the generator assigned; Suggested Category in QA_Detail gives the category that actually fits.
... A18: Sheets | B18: Summary (headline metrics, severity, error types + charts) · By_Category (every metric per category and per Text/Chart/Table) · ErrorType_x_Category · Discard_Analysis (why discarded + full list) · Revision_Analysis · QA_Detail (every QA with verdict, evidence, corrected answer; filterable) · Not_Verified.

Sheet Summary
A1: QA Quality Metrics — verified against page images
A2: Source: bi_single_final_internvl.jsonl & bi_single_qwen25_vl.jsonl; each QA checked against its page image in bi_images/single. All numbers are live formulas over QA_Detail.
A4: Model →
A5: Metric | B5: InternVL | C5: Qwen2.5-VL | D5: Overall | E5: Definition / formula
A6: QA verified (N) | B6: =COUNTIFS(QA_Detail!$B$2:$B$988,"InternVL") -> 495 | C6: =COUNTIFS(QA_Detail!$B$2:$B$988,"Qwen2.5-VL") -> 492 | D6: =COUNTIFS(QA_Detail!$B$2:$B$988,"*") -> 987 | E6: QA pairs checked against an available page image
A7: PASS (no change needed) | B7: =COUNTIFS(QA_Detail!$B$2:$B$988,"InternVL",QA_Detail!$L$2:$L$988,"PASS") -> 18 | C7: =COUNTIFS(QA_Detail!$B$2:$B$988,"Qwen2.5-VL",QA_Detail!$L$2:$L$988,"PASS") -> 104 | D7: =COUNTIFS(QA_Detail!$B$2:$B$988,"*",QA_Detail!$L$2:$L$988,"PASS") -> 122 | E7: Correct answer, correct category, no edits
A8: REVISE | B8: =COUNTIFS(QA_Detail!$B$2:$B$988,"InternVL",QA_Detail!$L$2:$L$988,"REVISE") -> 423 | C8: =COUNTIFS(QA_Detail!$B$2:$B$988,"Qwen2.5-VL",QA_Detail!$L$2:$L$988,"REVISE") -> 365 | D8: =COUNTIFS(QA_Detail!$B$2:$B$988,"*",QA_Detail!$L$2:$L$988,"REVISE") -> 788 | E8: Grounded in the page but needs a fix (value, period, unit, wording or category label)
A9: DISCARD | B9: =COUNTIFS(QA_Detail!$B$2:$B$988,"InternVL",QA_Detail!$L$2:$L$988,"DISCARD") -> 54 | C9: =COUNTIFS(QA_Detail!$B$2:$B$988,"Qwen2.5-VL",QA_Detail!$L$2:$L$988,"DISCARD") -> 23 | D9: =COUNTIFS(QA_Detail!$B$2:$B$988,"*",QA_Detail!$L$2:$L$988,"DISCARD") -> 77 | E9: Hallucinated: question AND answer not in the document
A10: Content correct | B10: =COUNTIFS(QA_Detail!$B$2:$B$988,"InternVL",QA_Detail!$R$2:$R$988,"Y") -> 64 | C10: =COUNTIFS(QA_Detail!$B$2:$B$988,"Qwen2.5-VL",QA_Detail!$R$2:$R$988,"Y") -> 232 | D10: =COUNTIFS(QA_Detail!$B$2:$B$988,"*",QA_Detail!$R$2:$R$988,"Y") -> 296 | E10: Answer factually right (only label/typo/format issues allowed)
A11: QA Accuracy | B11: =IFERROR(B10/B6,0) -> 0.12929293 | C11: =IFERROR(C10/C6,0) -> 0.47154472 | D11: =IFERROR(D10/D6,0) -> 0.29989868 | E11: % QA whose answer is factually correct from the start (ignores category label / typo / format fixes)
A12: Revision Rate | B12: =IFERROR(B8/B6,0) -> 0.85454545 | C12: =IFERROR(C8/C6,0) -> 0.74186992 | D12: =IFERROR(D8/D6,0) -> 0.79837893 | E12: % QA that need revision = REVISE / N
A13: Discard Rate | B13: =IFERROR(B9/B6,0) -> 0.10909091 | C13: =IFERROR(C9/C6,0) -> 0.046747967 | D13: =IFERROR(D9/D6,0) -> 0.078014184 | E13: % QA discarded (hallucinated) = DISCARD / N
A14: First Pass Yield (FPY) | B14: =IFERROR(B7/B6,0) -> 0.036363636 | C14: =IFERROR(C7/C6,0) -> 0.21138211 | D14: =IFERROR(D7/D6,0) -> 0.12360689 | E14: % QA that pass with zero revision of any kind (strict) = PASS / N
A15: Error Rate | B15: =IFERROR((B8+B9)/B6,0) -> 0.96363636 | C15: =IFERROR((C8+C9)/C6,0) -> 0.78861789 | D15: =IFERROR((D8+D9)/D6,0) -> 0.87639311 | E15: % QA with at least one error = (REVISE + DISCARD) / N = 1 − FPY
A16: Factual Error Rate | B16: =1-B11 -> 0.87070707 | C16: =1-C11 -> 0.52845528 | D16: =1-D11 -> 0.70010132 | E16: % QA with a content error (1 − Accuracy)
A17: Category label correct | B17: =IFERROR(COUNTIFS(QA_Detail!$B$2:$B$988,"InternVL",QA_Detail!$P$2:$P$988,"Y")/B6,0) -> 0.34343434 | C17: =IFERROR(COUNTIFS(QA_Detail!$B$2:$B$988,"Qwen2.5-VL",QA_Detail!$P$2:$P$988,"Y")/C6,0) -> 0.3699187 | D17: =IFERROR(COUNTIFS(QA_Detail!$B$2:$B$988,"*",QA_Detail!$P$2:$P$988,"Y")/D6,0) -> 0.35663627 | E17: % QA whose assigned category matches the evidence/task
A19: Error Severity
A20: Severity | B20: InternVL | C20: Qwen2.5-VL | D20: Overall | E20: % of all QA (Overall) | F20: InternVL % | G20: Qwen2.5-VL % | H20: Meaning
A21: Minor | B21: =COUNTIFS(QA_Detail!$B$2:$B$988,"InternVL",QA_Detail!$M$2:$M$988,"Minor") -> 108 | C21: =COUNTIFS(QA_Detail!$B$2:$B$988,"Qwen2.5-VL",QA_Detail!$M$2:$M$988,"Minor") -> 208 | D21: =COUNTIFS(QA_Detail!$B$2:$B$988,"*",QA_Detail!$M$2:$M$988,"Minor") -> 316 | E21: =IFERROR(D21/$D$6,0) -> 0.32016211 | F21: =IFERROR(B21/$B$6,0) -> 0.21818182 | G21: =IFERROR(C21/$C$6,0) -> 0.42276423 | H21: REVISE: core fact right; small fix (wording, unit label, period framing, category label, typo)
A22: Major | B22: =COUNTIFS(QA_Detail!$B$2:$B$988,"InternVL",QA_Detail!$M$2:$M$988,"Major") -> 315 | C22: =COUNTIFS(QA_Detail!$B$2:$B$988,"Qwen2.5-VL",QA_Detail!$M$2:$M$988,"Major") -> 157 | D22: =COUNTIFS(QA_Detail!$B$2:$B$988,"*",QA_Detail!$M$2:$M$988,"Major") -> 472 | E22: =IFERROR(D22/$D$6,0) -> 0.47821682 | F22: =IFERROR(B22/$B$6,0) -> 0.63636364 | G22: =IFERROR(C22/$C$6,0) -> 0.31910569 | H22: REVISE: key fact wrong (number / entity / period / direction / calculation) but question answerable from page
A23: Critical | B23: =COUNTIFS(QA_Detail!$B$2:$B$988,"InternVL",QA_Detail!$M$2:$M$988,"Critical") -> 54 | C23: =COUNTIFS(QA_Detail!$B$2:$B$988,"Qwen2.5-VL",QA_Detail!$M$2:$M$988,"Critical") -> 23 | D23: =COUNTIFS(QA_Detail!$B$2:$B$988,"*",QA_Detail!$M$2:$M$988,"Critical") -> 77 | E23: =IFERROR(D23/$D$6,0) -> 0.078014184 | F23: =IFERROR(B23/$B$6,0) -> 0.10909091 | G23: =IFERROR(C23/$C$6,0) -> 0.046747967 | H23: DISCARD: hallucinated, not grounded in page
A26: Error Type (primary = main reason; any = QA containing that error at all)
A27: Error Type | B27: InternVL (primary) | C27: Qwen2.5-VL (primary) | D27: Overall (primary) | E27: InternVL (any) | F27: Qwen2.5-VL (any) | G27: Overall (any) | H27: % of QA with this error (Overall)
A28: Hallucination | B28: =COUNTIFS(QA_Detail!$B$2:$B$988,"InternVL",QA_Detail!$N$2:$N$988,"Hallucination") -> 54 | C28: =COUNTIFS(QA_Detail!$B$2:$B$988,"Qwen2.5-VL",QA_Detail!$N$2:$N$988,"Hallucination") -> 23 | D28: =COUNTIFS(QA_Detail!$B$2:$B$988,"*",QA_Detail!$N$2:$N$988,"Hallucination") -> 77 | E28: =COUNTIFS(QA_Detail!$B$2:$B$988,"InternVL",QA_Detail!$Y$2:$Y$988,1) -> 55 | F28: =COUNTIFS(QA_Detail!$B$2:$B$988,"Qwen2.5-VL",QA_Detail!$Y$2:$Y$988,1) -> 23 | G28: =COUNTIFS(QA_Detail!$B$2:$B$988,"*",QA_Detail!$Y$2:$Y$988,1) -> 78 | H28: =IFERROR(G28/$D$6,0) -> 0.079027356
A29: Factual/Numerical | B29: =COUNTIFS(QA_Detail!$B$2:$B$988,"InternVL",QA_Detail!$N$2:$N$988,"Factual/Numerical") -> 234 | C29: =COUNTIFS(QA_Detail!$B$2:$B$988,"Qwen2.5-VL",QA_Detail!$N$2:$N$988,"Factual/Numerical") -> 84 | D29: =COUNTIFS(QA_Detail!$B$2:$B$988,"*",QA_Detail!$N$2:$N$988,"Factual/Numerical") -> 318 | E29: =COUNTIFS(QA_Detail!$B$2:$B$988,"InternVL",QA_Detail!$Z$2:$Z$988,1) -> 273 | F29: =COUNTIFS(QA_Detail!$B$2:$B$988,"Qwen2.5-VL",QA_Detail!$Z$2:$Z$988,1) -> 110 | G29: =COUNTIFS(QA_Detail!$B$2:$B$988,"*",QA_Detail!$Z$2:$Z$988,1) -> 383 | H29: =IFERROR(G29/$D$6,0) -> 0.38804458
A30: Calculation | B30: =COUNTIFS(QA_Detail!$B$2:$B$988,"InternVL",QA_Detail!$N$2:$N$988,"Calculation") -> 8 | C30: =COUNTIFS(QA_Detail!$B$2:$B$988,"Qwen2.5-VL",QA_Detail!$N$2:$N$988,"Calculation") -> 10 | D30: =COUNTIFS(QA_Detail!$B$2:$B$988,"*",QA_Detail!$N$2:$N$988,"Calculation") -> 18 | E30: =COUNTIFS(QA_Detail!$B$2:$B$988,"InternVL",QA_Detail!$AA$2:$AA$988,1) -> 30 | F30: =COUNTIFS(QA_Detail!$B$2:$B$988,"Qwen2.5-VL",QA_Detail!$AA$2:$AA$988,1) -> 16 | G30: =COUNTIFS(QA_Detail!$B$2:$B$988,"*",QA_Detail!$AA$2:$AA$988,1) -> 46 | H30: =IFERROR(G30/$D$6,0) -> 0.046605876
A31: Reasoning | B31: =COUNTIFS(QA_Detail!$B$2:$B$988,"InternVL",QA_Detail!$N$2:$N$988,"Reasoning") -> 46 | C31: =COUNTIFS(QA_Detail!$B$2:$B$988,"Qwen2.5-VL",QA_Detail!$N$2:$N$988,"Reasoning") -> 34 | D31: =COUNTIFS(QA_Detail!$B$2:$B$988,"*",QA_Detail!$N$2:$N$988,"Reasoning") -> 80 | E31: =COUNTIFS(QA_Detail!$B$2:$B$988,"InternVL",QA_Detail!$AB$2:$AB$988,1) -> 107 | F31: =COUNTIFS(QA_Detail!$B$2:$B$988,"Qwen2.5-VL",QA_Detail!$AB$2:$AB$988,1) -> 52 | G31: =COUNTIFS(QA_Detail!$B$2:$B$988,"*",QA_Detail!$AB$2:$AB$988,1) -> 159 | H31: =IFERROR(G31/$D$6,0) -> 0.16109422
A32: Temporal | B32: =COUNTIFS(QA_Detail!$B$2:$B$988,"InternVL",QA_Detail!$N$2:$N$988,"Temporal") -> 37 | C32: =COUNTIFS(QA_Detail!$B$2:$B$988,"Qwen2.5-VL",QA_Detail!$N$2:$N$988,"Temporal") -> 17 | D32: =COUNTIFS(QA_Detail!$B$2:$B$988,"*",QA_Detail!$N$2:$N$988,"Temporal") -> 54 | E32: =COUNTIFS(QA_Detail!$B$2:$B$988,"InternVL",QA_Detail!$AC$2:$AC$988,1) -> 123 | F32: =COUNTIFS(QA_Detail!$B$2:$B$988,"Qwen2.5-VL",QA_Detail!$AC$2:$AC$988,1) -> 35 | G32: =COUNTIFS(QA_Detail!$B$2:$B$988,"*",QA_Detail!$AC$2:$AC$988,1) -> 158 | H32: =IFERROR(G32/$D$6,0) -> 0.16008105
A33: Unit | B33: =COUNTIFS(QA_Detail!$B$2:$B$988,"InternVL",QA_Detail!$N$2:$N$988,"Unit") -> 4 | C33: =COUNTIFS(QA_Detail!$B$2:$B$988,"Qwen2.5-VL",QA_Detail!$N$2:$N$988,"Unit") -> 5 | D33: =COUNTIFS(QA_Detail!$B$2:$B$988,"*",QA_Detail!$N$2:$N$988,"Unit") -> 9 | E33: =COUNTIFS(QA_Detail!$B$2:$B$988,"InternVL",QA_Detail!$AD$2:$AD$988,1) -> 61 | F33: =COUNTIFS(QA_Detail!$B$2:$B$988,"Qwen2.5-VL",QA_Detail!$AD$2:$AD$988,1) -> 43 | G33: =COUNTIFS(QA_Detail!$B$2:$B$988,"*",QA_Detail!$AD$2:$AD$988,1) -> 104 | H33: =IFERROR(G33/$D$6,0) -> 0.10536981
A34: Incomplete | B34: =COUNTIFS(QA_Detail!$B$2:$B$988,"InternVL",QA_Detail!$N$2:$N$988,"Incomplete") -> 11 | C34: =COUNTIFS(QA_Detail!$B$2:$B$988,"Qwen2.5-VL",QA_Detail!$N$2:$N$988,"Incomplete") -> 28 | D34: =COUNTIFS(QA_Detail!$B$2:$B$988,"*",QA_Detail!$N$2:$N$988,"Incomplete") -> 39 | E34: =COUNTIFS(QA_Detail!$B$2:$B$988,"InternVL",QA_Detail!$AE$2:$AE$988,1) -> 54 | F34: =COUNTIFS(QA_Detail!$B$2:$B$988,"Qwen2.5-VL",QA_Detail!$AE$2:$AE$988,1) -> 62 | G34: =COUNTIFS(QA_Detail!$B$2:$B$988,"*",QA_Detail!$AE$2:$AE$988,1) -> 116 | H34: =IFERROR(G34/$D$6,0) -> 0.11752786
A35: Instruction-following | B35: =COUNTIFS(QA_Detail!$B$2:$B$988,"InternVL",QA_Detail!$N$2:$N$988,"Instruction-following") -> 41 | C35: =COUNTIFS(QA_Detail!$B$2:$B$988,"Qwen2.5-VL",QA_Detail!$N$2:$N$988,"Instruction-following") -> 157 | D35: =COUNTIFS(QA_Detail!$B$2:$B$988,"*",QA_Detail!$N$2:$N$988,"Instruction-following") -> 198 | E35: =COUNTIFS(QA_Detail!$B$2:$B$988,"InternVL",QA_Detail!$AF$2:$AF$988,1) -> 279 | F35: =COUNTIFS(QA_Detail!$B$2:$B$988,"Qwen2.5-VL",QA_Detail!$AF$2:$AF$988,1) -> 296 | G35: =COUNTIFS(QA_Detail!$B$2:$B$988,"*",QA_Detail!$AF$2:$AF$988,1) -> 575 | H35: =IFERROR(G35/$D$6,0) -> 0.58257345
A36: Format | B36: =COUNTIFS(QA_Detail!$B$2:$B$988,"InternVL",QA_Detail!$N$2:$N$988,"Format") -> 6 | C36: =COUNTIFS(QA_Detail!$B$2:$B$988,"Qwen2.5-VL",QA_Detail!$N$2:$N$988,"Format") -> 5 | D36: =COUNTIFS(QA_Detail!$B$2:$B$988,"*",QA_Detail!$N$2:$N$988,"Format") -> 11 | E36: =COUNTIFS(QA_Detail!$B$2:$B$988,"InternVL",QA_Detail!$AG$2:$AG$988,1) -> 35 | F36: =COUNTIFS(QA_Detail!$B$2:$B$988,"Qwen2.5-VL",QA_Detail!$AG$2:$AG$988,1) -> 34 | G36: =COUNTIFS(QA_Detail!$B$2:$B$988,"*",QA_Detail!$AG$2:$AG$988,1) -> 69 | H36: =IFERROR(G36/$D$6,0) -> 0.069908815
A37: Typo/Grammar | B37: =COUNTIFS(QA_Detail!$B$2:$B$988,"InternVL",QA_Detail!$N$2:$N$988,"Typo/Grammar") -> 36 | C37: =COUNTIFS(QA_Detail!$B$2:$B$988,"Qwen2.5-VL",QA_Detail!$N$2:$N$988,"Typo/Grammar") -> 25 | D37: =COUNTIFS(QA_Detail!$B$2:$B$988,"*",QA_Detail!$N$2:$N$988,"Typo/Grammar") -> 61 | E37: =COUNTIFS(QA_Detail!$B$2:$B$988,"InternVL",QA_Detail!$AH$2:$AH$988,1) -> 198 | F37: =COUNTIFS(QA_Detail!$B$2:$B$988,"Qwen2.5-VL",QA_Detail!$AH$2:$AH$988,1) -> 100 | G37: =COUNTIFS(QA_Detail!$B$2:$B$988,"*",QA_Detail!$AH$2:$AH$988,1) -> 298 | H37: =IFERROR(G37/$D$6,0) -> 0.30192503
A38: Total QA with errors | B38: =SUM(B28:B37) -> 477 | C38: =SUM(C28:C37) -> 388 | D38: =SUM(D28:D37) -> 865
A39: Primary counts sum to REVISE+DISCARD; "any" counts overlap because one QA can carry several errors.

Sheet QA_Detail
A1: QA_ID | B1: Model | C1: Document | D1: Page | E1: Image File | F1: Gen Idx | G1: Assigned Category | H1: Modality | I1: Question | J1: Answer | K1: Answer Type | L1: Verdict | M1: Severity | N1: Primary Error Type | O1: All Error Types | P1: Category Correct | Q1: Suggested Category | R1: Content Correct | S1: Discard Reason | T1: Discard Answer Basis | U1: Evidence on Page | V1: Reviewer Explanation | W1: Corrected Question | X1: Corrected Answer | Y1: ERR: Hallucination | Z1: ERR: Factual/Numerical | AA1: ERR: Calculation | AB1: ERR: Reasoning | AC1: ERR: Temporal | AD1: ERR: Unit | AE1: ERR: Incomplete | AF1: ERR: Instruction-following | AG1: ERR: Format | AH1: ERR: Typo/Grammar
A2: QA0001 | B2: InternVL | C2: KERProvinsiKalimantanTengahTriwulanIV2012 | D2: 13 | E2: 8dabadfb728f43cf89fe3bf6bb7614a3KERProvinsiKalimantanTengahTriwulanIV2012_p013.png | F2: 0 | G2: Text-Text Inference | H2: Text | I2: Bagaimana kondisi umum ekspor di Kalimantan Tengah selama periode 2005-2012? | J2: Ekspor di Kalimantan Tengah selama periode 2005-2012 meningkat dari 33,64 miliar rupiah pada tahun 2005 menjadi 55,38 miliar rupiah pada tahun 2012. | K2: pendek | L2: REVISE | M2: Major | N2: Factual/Numerical | O2: Factual/Numerical, Unit, Instruction-following | P2: N | Q2: Table-Comparison and Sorting | R2: N | U2: Tabel 1.1: Ekspor share of PDRB 33,64% (2005) -> 42,61% (2012); 55,38 is Impor 2011. Values are % shares, not miliar rupiah. | V2: 2012 value wrong (55,38 is Impor 2011), unit wrong (% share not miliar rupiah), and evidence is in the table, not text. | X2: Pangsa ekspor terhadap PDRB Kalimantan Tengah meningkat dari 33,64% pada tahun 2005 menjadi 42,61% pada tahun 2012 (sempat mencapai 44,56% pada 2011). | Y2: 0 | Z2: 1 | AA2: 0 | AB2: 0 | AC2: 0 | AD2: 1 | AE2: 0 | AF2: 1 | AG2: 0 | AH2: 0
A3: QA0002 | B3: InternVL | C3: KERProvinsiKalimantanTengahTriwulanIV2012 | D3: 13 | E3: 8dabadfb728f43cf89fe3bf6bb7614a3KERProvinsiKalimantanTengahTriwulanIV2012_p013.png | F3: 1 | G3: Chart-Numerical Calculation | H3: Chart | I3: Bagaimana pertumbuhan ekonomi di Kalimantan Tengah selama periode 2005-2012? | J3: Pertumbuhan ekonomi di Kalimantan Tengah selama periode 2005-2012 mencapai 6,62% (yoy). | K3: panjang | L3: REVISE | M3: Minor | N3: Temporal | O3: Temporal, Instruction-following | P3: N | Q3: Text-Text Inference | R3: N | U3: Text: ekonomi Kalteng triwulan IV-2012 tumbuh 6,62% (yoy), melambat dari 7,14% periode lalu. No chart on page. | V3: 6,62% yoy is Tw IV-2012 growth, not 2005-2012; page has no chart so Chart-Numerical Calculation label is wrong. | W3: Bagaimana pertumbuhan ekonomi Kalimantan Tengah pada triwulan IV-2012? | X3: Perekonomian Kalimantan Tengah pada triwulan IV-2012 tumbuh 6,62% (yoy), melambat dibanding periode sebelumnya yang tumbuh 7,14%. | Y3: 0 | Z3: 0 | AA3: 0 | AB3: 0 | AC3: 1 | AD3: 0 | AE3: 0 | AF3: 1 | AG3: 0 | AH3: 0
A4: QA0003 | B4: InternVL | C4: KERProvinsiKalimantanTengahTriwulanIV2012 | D4: 13 | E4: 8dabadfb728f43cf89fe3bf6bb7614a3KERProvinsiKalimantanTengahTriwulanIV2012_p013.png | F4: 2 | G4: Chart-Time-Sensitive | H4: Chart | I4: Bagaimana pertumbuhan investasi di Kalimantan Tengah selama periode 2005-2012? | J4: Investasi di Kalimantan Tengah selama periode 2005-2012 meningkat dari 5,56 miliar rupiah pada tahun 2005 menjadi 27,99 miliar rupiah pada tahun 2012. | K4: pendek | L4: REVISE | M4: Major | N4: Factual/Numerical | O4: Factual/Numerical, Unit, Instruction-following | P4: N | Q4: Table-Comparison and Sorting | R4: N | U4: Tabel 1.1: Pembentukan Modal Tetap Bruto (investasi) share 35,91% (2005) -> 46,44% (2012). 27,99 is Pertanian 2012. No chart. | V4: Values wrong (5,56 and 27,99 are not investment figures), unit should be % share of PDRB, and data is from a table not a chart. | X4: Pangsa investasi (PMTB) terhadap PDRB Kalimantan Tengah meningkat dari 35,91% pada tahun 2005 menjadi 46,44% pada tahun 2012. | Y4: 0 | Z4: 1 | AA4: 0 | AB4: 0 | AC4: 0 | AD4: 1 | AE4: 0 | AF4: 1 | AG4: 0 | AH4: 0
A5: QA0004 | B5: InternVL | C5: KERProvinsiKalimantanTengahTriwulanIV2012 | D5: 16 | E5: 8dabadfb728f43cf89fe3bf6bb7614a3KERProvinsiKalimantanTengahTriwulanIV2012_p016.png | F5: 0 | G5: Text-Text Inference | H5: Text | I5: Bagaimana kinerja kredit konsumsi lainnya pada tahun 2011? | J5: Kredit konsumsi lainnya meningkat 4,867 miliar rupiah | K5: pendek | L5: REVISE | M5: Major | N5: Factual/Numerical | O5: Factual/Numerical, Unit, Reasoning, Instruction-following | P5: N | Q5: Chart-Time-Sensitive | R5: N | U5: Grafik 1.3 (%yoy): Kredit Konsumsi Lainnya ~34% (Jan-2011), ~27% until Jul-2011, dropped to ~10% in Aug and ~10-13% to Dec-2011. No 4,867 miliar anywhere. | V5: The series exists only in Grafik 1.3 as % yoy growth; the answer's 4,867 miliar is fabricated with wrong unit, and growth actually slowed during 2011. Evidence is chart, not text. | X5: Pertumbuhan kredit konsumsi lainnya melambat sepanjang 2011, dari sekitar 34% (yoy) di awal tahun, stabil sekitar 27% hingga Juli, lalu turun ke kisaran 10-13% (yoy) sejak Agustus hingga akhir 2011. | Y5: 0 | Z5: 1 | AA5: 0 | AB5: 1 | AC5: 0 | AD5: 1 | AE5: 0 | AF5: 1 | AG5: 0 | AH5: 0
A6: QA0005 | B6: InternVL | C6: KERProvinsiKalimantanTengahTriwulanIV2012 | D6: 16 | E6: 8dabadfb728f43cf89fe3bf6bb7614a3KERProvinsiKalimantanTengahTriwulanIV2012_p016.png | F6: 1 | G6: Chart-Numerical Calculation | H6: Chart | I6: Bagaimana kontribusi K/L pada tahun 2011? | J6: K/L mengkontribusi 97% dari total anggaran belanja | K6: panjang | L6: REVISE | M6: Minor | N6: Temporal | O6: Temporal, Instruction-following | P6: N | Q6: Text-Text Inference | R6: N | U6: Text & Tabel 1.3: Anggaran K/L terealisasi Rp4,74 triliun atau sekitar 97% dari total anggaran belanja pusat untuk K/L di Kalteng, at Tw IV-2012 (2012 Q4). No 2011 K/L figure. | V6: 97% is K/L budget realization in Q4 2012, not 2011 and not a 'contribution'; no chart or calculation involved. | W6: Berapa realisasi anggaran K/L (APBN) di Kalimantan Tengah pada triwulan IV 2012? | X6: Anggaran K/L terealisasi sebesar Rp4,74 triliun atau sekitar 97% dari total anggaran belanja pusat yang dialokasikan untuk Kementerian dan Lembaga di Kalimantan Tengah. | Y6: 0 | Z6: 0 | AA6: 0 | AB6: 0 | AC6: 1 | AD6: 0 | AE6: 0 | AF6: 1 | AG6: 0 | AH6: 0
A7: QA0006 | B7: InternVL | C7: KERProvinsiKalimantanTengahTriwulanIV2012 | D7: 16 | E7: 8dabadfb728f43cf89fe3bf6bb7614a3KERProvinsiKalimantanTengahTriwulanIV2012_p016.png | F7: 2 | G7: Chart-Time-Sensitive | H7: Chart | I7: Bagaimana pertumbuhan investasi fisik pada tahun 2011? | J7: Investasi fisik meningkat 4,26% | K7: pendek | L7: REVISE | M7: Major | N7: Factual/Numerical | O7: Factual/Numerical, Temporal, Instruction-following | P7: N | Q7: Text-Text Inference | R7: N | U7: Text 1.2.2: PMTB tumbuh 17,59% (Tw IV-2012), up from 10,55% (yoy) in Tw III; contribution rose from 4,26% to 7,54%. No 2011 data; no chart on investment. | V7: 4,26% is the Tw III-2012 contribution to growth, not investment growth, and not 2011. Evidence is running text, not a chart. | W7: Bagaimana pertumbuhan investasi fisik (PMTB) Kalimantan Tengah pada triwulan IV 2012? | X7: Investasi PMTB tumbuh 17,59% (yoy), lebih tinggi dari triwulan III sebesar 10,55% (yoy), dengan kontribusi pertumbuhan meningkat dari 4,26% menjadi 7,54%. | Y7: 0 | Z7: 1 | AA7: 0 | AB7: 0 | AC7: 1 | AD7: 0 | AE7: 0 | AF7: 1 | AG7: 0 | AH7: 0
A8: QA0007 | B8: InternVL | C8: KERProvinsiKalimantanTengahTriwulanIV2012 | D8: 17 | E8: 8dabadfb728f43cf89fe3bf6bb7614a3KERProvinsiKalimantanTengahTriwulanIV2012_p017.png | F8: 0 | G8: Text-Text Inference | H8: Text | I8: Bagaimana perubahan ekspor di Kalimantan Tengah selama periode IV-2012? | J8: Ekspor di Kalimantan Tengah selama periode IV-2012 meningkat 43,5% dari tahun sebelumnya. | K8: pendek | L8: REVISE | M8: Major | N8: Reasoning | O8: Reasoning | P8: Y | Q8: Text-Text Inference | R8: N | U8: Text: transaksi ekspor luar negeri Tw IV-2012 US$211,38 juta atau turun 43,5% (yoy). | V8: Magnitude 43,5% is right but direction is wrong: exports fell (turun), not rose. | X8: Ekspor luar negeri Kalimantan Tengah pada triwulan IV-2012 sebesar US$211,38 juta atau turun 43,5% (yoy). | Y8: 0 | Z8: 0 | AA8: 0 | AB8: 1 | AC8: 0 | AD8: 0 | AE8: 0 | AF8: 0 | AG8: 0 | AH8: 0
A9: QA0008 | B9: InternVL | C9: KERProvinsiKalimantanTengahTriwulanIV2012 | D9: 17 | E9: 8dabadfb728f43cf89fe3bf6bb7614a3KERProvinsiKalimantanTengahTriwulanIV2012_p017.png | F9: 1 | G9: Chart-Numerical Calculation | H9: Chart | I9: Bagaimana perubahan import di Kalimantan Tengah selama periode IV-2012? | J9: Import di Kalimantan Tengah selama periode IV-2012 meningkat 143,1% dari tahun sebelumnya. | K9: pendek | L9: REVISE | M9: Major | N9: Factual/Numerical | O9: Factual/Numerical, Reasoning, Instruction-following | P9: N | Q9: Text-Text Inference | R9: N | U9: Text: pertumbuhan impor menurun dari 313,9% menjadi -36,0% (US$29,71 juta); volume impor turun dari 143,1% menjadi -61,7%. | V9: 143,1% is the previous-quarter volume growth; in Tw IV-2012 imports contracted (-36,0% value, -61,7% volume). Info is from text, not a chart calculation. | X9: Impor Kalimantan Tengah pada triwulan IV-2012 menurun: pertumbuhan nilai impor turun dari 313,9% menjadi -36,0% (total US$29,71 juta) dan volume impor turun dari 143,1% menjadi -61,7%. | Y9: 0 | Z9: 1 | AA9: 0 | AB9: 1 | AC9: 0 | AD9: 0 | AE9: 0 | AF9: 1 | AG9: 0 | AH9: 0
A10: QA0009 | B10: InternVL | C10: KERProvinsiKalimantanTengahTriwulanIV2012 | D10: 17 | E10: 8dabadfb728f43cf89fe3bf6bb7614a3KERProvinsiKalimantanTengahTriwulanIV2012_p017.png | F10: 2 | G10: Chart-Information Extraction | H10: Chart | I10: Bagaimana perubahan kredit investasi di Kalimantan Tengah selama periode IV-2012? | J10: Kredit investasi di Kalimantan Tengah selama periode IV-2012 meningkat 58% dari tahun sebelumnya. | K10: panjang | L10: REVISE | M10: Major | N10: Factual/Numerical | O10: Factual/Numerical | P10: Y | Q10: Chart-Information Extraction | R10: N | U10: Grafik 1.8: kredit investasi Tw IV-2012 ~Rp5,3 triliun (naik dari ~Rp4,7 triliun); garis rata-rata tahunan ~15%. | V10: No 58% growth shown; chart shows credit rising to ~Rp5,3 triliun with growth line around ~15% in Tw IV-2012. | X10: Kredit investasi perbankan Kalimantan Tengah pada triwulan IV-2012 meningkat menjadi sekitar Rp5,3 triliun (dari sekitar Rp4,7 triliun pada triwulan III), dengan pertumbuhan sekitar 15%. | Y10: 0 | Z10: 1 | AA10: 0 | AB10: 0 | AC10: 0 | AD10: 0 | AE10: 0 | AF10: 0 | AG10: 0 | AH10: 0
A11: QA0010 | B11: InternVL | C11: KERProvinsiKalimantanTengahTriwulanIV2012 | D11: 19 | E11: 8dabadfb728f43cf89fe3bf6bb7614a3KERProvinsiKalimantanTengahTriwulanIV2012_p019.png | F11: 0 | G11: Chart-Time-Sensitive | H11: Chart | I11: Bagaimana perubahan ekspor batubara di Kalimantan selama periode 2011 dan 2012? | J11: Ekspor batubara di Kalimantan meningkat dari 328 ton pada tahun 2011 menjadi 548 ribu pada tahun 2012. | K11: pendek | L11: REVISE | M11: Minor | N11: Instruction-following | O11: Instruction-following, Unit, Incomplete | P11: N | Q11: Text-Text Inference | R11: N | U11: Text: rata-rata ekspor 3 perusahaan (AKT, Merunda Graha Mineral, Multi Tambang Jaya Utama) 2012 diestimasi 548 ribu ton vs 2011 tercatat 328 ton. | V11: Values match text but they are avg exports of 3 large companies in Kalteng (not all Kalimantan), unit 'ton' missing after 548 ribu, and source is paragraph not chart. | W11: Bagaimana perubahan rata-rata ekspor batubara dari 3 perusahaan besar di Kalimantan Tengah pada tahun 2011 dan 2012? | X11: Rata-rata ekspor dari 3 perusahaan besar (PT Asmin Koalindo Tuhup, Merunda Graha Mineral, dan Multi Tambang Jaya Utama) meningkat dari 328 ton (sebagaimana tertulis) pada tahun 2011 menjadi sekitar 548 ribu ton pada tahun 2012. | Y11: 0 | Z11: 0 | AA11: 0 | AB11: 0 | AC11: 0 | AD11: 1 | AE11: 1 | AF11: 1 | AG11: 0 | AH11: 0
A12: QA0011 | B12: InternVL | C12: KERProvinsiKalimantanTengahTriwulanIV2012 | D12: 19 | E12: 8dabadfb728f43cf89fe3bf6bb7614a3KERProvinsiKalimantanTengahTriwulanIV2012_p019.png | F12: 1 | G12: Chart-Numerical Calculation | H12: Chart | I12: Bagaimana kontribusi ekspor batubara ke China di tahun 2011 dan 2012? | J12: Pada tahun 2011, kontribusi ekspor batubara ke China adalah 38,1%, dan pada tahun 2012, menjadi 41,8%. | K12: panjang | L12: REVISE | M12: Major | N12: Factual/Numerical | O12: Factual/Numerical, Instruction-following | P12: N | Q12: Text-Text Inference | R12: N | U12: Text: ekspor ke Jepang 2011 38,1%, ke China 28,5%; 2012 (Jan-Sep) Jepang 29,2%, China 41,8% dari total ekspor batubara Kalteng. | V12: China 2011 share is 28,5%, not 38,1% (that is Jepang). Shares are stated in text, no calculation from chart. | X12: Kontribusi ekspor batubara ke China sebesar 28,5% dari total ekspor batubara Kalteng pada tahun 2011 dan meningkat menjadi 41,8% pada tahun 2012 (Jan-Sep). | Y12: 0 | Z12: 1 | AA12: 0 | AB12: 0 | AC12: 0 | AD12: 0 | AE12: 0 | AF12: 1 | AG12: 0 | AH12: 0
A13: QA0012 | B13: InternVL | C13: KERProvinsiKalimantanTengahTriwulanIV2012 | D13: 19 | E13: 8dabadfb728f43cf89fe3bf6bb7614a3KERProvinsiKalimantanTengahTriwulanIV2012_p019.png | F13: 2 | G13: Chart-Information Extraction | H13: Chart | I13: Bagaimana perubahan ekspor batubara dari India, Jepang, dan China pada tahun 2011? | J13: Pada tahun 2011, India, Jepang, dan China mengkontribusi sebesar-besarnya ke ekspor batubara di Kalimantan, dengan India 38,1%, Jepang 28,5%, dan China 41,8%. | K13: pendek | L13: REVISE | M13: Major | N13: Factual/Numerical | O13: Factual/Numerical, Typo/Grammar, Instruction-following | P13: N | Q13: Text-Text Inference | R13: N | U13: Text: 2011 share Jepang 38,1%, China 28,5%; India only described as cenderung stabil (no share). 41,8% is China 2012. | V13: Shares misattributed: Jepang 38,1%, China 28,5% in 2011; 41,8% is China 2012; no India share on page. Question says 'ekspor dari' countries (they are destinations). | W13: Berapa kontribusi ekspor batubara Kalteng ke Jepang dan China pada tahun 2011, dan bagaimana ekspor ke India? | X13: Pada tahun 2011, ekspor batubara ke Jepang mencapai 38,1% dan ke China 28,5% dari total ekspor batubara Kalteng, sedangkan ekspor ke India cenderung stabil. | Y13: 0 | Z13: 1 | AA13: 0 | AB13: 0 | AC13: 0 | AD13: 0 | AE13: 0 | AF13: 1 | AG13: 0 | AH13: 1
A14: QA0013 | B14: InternVL | C14: KERProvinsiKalimantanTengahTriwulanIV2012 | D14: 21 | E14: 8dabadfb728f43cf89fe3bf6bb7614a3KERProvinsiKalimantanTengahTriwulanIV2012_p021.png | F14: 0 | G14: Chart-Numerical Calculation | H14: Chart | I14: Bagaimana kontribusi PDRB pada sektor pertamanya di periode ini? | J14: Kontribusi PDRB sektor pertamanya adalah 0.79% | K14: pendek | L14: REVISE | M14: Minor | N14: Instruction-following | O14: Instruction-following, Typo/Grammar | P14: N | Q14: Text-Text Inference | R14: Y | U14: Tabel 1.4 Kontribusi Pertanian IV-12 = 0.79; text: sumbangan pertanian turun dari 1,98% menjadi 0,79%. No chart on page. | V14: Value 0.79% is correct for Pertanian (first sector) in Tw IV-2012, but no chart/calculation involved (table/text lookup) and 'sektor pertamanya' is garbled. | W14: Berapa kontribusi (sumbangan pertumbuhan) sektor pertanian terhadap PDRB Kalimantan Tengah pada triwulan IV-2012? | X14: Sumbangan sektor pertanian terhadap pertumbuhan PDRB pada triwulan IV-2012 sebesar 0,79%, turun dari 1,98% pada triwulan sebelumnya. | Y14: 0 | Z14: 0 | AA14: 0 | AB14: 0 | AC14: 0 | AD14: 0 | AE14: 0 | AF14: 1 | AG14: 0 | AH14: 1
A15: QA0014 | B15: InternVL | C15: KERProvinsiKalimantanTengahTriwulanIV2012 | D15: 21 | E15: 8dabadfb728f43cf89fe3bf6bb7614a3KERProvinsiKalimantanTengahTriwulanIV2012_p021.png | F15: 1 | G15: Chart-Information Extraction | H15: Chart | I15: Bagaimana pertumbuhan produk di Kalimantan Tengah selama periode ini? | J15: Pertumbuhan produk di Kalimantan Tengah selama periode ini adalah 2,88% | K15: panjang | L15: REVISE | M15: Major | N15: Factual/Numerical | O15: Factual/Numerical, Instruction-following, Typo/Grammar | P15: N | Q15: Table-Comparison and Sorting | R15: N | U15: Tabel 1.4: PDRB Kalteng growth IV-12 = 6.62 (III-12 7.14). 2.88 is Pertanian growth IV-12. No chart. | V15: Kalteng (PDRB) growth in Tw IV-2012 is 6,62%, not 2,88% (that is the agriculture sector). Question vague ('produk'); data from table not chart; pure lookup has no exact label. | W15: Berapa pertumbuhan PDRB Kalimantan Tengah pada triwulan IV-2012? | X15: PDRB Kalimantan Tengah tumbuh 6,62% (yoy) pada triwulan IV-2012, melambat dari 7,14% pada triwulan III-2012. | Y15: 0 | Z15: 1 | AA15: 0 | AB15: 0 | AC15: 0 | AD15: 0 | AE15: 0 | AF15: 1 | AG15: 0 | AH15: 1
A16: QA0015 | B16: InternVL | C16: KERProvinsiKalimantanTengahTriwulanIV2012 | D16: 21 | E16: 8dabadfb728f43cf89fe3bf6bb7614a3KERProvinsiKalimantanTengahTriwulanIV2012_p021.png | F16: 2 | G16: Text-Text Inference | H16: Text | I16: Bagaimana pertumbuhan produk di sektor pertamanya di periode ini dibandingkan dengan sektor lainnya? | J16: Pertumbuhan produk di sektor pertamanya lebih rendah dibandingkan dengan sektor lainnya | K16: pendek | L16: REVISE | M16: Minor | N16: Reasoning | O16: Reasoning, Instruction-following, Typo/Grammar | P16: N | Q16: Table-Comparison and Sorting | R16: N | U16: Tabel 1.4 growth IV-12: Pertanian 2.88; Industri pengolahan 1.04 (lower); others 4.48-15.36; PDRB 6.62. | V16: Pertanian growth (2,88%) is lower than PDRB and most sectors but not all: Industri pengolahan (1,04%) is lower. Comparison uses table, not text. | W16: Bagaimana pertumbuhan sektor pertanian pada triwulan IV-2012 dibandingkan sektor lainnya? | X16: Pertumbuhan sektor pertanian (2,88%) lebih rendah dibanding PDRB (6,62%) dan sebagian besar sektor lain, namun masih di atas sektor industri pengolahan (1,04%). | Y16: 0 | Z16: 0 | AA16: 0 | AB16: 1 | AC16: 0 | AD16: 0 | AE16: 0 | AF16: 1 | AG16: 0 | AH16: 1
A17: QA0016 | B17: InternVL | C17: KERProvinsiKalimantanTengahTriwulanIV2012 | D17: 38 | E17: 8dabadfb728f43cf89fe3bf6bb7614a3KERProvinsiKalimantanTengahTriwulanIV2012_p038.png | F17: 0 | G17: Chart-Numerical Calculation | H17: Chart | I17: Bagaimana perubahan nilai Pertumbuhan Dana Pihak Ketiga (DPK) di Kota Palangka Raya selama periode IV-2012? | J17: Pertumbuhan Dana Pihak Ketiga (DPK) meningkat dari 18,47% menjadi 19,80% | K17: pendek | L17: REVISE | M17: Major | N17: Reasoning | O17: Reasoning, Factual/Numerical, Instruction-following | P17: N | Q17: Text-Text Inference | R17: N | U17: Text 3.1.3: DPK Kalteng Tw IV-2012 tumbuh 19,80% (yoy), melambat dari 28,15% periode sebelumnya; 18,47% adalah rata-rata historis 5 tahun. No chart. | V17: Growth slowed (28,15% -> 19,80%), not increased; 18,47% is the 5-year average. Data is for Kalteng province, not Kota Palangka Raya. No chart on page; evidence is text. | W17: Bagaimana perubahan pertumbuhan Dana Pihak Ketiga (DPK) perbankan Kalimantan Tengah pada triwulan IV-2012? | X17: Pertumbuhan DPK melambat dari 28,15% pada periode sebelumnya menjadi 19,80% (yoy) pada triwulan IV-2012, meskipun masih di atas rata-rata historis 5 tahun sebesar 18,47%. | Y17: 0 | Z17: 1 | AA17: 0 | AB17: 1 | AC17: 0 | AD17: 0 | AE17: 0 | AF17: 1 | AG17: 0 | AH17: 0
A18: QA0017 | B18: InternVL | C18: KERProvinsiKalimantanTengahTriwulanIV2012 | D18: 38 | E18: 8dabadfb728f43cf89fe3bf6bb7614a3KERProvinsiKalimantanTengahTriwulanIV2012_p038.png | F18: 1 | G18: Chart-Time-Sensitive | H18: Chart | I18: Bagaimana perubahan nilai Pertumbuhan Dana Jenis Tabungan (DPK) di Kota Palangka Raya selama periode IV-2012? | J18: Pertumbuhan Dana Jenis Tabungan meningkat dari 54,5% menjadi 54,7% | K18: panjang | L18: REVISE | M18: Major | N18: Factual/Numerical | O18: Factual/Numerical, Reasoning, Instruction-following | P18: N | Q18: Text-Text Inference | R18: N | U18: Text: pertumbuhan dana jenis tabungan melambat dari 21,9% menjadi 19,9%; 54,5% is tabungan share of DPK (Tabel 3.3: 54,4% Des-11, 54,5% Des-12). Kalteng, no chart. | V18: 54,5% is the composition share, not growth; 54,7% does not exist. Tabungan growth slowed 21,9% -> 19,9%. Entity is Kalteng not Palangka Raya. No chart. | W18: Bagaimana perubahan pertumbuhan dana jenis tabungan perbankan Kalimantan Tengah pada triwulan IV-2012? | X18: Pertumbuhan dana jenis tabungan melambat dari 21,9% menjadi 19,9%, disebabkan turunnya porsi tabungan sektor swasta. | Y18: 0 | Z18: 1 | AA18: 0 | AB18: 1 | AC18: 0 | AD18: 0 | AE18: 0 | AF18: 1 | AG18: 0 | AH18: 0
A19: QA0018 | B19: InternVL | C19: KERProvinsiKalimantanTengahTriwulanIV2012 | D19: 38 | E19: 8dabadfb728f43cf89fe3bf6bb7614a3KERProvinsiKalimantanTengahTriwulanIV2012_p038.png | F19: 2 | G19: Text-Text Inference | H19: Text | I19: Bagaimana perubahan nilai Pertumbuhan Dana Deposito di Kota Palangka Raya selama periode IV-2012? | J19: Pertumbuhan Dana Deposito meningkat dari 17,8% menjadi 18,0% | K19: pendek | L19: REVISE | M19: Major | N19: Factual/Numerical | O19: Factual/Numerical, Reasoning | P19: Y | Q19: Text-Text Inference | R19: N | U19: Text: deposito tumbuh 6,43% (yoy) pada Tw IV-2012 vs 8,31% di Tw III; 17,8% is deposito share of DPK. | V19: Deposito growth slowed from 8,31% to 6,43% yoy; answer uses composition share 17,8% and invented 18,0% with wrong direction. Entity is Kalteng, not Palangka Raya. | W19: Bagaimana perubahan pertumbuhan deposito perbankan Kalimantan Tengah pada triwulan IV-2012? | X19: Pertumbuhan deposito melambat dari 8,31% (yoy) pada triwulan III menjadi 6,43% (yoy) pada triwulan IV-2012. | Y19: 0 | Z19: 1 | AA19: 0 | AB19: 1 | AC19: 0 | AD19: 0 | AE19: 0 | AF19: 0 | AG19: 0 | AH19: 0
A20: QA0019 | B20: InternVL | C20: KERProvinsiKalimantanTengahTriwulanIV2012 | D20: 40 | E20: 8dabadfb728f43cf89fe3bf6bb7614a3KERProvinsiKalimantanTengahTriwulanIV2012_p040.png | F20: 0 | G20: Chart-Time-Sensitive | H20: Chart | I20: Bagaimana perubahan kredit ekonomi selama periode IV-2012? | J20: Kredit ekonomi meningkat sebesar 29,46% selama periode IV-2012 | K20: pendek | L20: REVISE | M20: Major | N20: Factual/Numerical | O20: Factual/Numerical, Typo/Grammar, Instruction-following | P20: N | Q20: Text-Text Inference | R20: N | U20: No 29,46% on page. Text: kredit perdagangan tumbuh 40,30% (rata-rata historis 29,26%), jasa-jasa 77,46%, modal kerja 46,37% (yoy) Tw IV-2012. | V20: 'Kredit ekonomi' is vague; 29,46% not on page (likely misread of 29,26%, the historical average of perdagangan credit). Sector growth figures come from text, not chart. | W20: Berapa pertumbuhan kredit sektor perdagangan di Kalteng pada triwulan IV-2012? | X20: Kredit sektor perdagangan tumbuh 40,30% (yoy) pada triwulan IV-2012, di atas rata-rata historisnya sebesar 29,26%. | Y20: 0 | Z20: 1 | AA20: 0 | AB20: 0 | AC20: 0 | AD20: 0 | AE20: 0 | AF20: 1 | AG20: 0 | AH20: 1
A21: QA0020 | B21: InternVL | C21: KERProvinsiKalimantanTengahTriwulanIV2012 | D21: 40 | E21: 8dabadfb728f43cf89fe3bf6bb7614a3KERProvinsiKalimantanTengahTriwulanIV2012_p040.png | F21: 1 | G21: Chart-Numerical Calculation | H21: Chart | I21: Bagaimana perubahan kredit konsumsi selama periode IV-2012? | J21: Kredit konsumsi meningkat 40,30% selama periode IV-2012 | K21: panjang | L21: REVISE | M21: Major | N21: Factual/Numerical | O21: Factual/Numerical, Instruction-following | P21: N | Q21: Chart-Time-Sensitive | R21: N | U21: 40,30% is kredit sektor perdagangan (text). Grafik 3.4: kredit konsumsi relatif konstan ~20-25% yoy; text: pertumbuhan kredit konsumsi relatif konstan. | V21: Wrong series: 40,30% belongs to perdagangan credit. Consumption credit growth is described as relatively constant (~24% yoy at end of Grafik 3.4). No calculation involved. | X21: Pertumbuhan kredit konsumsi relatif konstan (sekitar 20-25% yoy pada Grafik 3.4), sehingga pangsa kredit konsumsi kembali dominan pada periode laporan. | Y21: 0 | Z21: 1 | AA21: 0 | AB21: 0 | AC21: 0 | AD21: 0 | AE21: 0 | AF21: 1 | AG21: 0 | AH21: 0
A22: QA0021 | B22: InternVL | C22: KERProvinsiKalimantanTengahTriwulanIV2012 | D22: 40 | E22: 8dabadfb728f43cf89fe3bf6bb7614a3KERProvinsiKalimantanTengahTriwulanIV2012_p040.png | F22: 2 | G22: Text-Text Inference | H22: Text | I22: Bagaimana kredit modal terhadap kredit investasi selama periode IV-2012? | J22: Kredit modal lebih tinggi dibandingkan kredit investasi selama periode IV-2012 | K22: pendek | L22: REVISE | M22: Minor | N22: Typo/Grammar | O22: Typo/Grammar, Incomplete | P22: Y | Q22: Text-Text Inference | R22: N | U22: Text: kredit modal kerja tumbuh 46,37% (yoy) Tw IV-2012; kredit investasi semakin melambat hingga Tw IV-2012. Grafik 3.4 confirms modal kerja ~45% vs investasi ~0%. | V22: Core comparison right (modal kerja growth higher than investasi), but question is garbled ('kredit modal', unclear if level or growth) and answer lacks supporting figure. | W22: Bagaimana pertumbuhan kredit modal kerja dibandingkan kredit investasi pada triwulan IV-2012? | X22: Pertumbuhan kredit modal kerja lebih tinggi, yaitu 46,37% (yoy), sementara pertumbuhan kredit investasi semakin melambat hingga triwulan IV-2012. | Y22: 0 | Z22: 0 | AA22: 0 | AB22: 0 | AC22: 0 | AD22: 0 | AE22: 1 | AF22: 0 | AG22: 0 | AH22: 1
A23: QA0022 | B23: InternVL | C23: KERProvinsiKalimantanTengahTriwulanIV2012 | D23: 42 | E23: 8dabadfb728f43cf89fe3bf6bb7614a3KERProvinsiKalimantanTengahTriwulanIV2012_p042.png | F23: 0 | G23: Text-Text Inference | H23: Text | I23: Kapital umum KER pada periode IV-2012 berapa? | J23: Rp 3,38 triliun | K23: pendek | L23: REVISE | M23: Minor | N23: Typo/Grammar | O23: Typo/Grammar | P23: Y | Q23: Text-Text Inference | R23: Y | U23: Text: penyaluran kredit UMKM Tw IV-2012 tercatat Rp3,38 triliun (23,7% dari total kredit perbankan). | V23: Value Rp3,38 triliun is correct for UMKM credit, but question is garbled ('Kapital umum KER') and does not name UMKM credit. | W23: Berapa penyaluran kredit UMKM di Kalimantan Tengah pada triwulan IV-2012? | X23: Rp3,38 triliun | Y23: 0 | Z23: 0 | AA23: 0 | AB23: 0 | AC23: 0 | AD23: 0 | AE23: 0 | AF23: 0 | AG23: 0 | AH23: 1
A24: QA0023 | B24: InternVL | C24: KERProvinsiKalimantanTengahTriwulanIV2012 | D24: 42 | E24: 8dabadfb728f43cf89fe3bf6bb7614a3KERProvinsiKalimantanTengahTriwulanIV2012_p042.png | F24: 1 | G24: Table-Numerical Calculation | H24: Table | I24: Bagaimana berubah kredit umum KER dari periode IV-2011 hingga IV-2012? | J24: Kredit umum KER meningkat dari 2,612,917 juta menjadi 3,387,552 juta | K24: panjang | L24: REVISE | M24: Minor | N24: Typo/Grammar | O24: Typo/Grammar, Incomplete | P24: Y | Q24: Table-Numerical Calculation | R24: N | U24: Tabel 3.5 Kredit UMKM (Rp juta): Tw IV-2011 2,612,917; Tw IV-2012 3,387,552 (growth 29,65% yoy, also in text). | V24: Values correct but question garbled ('kredit umum KER' = kredit UMKM), unit label incomplete (Rp juta), and no growth computed despite calculation category. | W24: Bagaimana perubahan kredit UMKM Kalimantan Tengah dari Tw IV-2011 ke Tw IV-2012? | X24: Kredit UMKM meningkat dari Rp2.612.917 juta (Tw IV-2011) menjadi Rp3.387.552 juta (Tw IV-2012), tumbuh sekitar 29,65% (yoy). | Y24: 0 | Z24: 0 | AA24: 0 | AB24: 0 | AC24: 0 | AD24: 0 | AE24: 1 | AF24: 0 | AG24: 0 | AH24: 1
A25: QA0024 | B25: InternVL | C25: KERProvinsiKalimantanTengahTriwulanIV2012 | D25: 42 | E25: 8dabadfb728f43cf89fe3bf6bb7614a3KERProvinsiKalimantanTengahTriwulanIV2012_p042.png | F25: 2 | G25: Chart-Information Extraction | H25: Chart | I25: Persentase pertumbuhan kredit umum KER hingga IV-2012 berapa? | J25: 23,7% | K25: pendek | L25: REVISE | M25: Major | N25: Factual/Numerical | O25: Factual/Numerical, Instruction-following, Typo/Grammar | P25: N | Q25: Text-Text Inference | R25: N | U25: Text: pertumbuhan kredit UMKM meningkat dari 26,17% menjadi 29,65% (yoy); 23,7% is pangsa kredit UMKM to total kredit. | V25: 23,7% is the share of UMKM credit in total bank credit, not growth; growth is 29,65% yoy. No chart on page (text/table). | W25: Berapa pertumbuhan kredit UMKM Kalimantan Tengah pada triwulan IV-2012? | X25: 29,65% (yoy), meningkat dari 26,17% pada triwulan sebelumnya. | Y25: 0 | Z25: 1 | AA25: 0 | AB25: 0 | AC25: 0 | AD25: 0 | AE25: 0 | AF25: 1 | AG25: 0 | AH25: 1
A26: QA0025 | B26: InternVL | C26: KERProvinsiKalimantanTengahTriwulanIV2012 | D26: 44 | E26: 8dabadfb728f43cf89fe3bf6bb7614a3KERProvinsiKalimantanTengahTriwulanIV2012_p044.png | F26: 0 | G26: Chart-Time-Sensitive | H26: Chart | I26: Bagaimana perubahan jumlah uang yang masuk ke Bank Indonesia selama periode 2007-2012? | J26: Jumlah uang yang masuk ke Bank Indonesia meningkat dari 2007 hingga 2012, dengan kemampuan tertinggi di tahun 2011. | K26: pendek | L26: DISCARD | M26: Critical | N26: Hallucination | O26: Hallucination | P26: N | Q26: Chart-Time-Sensitive | R26: N | S26: Period/time comparison not on page | T26: Fabricated value/claim (not on page) | U26: Page charts only PTTB (Rp miliar) and Rasio PTTB thd Inflow (Grafik 3.10); inflow amounts are not shown anywhere. | V26: Inflow values for 2007-2012 are not on the page; the claimed rise peaking in 2011 has no support. | Y26: 1 | Z26: 0 | AA26: 0 | AB26: 0 | AC26: 0 | AD26: 0 | AE26: 0 | AF26: 0 | AG26: 0 | AH26: 0
A27: QA0026 | B27: InternVL | C27: KERProvinsiKalimantanTengahTriwulanIV2012 | D27: 44 | E27: 8dabadfb728f43cf89fe3bf6bb7614a3KERProvinsiKalimantanTengahTriwulanIV2012_p044.png | F27: 1 | G27: Chart-Numerical Calculation | H27: Chart | I27: Bagaimana perubahan rasio PTBT terhadap inflow selama periode 2007-2012? | J27: Rasio PTBT terhadap inflow meningkat dari 2007 hingga 2012, dengan kemampuan tertinggi di tahun 2011. | K27: panjang | L27: REVISE | M27: Major | N27: Reasoning | O27: Reasoning, Instruction-following, Typo/Grammar | P27: N | Q27: Chart-Time-Sensitive | R27: N | U27: Grafik 3.10: ratio fluctuates, ~7,5% (Tw I-2007), peaks ~26% Tw II-2007 and ~30% Tw IV-2011, drops to ~1% Tw II-2012, ~4% Tw IV-2012. | V27: The ratio did not rise steadily; it fluctuated and ended 2012 below 2007. Peak in 2011 (Tw IV) is right. It is a trend question, not a calculation. 'PTBT' is a typo. | W27: Bagaimana perubahan rasio PTTB terhadap inflow selama periode 2007-2012? | X27: Rasio PTTB terhadap inflow berfluktuasi selama 2007-2012, dengan puncak tertinggi sekitar 30% pada triwulan IV-2011, lalu turun tajam menjadi sekitar 1% pada triwulan II-2012 dan sekitar 4% pada triwulan IV-2012. | Y27: 0 | Z27: 0 | AA27: 0 | AB27: 1 | AC27: 0 | AD27: 0 | AE27: 0 | AF27: 1 | AG27: 0 | AH27: 1
A28: QA0027 | B28: InternVL | C28: KERProvinsiKalimantanTengahTriwulanIV2012 | D28: 44 | E28: 8dabadfb728f43cf89fe3bf6bb7614a3KERProvinsiKalimantanTengahTriwulanIV2012_p044.png | F28: 2 | G28: Chart-Information Extraction | H28: Chart | I28: Bagaimana perubahan jumlah uang yang dijelajahi oleh Bank Indonesia selama periode 2007-2012? | J28: Jumlah uang yang dijelajahi oleh Bank Indonesia meningkat dari 2007 hingga 2012, dengan kemampuan tertinggi di tahun 2011. | K28: pendek | L28: DISCARD | M28: Critical | N28: Hallucination | O28: Hallucination, Typo/Grammar | P28: N | Q28: Chart-Information Extraction | R28: N | S28: Garbled/unintelligible question | T28: Non-answer (no factual content) | U28: The page has no 'uang yang dijelajahi' metric; charts show PTTB and ratio/growth of PTTB. | V28: The question is garbled ('dijelajahi') and refers to no metric on the page; the answer is boilerplate with no support. | Y28: 1 | Z28: 0 | AA28: 0 | AB28: 0 | AC28: 0 | AD28: 0 | AE28: 0 | AF28: 0 | AG28: 0 | AH28: 1
A29: QA0028 | B29: InternVL | C29: KERProvinsiKalimantanTengahTriwulanIV2012 | D29: 47 | E29: 8dabadfb728f43cf89fe3bf6bb7614a3KERProvinsiKalimantanTengahTriwulanIV2012_p047.png | F29: 0 | G29: Text-Text Inference | H29: Text | I29: Bagaimana hasil kontribusi anggaran pemerintah pada tahun 2011 dan 2012? | J29: Kontribusi anggaran pemerintah pada tahun 2011 sebesar 528,49 miliar, pada tahun 2012 sebesar 528,49 miliar | K29: pendek | L29: REVISE | M29: Major | N29: Factual/Numerical | O29: Factual/Numerical, Temporal, Typo/Grammar, Instruction-following | P29: N | Q29: Table-Comparison and Sorting | R29: N | U29: Tabel 4.1: Surplus/(Defisit) 2011 (581.246) juta, 2012 (528.494) juta; text: defisit 2012 Rp528,49 miliar. | V29: Vague 'kontribusi anggaran pemerintah'; 528,49 miliar is the 2012 deficit only, 2011 deficit was Rp581,25 miliar. Same value for both years is wrong; data is from table. | W29: Berapa defisit APBD Kalimantan Tengah pada tahun 2011 dan 2012? | X29: Defisit APBD Kalimantan Tengah sebesar Rp581,25 miliar pada tahun 2011 dan Rp528,49 miliar pada tahun 2012. | Y29: 0 | Z29: 1 | AA29: 0 | AB29: 0 | AC29: 1 | AD29: 0 | AE29: 0 | AF29: 1 | AG29: 0 | AH29: 1
A30: QA0029 | B30: InternVL | C30: KERProvinsiKalimantanTengahTriwulanIV2012 | D30: 47 | E30: 8dabadfb728f43cf89fe3bf6bb7614a3KERProvinsiKalimantanTengahTriwulanIV2012_p047.png | F30: 1 | G30: Chart-Numerical Calculation | H30: Chart | I30: Bagaimana berlakulah pengeluaran APBD pada tahun 2011 dan 2012? | J30: Pada tahun 2011, pengeluaran APBD sebesar 47,42 miliar, pada tahun 2012, sebesar 47,42 miliar | K30: panjang | L30: REVISE | M30: Major | N30: Factual/Numerical | O30: Factual/Numerical, Temporal, Typo/Grammar, Instruction-following | P30: N | Q30: Table-Comparison and Sorting | R30: N | U30: Tabel 4.1 Total Belanja: 10.103.457 juta (2011), 11.603.391 juta (2012); 47,42 miliar = hasil pengelolaan kekayaan daerah 2012 (text). | V30: 47,42 miliar is not APBD expenditure; total belanja was Rp10,10 T (2011) and Rp11,60 T (2012). Garbled question; no chart on page. | W30: Berapa total belanja APBD Kalimantan Tengah pada tahun 2011 dan 2012? | X30: Total belanja APBD Kalimantan Tengah sebesar Rp10,10 triliun (Rp10.103.457 juta) pada 2011 dan Rp11,60 triliun (Rp11.603.391 juta) pada 2012. | Y30: 0 | Z30: 1 | AA30: 0 | AB30: 0 | AC30: 1 | AD30: 0 | AE30: 0 | AF30: 1 | AG30: 0 | AH30: 1
A31: QA0030 | B31: InternVL | C31: KERProvinsiKalimantanTengahTriwulanIV2012 | D31: 47 | E31: 8dabadfb728f43cf89fe3bf6bb7614a3KERProvinsiKalimantanTengahTriwulanIV2012_p047.png | F31: 2 | G31: Chart-Information Extraction | H31: Chart | I31: Bagaimana berlakulah keuangan daerah pada tahun 2011 dan 2012? | J31: Pada tahun 2011, keuangan daerah sebesar 126,6 miliar, pada tahun 2012, sebesar 126,6 miliar | K31: pendek | L31: REVISE | M31: Major | N31: Factual/Numerical | O31: Factual/Numerical, Typo/Grammar, Temporal, Instruction-following | P31: N | Q31: Table-Comparison and Sorting | R31: N | U31: Text: retribusi daerah 2012 Rp126,6 miliar (no 2011 value). Tabel 4.1 Total Pendapatan 9.522.211 juta (2011), 11.074.897 juta (2012). | V31: Question garbled/vague; 126,6 miliar is only the 2012 retribusi target, repeated for 2011. No chart. Rewritten as total pendapatan from Tabel 4.1. | W31: Berapa total pendapatan APBD Kalimantan Tengah pada tahun 2011 dan 2012? | X31: Total pendapatan APBD Kalimantan Tengah sebesar Rp9,52 triliun (Rp9.522.211 juta) pada 2011 dan Rp11,07 triliun (Rp11.074.897 juta) pada 2012. | Y31: 0 | Z31: 1 | AA31: 0 | AB31: 0 | AC31: 1 | AD31: 0 | AE31: 0 | AF31: 1 | AG31: 0 | AH31: 1
A32: QA0031 | B32: InternVL | C32: KERProvinsiKalimantanTengahTriwulanIV2012 | D32: 53 | E32: 8dabadfb728f43cf89fe3bf6bb7614a3KERProvinsiKalimantanTengahTriwulanIV2012_p053.png | F32: 0 | G32: Text-Text Inference | H32: Text | I32: Bagaimana kondisi kesejahteraan masyarakat Kaliemantan Tengah pada bulan Desember 2012? | J32: Kondisi kesejahteraan masyarakat Kaliemantan Tengah pada bulan Desember 2012 meningkat sekitar 98,66% dibandingkan bulan sebelumnya. | K32: pendek | L32: REVISE | M32: Major | N32: Reasoning | O32: Reasoning, Factual/Numerical, Unit, Typo/Grammar | P32: Y | Q32: Text-Text Inference | R32: N | U32: Text: Indeks NTP Desember 2012 sebesar 98,66, lebih rendah dari triwulan sebelumnya 98,95; kesejahteraan petani menurun. | V32: Direction wrong (welfare fell, not rose) and 98,66 is the NTP index level, not a % increase. 'Kaliemantan' typo. | W32: Bagaimana kondisi kesejahteraan petani Kalimantan Tengah pada bulan Desember 2012? | X32: Kesejahteraan petani menurun; indeks NTP Desember 2012 tercatat 98,66, lebih rendah dari triwulan sebelumnya (98,95) dan masih berada di area defisit (<100). | Y32: 0 | Z32: 1 | AA32: 0 | AB32: 1 | AC32: 0 | AD32: 1 | AE32: 0 | AF32: 0 | AG32: 0 | AH32: 1
A33: QA0032 | B33: InternVL | C33: KERProvinsiKalimantanTengahTriwulanIV2012 | D33: 53 | E33: 8dabadfb728f43cf89fe3bf6bb7614a3KERProvinsiKalimantanTengahTriwulanIV2012_p053.png | F33: 1 | G33: Chart-Time-Sensitive | H33: Chart | I33: Bagaimana perubahan kesejahteraan masyarakat Kaliemantan Tengah selama periode tiga tahun terakhir? | J33: Kesejahteraan masyarakat Kaliemantan Tengah meningkat sekitar 0,1% setiap tahun selama periode tiga tahun terakhir. | K33: panjang | L33: REVISE | M33: Major | N33: Factual/Numerical | O33: Temporal, Factual/Numerical, Instruction-following, Typo/Grammar | P33: N | Q33: Text-Text Inference | R33: N | U33: Text: dalam 10 tahun terakhir laju pertumbuhan ekonomi naik 4,91% -> 6,26% (rata-rata 0,1%/tahun); persentase penduduk miskin turun rata-rata 0,54%/tahun. | V33: 0,1% per year refers to economic growth over 10 years, not welfare over 3 years; evidence is text, not chart. | W33: Bagaimana perubahan kesejahteraan masyarakat Kalimantan Tengah dalam 10 tahun terakhir? | X33: Kesejahteraan membaik: persentase penduduk miskin turun rata-rata 0,54% per tahun (dari hampir 12% pada 2003 menjadi 6,51% pada Maret 2012), seiring pertumbuhan ekonomi yang naik dari 4,91% menjadi 6,26%. | Y33: 0 | Z33: 1 | AA33: 0 | AB33: 0 | AC33: 1 | AD33: 0 | AE33: 0 | AF33: 1 | AG33: 0 | AH33: 1
A34: QA0033 | B34: InternVL | C34: KERProvinsiKalimantanTengahTriwulanIV2012 | D34: 53 | E34: 8dabadfb728f43cf89fe3bf6bb7614a3KERProvinsiKalimantanTengahTriwulanIV2012_p053.png | F34: 2 | G34: Table-Numerical Calculation | H34: Table | I34: Bagaimana kesejahteraan masyarakat Kaliemantan Tengah pada bulan Desember 2011? | J34: Kesejahteraan masyarakat Kaliemantan Tengah pada bulan Desember 2011 adalah 98,95. | K34: pendek | L34: DISCARD | M34: Critical | N34: Hallucination | O34: Hallucination, Temporal | P34: N | Q34: Table-Comparison and Sorting | R34: N | S34: Period/time comparison not on page | T34: Borrowed value from another metric on the page | U34: Tabel 5.2 only covers Jun-12, Sep-12, Des-12; NTP Sep-12 = 98,95. No December 2011 data on page. | V34: December 2011 NTP/welfare is not on the page; 98,95 is Sep-12 value. | Y34: 1 | Z34: 0 | AA34: 0 | AB34: 0 | AC34: 1 | AD34: 0 | AE34: 0 | AF34: 0 | AG34: 0 | AH34: 0
A35: QA0034 | B35: InternVL | C35: Buletin - Beyond Infinity Edisi Desember 2025 | D35: 9 | E35: Buletin 20- 20Beyond 20Infinity 20Edisi 20Desember 202025_p009.png | F35: 0 | G35: Text-Text Inference | H35: Text | I35: Mengapa ada banyak kapal di luar pantai? | J35: Untuk mendukung industri minyak dan gas | K35: pendek | L35: DISCARD | M35: Critical | N35: Hallucination | O35: Hallucination | P35: N | Q35: Text-Text Inference | R35: N | S35: False premise / speculation | T35: Fabricated value/claim (not on page) | U35: Page is a photo of an offshore rig with two supply boats plus 'Inspirasi' (book list) and 'Penulis' (author bio) boxes; no text explains the ships. | V35: No text on the page explains why ships are offshore; the answer is speculation from the photo, not grounded in document content. | Y35: 1 | Z35: 0 | AA35: 0 | AB35: 0 | AC35: 0 | AD35: 0 | AE35: 0 | AF35: 0 | AG35: 0 | AH35: 0
A36: QA0035 | B36: InternVL | C36: Buletin - Beyond Infinity Edisi Desember 2025 | D36: 9 | E36: Buletin 20- 20Beyond 20Infinity 20Edisi 20Desember 202025_p009.png | F36: 1 | G36: Chart-Information Extraction | H36: Chart | I36: Bagaimana industri minyak dan gas menghubungkan dengan ekonomi Indonesia? | J36: Industri minyak dan gas memberikan kontribusi besar untuk pembangunan ekonomi Indonesia, termasuk melalui pembangunan daerah dan pembangunan teknologi. | K36: panjang | L36: DISCARD | M36: Critical | N36: Hallucination | O36: Hallucination, Instruction-following | P36: N | Q36: Text-Text Inference | R36: N | S36: Metric/topic not on page | T36: Fabricated value/claim (not on page) | U36: No chart and no text about the oil and gas industry's contribution to the Indonesian economy; only a photo, book list and author bio. | V36: Topic (oil & gas contribution to regional/technology development) is not on the page; there is no chart either. | Y36: 1 | Z36: 0 | AA36: 0 | AB36: 0 | AC36: 0 | AD36: 0 | AE36: 0 | AF36: 1 | AG36: 0 | AH36: 0
A37: QA0036 | B37: InternVL | C37: Buletin - Beyond Infinity Edisi Desember 2025 | D37: 9 | E37: Buletin 20- 20Beyond 20Infinity 20Edisi 20Desember 202025_p009.png | F37: 2 | G37: Chart-Numerical Calculation | H37: Chart | I37: Penggunaan kapal di luar pantai berdasarkan dokumen? | J37: Dokumen tidak menyediakan informasi numerik | K37: pendek | L37: DISCARD | M37: Critical | N37: Hallucination | O37: Hallucination, Typo/Grammar, Instruction-following | P37: N | Q37: Text-Text Inference | R37: N | S37: Garbled/unintelligible question | T37: Non-answer (no factual content) | U37: No chart or numeric data on ship usage; page has only a photo, book list and author bio. | V37: Garbled question about ship usage has no grounding; no chart or numbers exist, answer is a non-answer. | Y37: 1 | Z37: 0 | AA37: 0 | AB37: 0 | AC37: 0 | AD37: 0 | AE37: 0 | AF37: 1 | AG37: 0 | AH37: 1
A38: QA0037 | B38: InternVL | C38: Buletin - Beyond Infinity Edisi Desember 2025 | D38: 21 | E38: Buletin 20- 20Beyond 20Infinity 20Edisi 20Desember 202025_p021.png | F38: 0 | G38: Chart-Information Extraction | H38: Chart | I38: Jumlah penyelenggaran ITSK terdafar pada bulan Juni 2025 berapa? | J38: 30 | K38: pendek | L38: REVISE | M38: Minor | N38: Format | O38: Format, Typo/Grammar | P38: Y | Q38: Chart-Information Extraction | R38: Y | U38: Chart 'Perkembangan Jumlah Penyelenggara ITSK': Terdaftar (yellow) Jun = 30; text: total 30 terdiri dari 10 PKA dan 20 PAJK. | V38: Value 30 is correct, but answer is a bare number without context and question has typos (penyelenggaran, terdafar). | W38: Berapa jumlah penyelenggara ITSK terdaftar pada bulan Juni 2025? | X38: Jumlah penyelenggara ITSK terdaftar pada Juni 2025 sebanyak 30, terdiri dari 10 PKA dan 20 PAJK. | Y38: 0 | Z38: 0 | AA38: 0 | AB38: 0 | AC38: 0 | AD38: 0 | AE38: 0 | AF38: 0 | AG38: 1 | AH38: 1
A39: QA0038 | B39: InternVL | C39: Buletin - Beyond Infinity Edisi Desember 2025 | D39: 21 | E39: Buletin 20- 20Beyond 20Infinity 20Edisi 20Desember 202025_p021.png | F39: 1 | G39: Chart-Time-Sensitive | H39: Chart | I39: Bagaimana perkembangan jumlah penyelenggaran ITSK dari bulan Januari hingga Juni 2025? | J39: Jumlah penyelenggaran ITSK meningkat secara konsisten dari bulan Januari hingga Juni 2025, dengan jumlah terbesar pada bulan Juni 2025. | K39: panjang | L39: PASS | M39: None | N39: None | P39: Y | Q39: Chart-Time-Sensitive | R39: Y | U39: Terdaftar bars Jan-Jun 2025: 17, 21, 26, 28, 29, 30 - rising every month, peak in June. | V39: Consistent increase with maximum in June matches the chart; trend category fits. | Y39: 0 | Z39: 0 | AA39: 0 | AB39: 0 | AC39: 0 | AD39: 0 | AE39: 0 | AF39: 0 | AG39: 0 | AH39: 0
A40: QA0039 | B40: InternVL | C40: Buletin - Beyond Infinity Edisi Desember 2025 | D40: 21 | E40: Buletin 20- 20Beyond 20Infinity 20Edisi 20Desember 202025_p021.png | F40: 2 | G40: Chart-Numerical Calculation | H40: Chart | I40: Bagaimana perkembangan total aset penyelenggaran ITSK terdafar dari bulan Januari hingga November 2025? | J40: Total aset penyelenggaran ITSK terdafar meningkat dari 106,27 juta pada bulan Januari 2025 menjadi 476,15 juta pada bulan November 2025. | K40: pendek | L40: REVISE | M40: Major | N40: Factual/Numerical | O40: Factual/Numerical, Unit, Instruction-following | P40: N | Q40: Chart-Time-Sensitive | R40: N | U40: Total Aset chart (Rp Miliar): PKA 379,47 (Jan) -> 476,15 (Nov); PAJK 106,27 (Jan) -> 185,25 (Nov). | V40: Answer mixes series (106,27 is PAJK Jan, 476,15 is PKA Nov) and uses 'juta' instead of Rp miliar; question is a trend description, not a calculation. | X40: Total aset PKA terdaftar naik dari Rp379,47 miliar (Januari 2025) menjadi Rp476,15 miliar (November 2025), sedangkan total aset PAJK terdaftar naik dari Rp106,27 miliar menjadi Rp185,25 miliar. | Y40: 0 | Z40: 1 | AA40: 0 | AB40: 0 | AC40: 0 | AD40: 1 | AE40: 0 | AF40: 1 | AG40: 0 | AH40: 0
A41: QA0040 | B41: InternVL | C41: Buletin - Beyond Infinity Edisi Desember 2025 | D41: 23 | E41: Buletin 20- 20Beyond 20Infinity 20Edisi 20Desember 202025_p023.png | F41: 0 | G41: Text-Text Inference | H41: Text | I41: Bagaimana jumlah pengguna di DKI Jakarta? | J41: 3,276,235 | K41: pendek | L41: REVISE | M41: Minor | N41: Format | O41: Format | P41: Y | Q41: Text-Text Inference | R41: Y | U41: Text: DKI Jakarta sejumlah 3.276.235 pengguna (20%), data s.d. November 2025. | V41: Value correct, but answer is a bare number with English separators, no unit (pengguna) or period. | W41: Berapa jumlah pengguna Penyelenggara PAJK terdaftar di DKI Jakarta per November 2025? | X41: Jumlah pengguna Penyelenggara PAJK di DKI Jakarta per November 2025 sebanyak 3.276.235 pengguna (20% dari total). | Y41: 0 | Z41: 0 | AA41: 0 | AB41: 0 | AC41: 0 | AD41: 0 | AE41: 0 | AF41: 0 | AG41: 1 | AH41: 0
A42: QA0041 | B42: InternVL | C42: Buletin - Beyond Infinity Edisi Desember 2025 | D42: 23 | E42: Buletin 20- 20Beyond 20Infinity 20Edisi 20Desember 202025_p023.png | F42: 1 | G42: Chart-Numerical Calculation | H42: Chart | I42: Bagaimana berbagi jumlah pengguna antara DKI Jakarta dan Jawa Barat? | J42: DKI Jakarta: 3,276,235 (20%), Jawa Barat: 2,716,659 (17%) | K42: panjang | L42: REVISE | M42: Minor | N42: Instruction-following | O42: Instruction-following, Typo/Grammar | P42: N | Q42: Chart-Information Extraction | R42: Y | U42: Bar chart 'Provinsi dengan Sebaran Pengguna Tertinggi': DKI Jakarta 3.276.235 (20%), Jawa Barat 2.716.659 (17%). | V42: Values correct but no calculation is performed (pure chart reading); question wording 'berbagi' is garbled. | W42: Bagaimana perbandingan jumlah pengguna PAJK antara DKI Jakarta dan Jawa Barat pada November 2025? | X42: DKI Jakarta memiliki 3.276.235 pengguna (20%), sedangkan Jawa Barat 2.716.659 pengguna (17%). | Y42: 0 | Z42: 0 | AA42: 0 | AB42: 0 | AC42: 0 | AD42: 0 | AE42: 0 | AF42: 1 | AG42: 0 | AH42: 1
A43: QA0042 | B43: InternVL | C43: Buletin - Beyond Infinity Edisi Desember 2025 | D43: 23 | E43: Buletin 20- 20Beyond 20Infinity 20Edisi 20Desember 202025_p023.png | F43: 2 | G43: Chart-Information Extraction | H43: Chart | I43: Bagaimana jumlah pengguna di Banten? | J43: 500,948 | K43: pendek | L43: REVISE | M43: Minor | N43: Format | O43: Format | P43: Y | Q43: Chart-Information Extraction | R43: Y | U43: Bar chart and map: Banten 500.948 pengguna (3%), Nov 2025. | V43: Value correct but bare number with English separator and no unit/context. | W43: Berapa jumlah pengguna Penyelenggara PAJK terdaftar di Banten pada November 2025? | X43: Jumlah pengguna PAJK di Banten pada November 2025 sebanyak 500.948 pengguna (3%). | Y43: 0 | Z43: 0 | AA43: 0 | AB43: 0 | AC43: 0 | AD43: 0 | AE43: 0 | AF43: 0 | AG43: 1 | AH43: 0
A44: QA0043 | B44: InternVL | C44: Buletin - Beyond Infinity Edisi Desember 2025 | D44: 24 | E44: Buletin 20- 20Beyond 20Infinity 20Edisi 20Desember 202025_p024.png | F44: 0 | G44: Chart-Numerical Calculation | H44: Chart | I44: Jumlah tenaga kerja PKA dan PJAK terhadap ITSK pada bulan November 2025 berapa? | J44: PAJK: 445, PKA: 117 | K44: pendek | L44: REVISE | M44: Minor | N44: Instruction-following | O44: Instruction-following, Typo/Grammar | P44: N | Q44: Chart-Information Extraction | R44: Y | U44: Bar charts (and side text): Nov 2025 tenaga kerja PKA terdaftar 117, PAJK terdaftar 445. | V44: Values correct, but it is a direct read of the Nov bars (no calculation), so category should be Chart-Information Extraction; 'PJAK' typo and answer lacks context. | W44: Berapa jumlah tenaga kerja penyelenggara ITSK jenis PKA dan PAJK yang terdaftar pada November 2025? | X44: Pada November 2025, tenaga kerja penyelenggara ITSK jenis PKA yang terdaftar sebanyak 117 dan jenis PAJK sebanyak 445. | Y44: 0 | Z44: 0 | AA44: 0 | AB44: 0 | AC44: 0 | AD44: 0 | AE44: 0 | AF44: 1 | AG44: 0 | AH44: 1
A45: QA0044 | B45: InternVL | C45: Buletin - Beyond Infinity Edisi Desember 2025 | D45: 24 | E45: Buletin 20- 20Beyond 20Infinity 20Edisi 20Desember 202025_p024.png | F45: 1 | G45: Text-Text Inference | H45: Text | I45: Banyak aset kripto yang terdaftar di Indonesia pada periode November 2025 berapa? | J45: 25 aset kripto | K45: panjang | L45: REVISE | M45: Major | N45: Factual/Numerical | O45: Factual/Numerical, Instruction-following | P45: N | Q45: Table-Numerical Calculation | R45: N | U45: Table title: '25 Pedagang Aset Keuangan Digital (PAKD)' listing 25 traders (Tokocrypto ... Invest); number of crypto assets not shown. | V45: 25 is the number of registered digital asset traders (PAKD), not crypto assets; page has no count of crypto assets. Evidence is the table (count of rows), not running text. | W45: Berapa jumlah Pedagang Aset Keuangan Digital (PAKD) yang tercantum pada tabel Aktivitas Perdagangan Aset Kripto? | X45: Terdapat 25 Pedagang Aset Keuangan Digital (PAKD). | Y45: 0 | Z45: 1 | AA45: 0 | AB45: 0 | AC45: 0 | AD45: 0 | AE45: 0 | AF45: 1 | AG45: 0 | AH45: 0
A46: QA0045 | B46: InternVL | C46: Buletin - Beyond Infinity Edisi Desember 2025 | D46: 24 | E46: Buletin 20- 20Beyond 20Infinity 20Edisi 20Desember 202025_p024.png | F46: 2 | G46: Chart-Information Extraction | H46: Chart | I46: Tanggal pendaftaran terakhir dari aset kripto Bitwre ada pada bulan November 2025? | J46: S-13/07/2025 | K46: pendek | L46: REVISE | M46: Major | N46: Factual/Numerical | O46: Factual/Numerical, Typo/Grammar, Instruction-following | P46: N | Q46: Table-Comparison and Sorting | R46: N | U46: PAKD table: Bitwyre (PT Teknologi Struktur Berantai, bitwyre.id) SK S-9/D.07/2025; S-13/D.07/2025 belongs to Ajaib Kripto. No registration dates shown. | V46: Wrong row: Bitwyre's SK is S-9/D.07/2025. Question is garbled (asks a date; table only has SK numbers; 'Bitwre' typo). Data is a table, not a chart. | W46: Apa nomor SK untuk pedagang aset kripto Bitwyre pada tabel PAKD? | X46: Nomor SK Bitwyre (PT Teknologi Struktur Berantai) adalah S-9/D.07/2025. | Y46: 0 | Z46: 1 | AA46: 0 | AB46: 0 | AC46: 0 | AD46: 0 | AE46: 0 | AF46: 1 | AG46: 0 | AH46: 1
A47: QA0046 | B47: InternVL | C47: Buletin - Beyond Infinity Edisi Desember 2025 | D47: 25 | E47: Buletin 20- 20Beyond 20Infinity 20Edisi 20Desember 202025_p025.png | F47: 0 | G47: Chart-Time-Sensitive | H47: Chart | I47: Tanggal pembuatan daftar aset kripto pada 2 bulan terakhir 2025? | J47: Tanggal pembuatan daftar aset kripto pada bulan November dan Desember 2025 | K47: pendek | L47: REVISE | M47: Major | N47: Temporal | O47: Temporal, Instruction-following, Typo/Grammar | P47: N | Q47: Text-Text Inference | R47: N | U47: Text: 2 SK Direksi CFX penetapan DAK in November: CFX/DIR-SK/020/XI/2025 (06/11/2025) - 1.307 DAK; CFX/DIR-SK/022/XI/2025 (20/11/2025) - 1.347 DAK. | V47: Both DAK decrees were issued in November 2025 (6 and 20 Nov), not November and December. Info is in text, not chart; question wording garbled. | W47: Kapan 2 Surat Keputusan Direksi CFX tentang Penetapan Daftar Aset Kripto diterbitkan? | X47: Keduanya diterbitkan pada November 2025, yaitu tanggal 6 November 2025 (1.307 DAK) dan 20 November 2025 (1.347 DAK). | Y47: 0 | Z47: 0 | AA47: 0 | AB47: 0 | AC47: 1 | AD47: 0 | AE47: 0 | AF47: 1 | AG47: 0 | AH47: 1
A48: QA0047 | B48: InternVL | C48: Buletin - Beyond Infinity Edisi Desember 2025 | D48: 25 | E48: Buletin 20- 20Beyond 20Infinity 20Edisi 20Desember 202025_p025.png | F48: 1 | G48: Chart-Numerical Calculation | H48: Chart | I48: Jumlah aset kripto pada bulan November 2025? | J48: Jumlah aset kripto pada bulan November 2025 adalah 49,282 Trilun (Ytd) | K48: panjang | L48: REVISE | M48: Major | N48: Factual/Numerical | O48: Factual/Numerical, Instruction-following, Typo/Grammar | P48: N | Q48: Chart-Information Extraction | R48: N | U48: Grafik Nilai Transaksi Aset Kripto: Nov 2025 = 37,2 (Okt 49,29); text: kumulatif Rp449,5282 Triliun (Ytd) hingga Nov 2025. DAK = 1.347. | V48: 49,282 matches nothing; Ytd cumulative is Rp449,5282 triliun and November monthly value is 37,2. Question vague ('jumlah aset kripto'); no calculation needed, so not Numerical Calculation. | W48: Berapa nilai transaksi aset kripto pada bulan November 2025? | X48: Nilai transaksi aset kripto pada November 2025 sebesar Rp37,2 triliun; secara kumulatif mencapai Rp449,5282 triliun (Ytd). | Y48: 0 | Z48: 1 | AA48: 0 | AB48: 0 | AC48: 0 | AD48: 0 | AE48: 0 | AF48: 1 | AG48: 0 | AH48: 1
A49: QA0048 | B49: InternVL | C49: Buletin - Beyond Infinity Edisi Desember 2025 | D49: 25 | E49: Buletin 20- 20Beyond 20Infinity 20Edisi 20Desember 202025_p025.png | F49: 2 | G49: Text-Text Inference | H49: Text | I49: Perubahan aset kripto pada bulan November 2025? | J49: Perubahan aset kripto pada bulan November 2025 adalah -34,633 | K49: pendek | L49: REVISE | M49: Major | N49: Factual/Numerical | O49: Factual/Numerical, Unit, Instruction-following | P49: N | Q49: Chart-Information Extraction | R49: N | U49: Grafik Perubahan Bulanan: Nov = -24,52; Jun = -34,63. Text: nilai transaksi November turun dibanding Oktober. | V49: November monthly change is -24,52 (%), not -34,633 (June value, misread). No unit; evidence is chart, not text. | W49: Berapa perubahan bulanan nilai transaksi aset kripto pada bulan November 2025? | X49: Nilai transaksi aset kripto November 2025 turun 24,52% (mtm), dari Rp49,29 triliun pada Oktober menjadi Rp37,2 triliun. | Y49: 0 | Z49: 1 | AA49: 0 | AB49: 0 | AC49: 0 | AD49: 1 | AE49: 0 | AF49: 1 | AG49: 0 | AH49: 0
A50: QA0049 | B50: InternVL | C50: Buletin - Beyond Infinity Edisi Desember 2025 | D50: 34 | E50: Buletin 20- 20Beyond 20Infinity 20Edisi 20Desember 202025_p034.png | F50: 0 | G50: Chart-Information Extraction | H50: Chart | I50: Bagaimana peringkat syariah Indonesia dijadwalkan? | J50: Indonesia mencapai 64 di jumlah syariah terbanyak | K50: pendek | L50: REVISE | M50: Minor | N50: Typo/Grammar | O50: Typo/Grammar, Incomplete | P50: Y | Q50: Chart-Information Extraction | R50: N | U50: Chart 'Peringkat Negara dengan Jumlah Fintech Syariah Terbanyak': Arab Saudi 72, Indonesia 64 (peringkat 2), Malaysia 58. | V50: Question is garbled ('dijadwalkan'); answer's 64 is correct but should state Indonesia ranks 2nd with 64 fintech syariah. | W50: Berapa jumlah fintech syariah di Indonesia dan di peringkat berapa Indonesia berada? | X50: Indonesia memiliki 64 fintech syariah dan berada di peringkat ke-2 setelah Arab Saudi (72). | Y50: 0 | Z50: 0 | AA50: 0 | AB50: 0 | AC50: 0 | AD50: 0 | AE50: 1 | AF50: 0 | AG50: 0 | AH50: 1
A51: QA0050 | B51: InternVL | C51: Buletin - Beyond Infinity Edisi Desember 2025 | D51: 34 | E51: Buletin 20- 20Beyond 20Infinity 20Edisi 20Desember 202025_p034.png | F51: 1 | G51: Chart-Numerical Calculation | H51: Chart | I51: Bagaimana ekosistem fintech syariah terbait Indonesia | J51: Indonesia mengungkapkan 64 di jumlah ekosistem fintech syariah terbait | K51: panjang | L51: REVISE | M51: Minor | N51: Typo/Grammar | O51: Typo/Grammar, Instruction-following | P51: N | Q51: Chart-Information Extraction | R51: Y | U51: Chart 'Ranking Negara dengan Ekosistem Fintech Syariah Terbaik': Indonesia 64 (listed 3rd after Arab Saudi 72, Malaysia 58). | V51: Value 64 is correct but question/answer are garbled ('terbait', 'mengungkapkan'); no calculation required, so category should be extraction. | W51: Berapa skor Indonesia dalam ranking negara dengan ekosistem fintech syariah terbaik? | X51: Skor Indonesia sebesar 64, di bawah Arab Saudi (72). | Y51: 0 | Z51: 0 | AA51: 0 | AB51: 0 | AC51: 0 | AD51: 0 | AE51: 0 | AF51: 1 | AG51: 0 | AH51: 1
A52: QA0051 | B52: InternVL | C52: Buletin - Beyond Infinity Edisi Desember 2025 | D52: 34 | E52: Buletin 20- 20Beyond 20Infinity 20Edisi 20Desember 202025_p034.png | F52: 2 | G52: Text-Text Inference | H52: Text | I52: Bagaimana pertumbuhan fintech syariah di Indonesia? | J52: Pertumbuhan fintech syariah di Indonesia mencapai 11,4% pada tahun 2025 | K52: pendek | L52: REVISE | M52: Major | N52: Factual/Numerical | O52: Factual/Numerical | P52: Y | Q52: Text-Text Inference | R52: N | U52: Text: pertumbuhan fintech syariah terbanyak kedua di dunia, mengalahkan Malaysia dan UAE; 11,47% is pangsa pasar keuangan syariah per Juni 2025. | V52: 11,4% is misattributed (it's the Islamic finance market share, 11,47%); the page describes fintech syariah growth as the 2nd largest in the world. | X52: Pertumbuhan fintech syariah Indonesia terbanyak kedua di dunia, mengalahkan Malaysia dan UAE (Global Islamic Fintech Report, 2025). | Y52: 0 | Z52: 1 | AA52: 0 | AB52: 0 | AC52: 0 | AD52: 0 | AE52: 0 | AF52: 0 | AG52: 0 | AH52: 0
A53: QA0052 | B53: InternVL | C53: KEKR Provinsi Maluku Utara Mei 2017 | D53: 34 | E53: KEKR 20Provinsi 20Maluku 20Utara 20Mei 202017_p034.png | F53: 0 | G53: Text-Text Inference | H53: Text | I53: Bagaimana pertumbuhan ekonomi di Provinsi Maluku Utara selama periode 2012-2016? | J53: Pertumbuhan ekonomi di Provinsi Maluku Utara selama periode 2012-2016 meningkatkan produksi sektor pertanian, khususnya pertambangan dan pengalihan, industri pengolahan, dan pengadaan listrik dan gas. | K53: panjang | L53: REVISE | M53: Major | N53: Reasoning | O53: Reasoning, Typo/Grammar | P53: Y | Q53: Text-Text Inference | R53: N | U53: Text: kecenderungan pertumbuhan ekonomi Malut 2012-2016 menunjukkan penurunan, karena produksi pertanian masih tradisional dan ketergantungan pada komoditas mentah termasuk bahan tambang. | V53: Answer misstates the finding: text says growth trend declined, with traditional agriculture and raw-commodity dependence as causes; answer invents 'increased production' and garbles sectors. | X53: Pertumbuhan ekonomi Maluku Utara pada 2012-2016 cenderung menurun, antara lain karena proses produksi sektor pertanian yang masih tradisional dan ketergantungan pada komoditas mentah termasuk bahan tambang. | Y53: 0 | Z53: 0 | AA53: 0 | AB53: 1 | AC53: 0 | AD53: 0 | AE53: 0 | AF53: 0 | AG53: 0 | AH53: 1
A54: QA0053 | B54: InternVL | C54: KEKR Provinsi Maluku Utara Mei 2017 | D54: 34 | E54: KEKR 20Provinsi 20Maluku 20Utara 20Mei 202017_p034.png | F54: 1 | G54: Chart-Numerical Calculation | H54: Chart | I54: Bagaimana pertumbuhan PDRB di Provinsi Maluku Utara selama periode 2012-2016? | J54: PDRB di Provinsi Maluku Utara selama periode 2012-2016 meningkatkan dari 6,47% pada tahun 2012 menjadi 4,27% pada tahun 2016. | K54: pendek | L54: REVISE | M54: Major | N54: Factual/Numerical | O54: Factual/Numerical, Reasoning, Instruction-following | P54: N | Q54: Table-Comparison and Sorting | R54: N | U54: Tabel 1 PDRB row: 6,98% (2012), 6,36% (2013), 5,49% (2014), 6,10% (2015), 5,77% (2016). 6,47%/4,27% are Pertanian row. | V54: Values taken from Pertanian row, not PDRB; 'meningkat' is wrong (growth fell). Data from Tabel 1, no chart, no calculation performed. | X54: Pertumbuhan PDRB Maluku Utara cenderung melambat, dari 6,98% pada 2012 menjadi 5,77% pada 2016 (6,36% pada 2013, 5,49% pada 2014, 6,10% pada 2015). | Y54: 0 | Z54: 1 | AA54: 0 | AB54: 1 | AC54: 0 | AD54: 0 | AE54: 0 | AF54: 1 | AG54: 0 | AH54: 0
A55: QA0054 | B55: InternVL | C55: KEKR Provinsi Maluku Utara Mei 2017 | D55: 34 | E55: KEKR 20Provinsi 20Maluku 20Utara 20Mei 202017_p034.png | F55: 2 | G55: Chart-Information Extraction | H55: Chart | I55: Bagaimana pertumbuhan produksi pertanian di Provinsi Maluku Utara selama periode 2012-2016? | J55: Pertumbuhan produksi pertanian di Provinsi Maluku Utara selama periode 2012-2016 meningkatkan dari 3,13% pada tahun 2012 menjadi 15,14% pada tahun 2016. | K55: panjang | L55: REVISE | M55: Major | N55: Factual/Numerical | O55: Factual/Numerical, Reasoning, Instruction-following | P55: N | Q55: Table-Comparison and Sorting | R55: N | U55: Tabel 1 Pertanian, Kehutanan, dan Perikanan: 6,47% (2012), 3,54%, 3,02%, 1,67%, 4,27% (2016). 3,13% = Pertambangan 2012; 15,14% = Industri 2016. | V55: Wrong rows mixed (Pertambangan 2012, Industri Pengolahan 2016); direction wrong: agriculture growth fell from 6,47% to 4,27%. Source is a table, not chart. | X55: Pertumbuhan sektor Pertanian, Kehutanan, dan Perikanan melambat dari 6,47% pada 2012 menjadi 4,27% pada 2016, dengan titik terendah 1,67% pada 2015. | Y55: 0 | Z55: 1 | AA55: 0 | AB55: 1 | AC55: 0 | AD55: 0 | AE55: 0 | AF55: 1 | AG55: 0 | AH55: 0
A56: QA0055 | B56: InternVL | C56: KEKR Provinsi Maluku Utara Mei 2017 | D56: 35 | E56: KEKR 20Provinsi 20Maluku 20Utara 20Mei 202017_p035.png | F56: 0 | G56: Text-Text Inference | H56: Text | I56: Bagaimana banyak ton perikanan yang mengalami penurunan di Provinsi Maluku Utara selama periode 2012-2016? | J56: 1,12% | K56: pendek | L56: REVISE | M56: Major | N56: Factual/Numerical | O56: Factual/Numerical, Typo/Grammar | P56: Y | Q56: Text-Text Inference | R56: N | U56: Text: pangsa sektor pertanian dalam PDRB terus menurun dalam 2012-2016 sebesar 1,12%. No fishery tonnage decline stated. | V56: 1,12% is the decline in agriculture sector's PDRB share over 2012-2016, not a tonnage of fisheries; question misattributes the metric and is garbled. | W56: Berapa penurunan pangsa sektor pertanian dalam PDRB Maluku Utara selama 2012-2016? | X56: Pangsa sektor pertanian menurun sebesar 1,12% dalam kurun 2012-2016. | Y56: 0 | Z56: 1 | AA56: 0 | AB56: 0 | AC56: 0 | AD56: 0 | AE56: 0 | AF56: 0 | AG56: 0 | AH56: 1
A57: QA0056 | B57: InternVL | C57: KEKR Provinsi Maluku Utara Mei 2017 | D57: 35 | E57: KEKR 20Provinsi 20Maluku 20Utara 20Mei 202017_p035.png | F57: 1 | G57: Chart-Numerical Calculation | H57: Chart | I57: Bagaimana berbagi potensi perikanan antara ton perikanan terbaik dan ton perikanan terendah di Provinsi Maluku Utara? | J57: Potensi perikanan terbaik: 1,035,230 ton per tahun, potensi perikanan terendah: 106,510 ton per tahun | K57: panjang | L57: REVISE | M57: Major | N57: Reasoning | O57: Reasoning, Instruction-following, Typo/Grammar | P57: N | Q57: Text-Text Inference | R57: N | U57: Text: potensi sumberdaya ikan (standing stock) 1.035.230 ton/tahun; potensi lestari 517.000 ton/tahun; potensi ikan pelagis besar 106.510 ton/tahun. No chart. | V57: 1.035.230 is total standing stock and 106.510 is pelagis besar potential; they are not 'best vs lowest' fisheries. Question garbled; no chart on page for a Chart calculation. | W57: Berapa potensi sumberdaya ikan total dan potensi ikan pelagis besar per tahun di Maluku Utara? | X57: Potensi sumberdaya ikan (standing stock) mencapai 1.035.230 ton per tahun, sedangkan potensi ikan pelagis besar 106.510 ton per tahun. | Y57: 0 | Z57: 0 | AA57: 0 | AB57: 1 | AC57: 0 | AD57: 0 | AE57: 0 | AF57: 1 | AG57: 0 | AH57: 1
A58: QA0057 | B58: InternVL | C58: KEKR Provinsi Maluku Utara Mei 2017 | D58: 35 | E58: KEKR 20Provinsi 20Maluku 20Utara 20Mei 202017_p035.png | F58: 2 | G58: Chart-Information Extraction | H58: Chart | I58: Bagaimana banyak ton perikanan yang mengalami peningkatan di Provinsi Maluku Utara selama periode 2012-2016? | J58: 31,48% | K58: pendek | L58: DISCARD | M58: Critical | N58: Hallucination | O58: Hallucination | P58: N | Q58: Text-Text Inference | R58: N | S58: False premise / speculation | T58: Borrowed value from another metric on the page | U58: Text: 31,48% is pemanfaatan ikan pelagis kecil; page gives no fishery tonnage increase over 2012-2016. No chart. | V58: Page has no data on fishery tonnage increasing in 2012-2016; 31,48% is pelagis kecil utilization rate. Premise not grounded. | Y58: 1 | Z58: 0 | AA58: 0 | AB58: 0 | AC58: 0 | AD58: 0 | AE58: 0 | AF58: 0 | AG58: 0 | AH58: 0
A59: QA0058 | B59: InternVL | C59: KEKR Provinsi Maluku Utara Mei 2017 | D59: 48 | E59: KEKR 20Provinsi 20Maluku 20Utara 20Mei 202017_p048.png | F59: 0 | G59: Text-Text Inference | H59: Text | I59: Bagaimana penurunan pendapatan asli daerah pada APBD 2017? | J59: Pada APBD 2017, pendapatan asli daerah menurun 16,53% dibandingkan dengan tahun sebelumnya. | K59: pendek | L59: REVISE | M59: Major | N59: Factual/Numerical | O59: Factual/Numerical, Reasoning | P59: Y | Q59: Text-Text Inference | R59: N | U59: Tabel 2.1 & text: PAD naik 99,17% (yoy), from Rp244,37 miliar (APBD 2016) to Rp486,71 miliar (APBD 2017). 16,53% is Belanja Operasi. | V59: PAD increased, not decreased. 16,53% belongs to Belanja Operasi. The question's premise is wrong but fixable from the page. | W59: Bagaimana perubahan pendapatan asli daerah (PAD) pada APBD 2017? | X59: Pada APBD 2017, pendapatan asli daerah meningkat 99,17% (yoy), dari Rp244,37 miliar pada APBD 2016 menjadi Rp486,71 miliar. | Y59: 0 | Z59: 1 | AA59: 0 | AB59: 1 | AC59: 0 | AD59: 0 | AE59: 0 | AF59: 0 | AG59: 0 | AH59: 0
A60: QA0059 | B60: InternVL | C60: KEKR Provinsi Maluku Utara Mei 2017 | D60: 48 | E60: KEKR 20Provinsi 20Maluku 20Utara 20Mei 202017_p048.png | F60: 1 | G60: Chart-Numerical Calculation | H60: Chart | I60: Bagaimana berubah pendapatan transfer pada APBD 2017? | J60: Pada APBD 2017, pendapatan transfer meningkat 16,53% dibandingkan dengan tahun sebelumnya. | K60: panjang | L60: REVISE | M60: Major | N60: Factual/Numerical | O60: Factual/Numerical, Instruction-following | P60: N | Q60: Table-Numerical Calculation | R60: N | U60: Tabel 2.1: Pendapatan Transfer Rp1.743,20 miliar (2016) -> Rp1.907,79 miliar (2017), perubahan 9,44% (text states 30,43%). No chart on page. | V60: 16,53% belongs to Belanja Operasi. The table shows 9,44% for transfer income. The page has no chart, only a table. | W60: Bagaimana perubahan pendapatan transfer pada APBD 2017? | X60: Pada APBD 2017, pendapatan transfer meningkat 9,44% dibandingkan APBD 2016, dari Rp1.743,20 miliar menjadi Rp1.907,79 miliar (Tabel 2.1). | Y60: 0 | Z60: 1 | AA60: 0 | AB60: 0 | AC60: 0 | AD60: 0 | AE60: 0 | AF60: 1 | AG60: 0 | AH60: 0
A61: QA0060 | B61: InternVL | C61: KEKR Provinsi Maluku Utara Mei 2017 | D61: 48 | E61: KEKR 20Provinsi 20Maluku 20Utara 20Mei 202017_p048.png | F61: 2 | G61: Chart-Information Extraction | H61: Chart | I61: Bagaimana berubah belanja operasi pada APBD 2017? | J61: Pada APBD 2017, belanja operasi meningkat 99,17% dibandingkan dengan tahun sebelumnya. | K61: pendek | L61: REVISE | M61: Major | N61: Factual/Numerical | O61: Factual/Numerical, Instruction-following | P61: N | Q61: Table-Numerical Calculation | R61: N | U61: Tabel 2.1: Belanja Operasi Rp1.672,22 miliar (2016) -> Rp1.948,69 miliar (2017), perubahan 16,53%. No chart. | V61: 99,17% is the PAD change. Belanja Operasi rose 16,53%. The source is a table, not a chart. | W61: Bagaimana perubahan belanja operasi pada APBD 2017? | X61: Pada APBD 2017, belanja operasi meningkat 16,53% dibandingkan APBD 2016, dari Rp1.672,22 miliar menjadi Rp1.948,69 miliar. | Y61: 0 | Z61: 1 | AA61: 0 | AB61: 0 | AC61: 0 | AD61: 0 | AE61: 0 | AF61: 1 | AG61: 0 | AH61: 0
A62: QA0061 | B62: InternVL | C62: KEKR Provinsi Maluku Utara Mei 2017 | D62: 50 | E62: KEKR 20Provinsi 20Maluku 20Utara 20Mei 202017_p050.png | F62: 0 | G62: Text-Text Inference | H62: Text | I62: Jumlah realisasi pendapatan Pemerintah Provinsi Maluku Utara pada tahun 2017 berapa? | J62: Rp549,532 miliar | K62: pendek | L62: REVISE | M62: Minor | N62: Temporal | O62: Temporal | P62: Y | Q62: Text-Text Inference | R62: N | U62: Text: total realisasi pendapatan daerah Pemprov Maluku Utara pada triwulan I 2017 sebesar Rp549,532 miliar. | V62: Value correct but it is triwulan I 2017, not the full year 2017. | W62: Berapa jumlah realisasi pendapatan Pemerintah Provinsi Maluku Utara pada triwulan I 2017? | X62: Rp549,532 miliar pada triwulan I 2017. | Y62: 0 | Z62: 0 | AA62: 0 | AB62: 0 | AC62: 1 | AD62: 0 | AE62: 0 | AF62: 0 | AG62: 0 | AH62: 0
A63: QA0062 | B63: InternVL | C63: KEKR Provinsi Maluku Utara Mei 2017 | D63: 50 | E63: KEKR 20Provinsi 20Maluku 20Utara 20Mei 202017_p050.png | F63: 1 | G63: Chart-Numerical Calculation | H63: Chart | I63: Persentase pertumbuhan realisasi pendapatan Pemerintah Provinsi Maluku Utara dari tahun 2016 ke tahun 2017 berapa? | J63: 19,19% | K63: pendek | L63: REVISE | M63: Major | N63: Factual/Numerical | O63: Factual/Numerical, Reasoning, Temporal, Instruction-following | P63: N | Q63: Text-Text Inference | R63: N | U63: Text: Tw I 2017 realisasi 19,19%, lebih rendah dari Tw I 2016 25,11% (realization rates). Grafik 2.3: Tw I 2016 ~Rp540 M, Tw I 2017 ~Rp549,5 M. | V63: 19,19% is the Tw I 2017 realization rate, not growth from 2016 to 2017; the rate fell vs 25,11%. Nominally Tw I 2017 is only slightly above Tw I 2016 in the chart. | W63: Bagaimana persentase realisasi pendapatan Pemerintah Provinsi Maluku Utara pada triwulan I 2017 dibandingkan triwulan I 2016? | X63: Realisasi pendapatan triwulan I 2017 sebesar 19,19%, lebih rendah dibanding triwulan I 2016 yang terealisasi sebesar 25,11%. | Y63: 0 | Z63: 1 | AA63: 0 | AB63: 1 | AC63: 1 | AD63: 0 | AE63: 0 | AF63: 1 | AG63: 0 | AH63: 0
A64: QA0063 | B64: InternVL | C64: KEKR Provinsi Maluku Utara Mei 2017 | D64: 50 | E64: KEKR 20Provinsi 20Maluku 20Utara 20Mei 202017_p050.png | F64: 2 | G64: Chart-Information Extraction | H64: Chart | I64: Realisasi pendapatan Pemerintah Provinsi Maluku Utara pada tahun 2016 berapa? | J64: Rp549,532 miliar | K64: pendek | L64: REVISE | M64: Major | N64: Factual/Numerical | O64: Factual/Numerical, Temporal | P64: Y | Q64: Chart-Information Extraction | R64: N | U64: Grafik 2.3: bar Tw I 2016 ~540.000 (juta Rp) i.e. ~Rp540 miliar; Rp549,532 miliar is Tw I 2017 (text). | V64: Rp549,532 miliar belongs to Tw I 2017; Tw I 2016 is ~Rp540 miliar in the chart. Full-year 2016 is not stated; question should specify triwulan I. | W64: Berapa realisasi pendapatan Pemerintah Provinsi Maluku Utara pada triwulan I 2016? | X64: Berdasarkan Grafik 2.3, realisasi pendapatan triwulan I 2016 sekitar Rp540 miliar (sekitar 540.000 juta rupiah). | Y64: 0 | Z64: 1 | AA64: 0 | AB64: 0 | AC64: 1 | AD64: 0 | AE64: 0 | AF64: 0 | AG64: 0 | AH64: 0
A65: QA0064 | B65: InternVL | C65: KEKR Provinsi Maluku Utara Mei 2017 | D65: 71 | E65: KEKR 20Provinsi 20Maluku 20Utara 20Mei 202017_p071.png | F65: 0 | G65: Text-Text Inference | H65: Text | I65: Pertumbuhan jumlah rekening dari kemampuan ke 3 juta per kategori penggunaan pada 2017 dibandingkan dengan 2016? | J65: Pertumbuhan jumlah rekening dari kemampuan ke 3 juta per kategori penggunaan pada 2017 dibandingkan dengan 2016 adalah 10,79% (yoy) dan 12,09% (yoy). | K65: panjang | L65: REVISE | M65: Major | N65: Factual/Numerical | O65: Factual/Numerical, Typo/Grammar | P65: Y | Q65: Text-Text Inference | R65: N | U65: Text: pertumbuhan jumlah rekening naik dari 12,09% (yoy) Tw I 2016 menjadi 13,97% (yoy) Tw I 2017; 10,79% is DPK Perseorangan growth Tw I 2016. | V65: Question garbled (no account data by 3 juta income category). Answer gives 10,79% (DPK growth) instead of 13,97% for 2017; account growth 2017 vs 2016 is 12,09% -> 13,97%. | W65: Bagaimana pertumbuhan jumlah rekening masyarakat di perbankan pada triwulan I 2017 dibandingkan triwulan I 2016? | X65: Pertumbuhan jumlah rekening meningkat dari 12,09% (yoy) pada triwulan I 2016 menjadi 13,97% (yoy) pada triwulan I 2017. | Y65: 0 | Z65: 1 | AA65: 0 | AB65: 0 | AC65: 0 | AD65: 0 | AE65: 0 | AF65: 0 | AG65: 0 | AH65: 1
A66: QA0065 | B66: InternVL | C66: KEKR Provinsi Maluku Utara Mei 2017 | D66: 71 | E66: KEKR 20Provinsi 20Maluku 20Utara 20Mei 202017_p071.png | F66: 1 | G66: Chart-Time-Sensitive | H66: Chart | I66: Bagaimana berubah komposisi konsumsinya dari kategori pendapatan menengah dan menengah tua pada 2017 dibandingkan dengan 2016? | J66: Komposisi konsumsinya dari kategori pendapatan menengah dan menengah tua pada 2017 dibandingkan dengan 2016 meningkat dari 58,33% menjadi 58,33% dan 58,33% menjadi 58,33%. | K66: panjang | L66: DISCARD | M66: Critical | N66: Hallucination | O66: Hallucination, Temporal, Typo/Grammar | P66: N | Q66: Table-Comparison and Sorting | R66: N | S66: False premise / speculation | T66: Fabricated value/claim (not on page) | U66: Tabel 4.1 shows a single-period snapshot: Konsumsi Rp3-4 juta 58,33; Rp4-5 juta 58,33. No 2016 vs 2017 comparison of consumption composition; no chart. | V66: Premise of a 2016->2017 change in consumption composition is not on the page; answer '58,33% menjadi 58,33%' is nonsensical. | Y66: 1 | Z66: 0 | AA66: 0 | AB66: 0 | AC66: 1 | AD66: 0 | AE66: 0 | AF66: 0 | AG66: 0 | AH66: 1
A67: QA0066 | B67: InternVL | C67: KEKR Provinsi Maluku Utara Mei 2017 | D67: 71 | E67: KEKR 20Provinsi 20Maluku 20Utara 20Mei 202017_p071.png | F67: 2 | G67: Chart-Information Extraction | H67: Chart | I67: Bagaimana berubah jumlah rekening dari kemampuan ke 4 juta per kategori penggunaan pada 2017 dibandingkan dengan 2016? | J67: Jumlah rekening dari kemampuan ke 4 juta per kategori penggunaan pada 2017 dibandingkan dengan 2016 adalah 20,83% (yoy) dan 20,83% (yoy). | K67: pendek | L67: REVISE | M67: Major | N67: Factual/Numerical | O67: Factual/Numerical, Typo/Grammar, Instruction-following | P67: N | Q67: Text-Text Inference | R67: N | U67: Text: jumlah rekening tumbuh 12,09% (yoy) Tw I 2016 -> 13,97% (yoy) Tw I 2017. 20,83 is cicilan/tabungan share for Rp3-4 juta (Tabel 4.1). No chart. | V67: Garbled question; answer 20,83% (yoy) is an income-allocation share misread as account growth. Evidence is text, not chart. | W67: Bagaimana perubahan pertumbuhan jumlah rekening masyarakat di perbankan pada triwulan I 2017 dibandingkan triwulan I 2016? | X67: Pertumbuhan jumlah rekening meningkat dari 12,09% (yoy) pada triwulan I 2016 menjadi 13,97% (yoy) pada triwulan I 2017. | Y67: 0 | Z67: 1 | AA67: 0 | AB67: 0 | AC67: 0 | AD67: 0 | AE67: 0 | AF67: 1 | AG67: 0 | AH67: 1
A68: QA0067 | B68: InternVL | C68: KEKR Provinsi Maluku Utara Mei 2017 | D68: 87 | E68: KEKR 20Provinsi 20Maluku 20Utara 20Mei 202017_p087.png | F68: 0 | G68: Text-Text Inference | H68: Text | I68: Jumlah transaksi pembayaran non tunai pada periode I 2017 di Maluku Utara berapa? | J68: 234,92 miliar | K68: pendek | L68: REVISE | M68: Minor | N68: Unit | O68: Unit, Typo/Grammar | P68: Y | Q68: Text-Text Inference | R68: N | U68: Text 5.2.1: transaksi nontunai melalui kliring triwulan I 2017 tercatat sebesar Rp234,92 miliar. | V68: Value correct, but it is the nominal of clearing transactions (Rp missing) and 'periode I' should be triwulan I; 'jumlah transaksi' may be confused with transaction count. | W68: Berapa nominal transaksi pembayaran nontunai melalui kliring di Maluku Utara pada triwulan I 2017? | X68: Rp234,92 miliar. | Y68: 0 | Z68: 0 | AA68: 0 | AB68: 0 | AC68: 0 | AD68: 1 | AE68: 0 | AF68: 0 | AG68: 0 | AH68: 1
A69: QA0068 | B69: InternVL | C69: KEKR Provinsi Maluku Utara Mei 2017 | D69: 87 | E69: KEKR 20Provinsi 20Maluku 20Utara 20Mei 202017_p087.png | F69: 1 | G69: Chart-Numerical Calculation | H69: Chart | I69: Bagaimana perubahan kontraksi terkontraksi pada periode I 2017 di Maluku Utara? | J69: 9,81% (yoy) | K69: pendek | L69: REVISE | M69: Minor | N69: Instruction-following | O69: Instruction-following, Typo/Grammar, Incomplete | P69: N | Q69: Text-Text Inference | R69: N | U69: Text: nominal kliring Tw I 2017 terkontraksi semakin dalam dari 7,45% (yoy) pada triwulan sebelumnya menjadi 9,81% (yoy). | V69: 9,81% yoy is right but comes from text, not a chart calculation; question is garbled and answer omits the change from 7,45%. | W69: Bagaimana perubahan kontraksi nominal transaksi kliring di Maluku Utara pada triwulan I 2017? | X69: Kontraksi nominal transaksi kliring semakin dalam, dari 7,45% (yoy) pada triwulan sebelumnya menjadi 9,81% (yoy) pada triwulan I 2017. | Y69: 0 | Z69: 0 | AA69: 0 | AB69: 0 | AC69: 0 | AD69: 0 | AE69: 1 | AF69: 1 | AG69: 0 | AH69: 1
A70: QA0069 | B70: InternVL | C70: KEKR Provinsi Maluku Utara Mei 2017 | D70: 87 | E70: KEKR 20Provinsi 20Maluku 20Utara 20Mei 202017_p087.png | F70: 2 | G70: Chart-Information Extraction | H70: Chart | I70: Bagaimana perubahan jumlah transaksi pembayaran non tunai pada periode IV 2016 di Maluku Utara? | J70: 31 jumlah transaksi | K70: pendek | L70: REVISE | M70: Major | N70: Factual/Numerical | O70: Factual/Numerical, Unit | P70: Y | Q70: Chart-Information Extraction | R70: N | U70: Grafik 5.2: jumlah warkat Tw IV 2016 approx. 4.900 lembar (below ~5.100 in Tw IV 2015); nominal ~Rp245.000 juta. Tabel 5.2: cek kosong Tw IV 2016 = 44; 31 is 2015. | V70: '31' is cek/BG kosong count for 2015 Tw I/IV, not the Tw IV 2016 clearing transaction count; chart shows ~4.900 warkat. | W70: Berapa jumlah warkat kliring di Maluku Utara pada triwulan IV 2016? | X70: Jumlah warkat kliring pada triwulan IV 2016 sekitar 4.900 lembar, lebih rendah dibanding triwulan IV 2015 (sekitar 5.100 lembar). | Y70: 0 | Z70: 1 | AA70: 0 | AB70: 0 | AC70: 0 | AD70: 1 | AE70: 0 | AF70: 0 | AG70: 0 | AH70: 0
A71: QA0070 | B71: InternVL | C71: KEKR Provinsi Maluku Utara Mei 2017 | D71: 88 | E71: KEKR 20Provinsi 20Maluku 20Utara 20Mei 202017_p088.png | F71: 0 | G71: Chart-Information Extraction | H71: Chart | I71: Jumlah agen LKD di Maluku Utara pada tahun 2017 berapa? | J71: 539 | K71: pendek | L71: REVISE | M71: Minor | N71: Temporal | O71: Temporal, Format | P71: Y | Q71: Chart-Information Extraction | R71: N | U71: Grafik 5.3: 2017 bar only for Tw I = 539 agen (also in text: triwulan I 2017, 539 agen). | V71: 539 is correct but refers to Tw I 2017 only, not the full year; answer is a bare number. | W71: Berapa jumlah agen LKD di Maluku Utara pada triwulan I 2017? | X71: Jumlah agen LKD di Maluku Utara pada triwulan I 2017 sebanyak 539 agen. | Y71: 0 | Z71: 0 | AA71: 0 | AB71: 0 | AC71: 1 | AD71: 0 | AE71: 0 | AF71: 0 | AG71: 1 | AH71: 0
A72: QA0071 | B72: InternVL | C72: KEKR Provinsi Maluku Utara Mei 2017 | D72: 88 | E72: KEKR 20Provinsi 20Maluku 20Utara 20Mei 202017_p088.png | F72: 1 | G72: Chart-Time-Sensitive | H72: Chart | I72: Bagaimana perubahan jumlah agen LKD di Maluku Utara antara tahun 2016 dan 2017? | J72: Jumlah agen LKD di Maluku Utara meningkat dari 265 pada tahun 2016 menjadi 571 pada tahun 2017. | K72: panjang | L72: REVISE | M72: Major | N72: Factual/Numerical | O72: Factual/Numerical, Temporal | P72: Y | Q72: Chart-Time-Sensitive | R72: N | U72: Grafik 5.3: 2016 Tw I 265, II 302, III 411, IV 571; 2017 Tw I 539 (down 32 from Tw IV 2016). | V72: 571 is Tw IV 2016, not 2017; 2017 (Tw I) is 539. Answer misattributes periods and misses the qtq decline. | X72: Jumlah agen LKD naik dari 265 agen (Tw I 2016) hingga 571 agen (Tw IV 2016), lalu turun menjadi 539 agen pada Tw I 2017; secara tahunan tumbuh 103% (yoy) dari 265 pada Tw I 2016. | Y72: 0 | Z72: 1 | AA72: 0 | AB72: 0 | AC72: 1 | AD72: 0 | AE72: 0 | AF72: 0 | AG72: 0 | AH72: 0
A73: QA0072 | B73: InternVL | C73: KEKR Provinsi Maluku Utara Mei 2017 | D73: 88 | E73: KEKR 20Provinsi 20Maluku 20Utara 20Mei 202017_p088.png | F73: 2 | G73: Chart-Numerical Calculation | H73: Chart | I73: Persentase pertumbuhan jumlah agen LKD di Maluku Utara antara tahun 2016 dan 2017 berapa? | J73: Pertumbuhan jumlah agen LKD di Maluku Utara antara tahun 2016 dan 2017 adalah 149%. | K73: pendek | L73: REVISE | M73: Major | N73: Factual/Numerical | O73: Factual/Numerical, Temporal | P73: Y | Q73: Chart-Numerical Calculation | R73: N | U73: Grafik 5.3: Tw I 2016 = 265, Tw I 2017 = 539 -> +103% yoy (text: 103% yoy); 149% is Tw IV 2016 yoy growth. | V73: 149% is the Tw IV 2016 growth; growth from 2016 to 2017 (Tw I yoy) is 539/265-1 = 103%. | W73: Berapa persentase pertumbuhan jumlah agen LKD di Maluku Utara dari triwulan I 2016 ke triwulan I 2017? | X73: Jumlah agen LKD tumbuh sekitar 103% (yoy), dari 265 agen pada triwulan I 2016 menjadi 539 agen pada triwulan I 2017. | Y73: 0 | Z73: 1 | AA73: 0 | AB73: 0 | AC73: 1 | AD73: 0 | AE73: 0 | AF73: 0 | AG73: 0 | AH73: 0
A74: QA0073 | B74: InternVL | C74: KEKR Provinsi Maluku Utara Mei 2017 | D74: 91 | E74: KEKR 20Provinsi 20Maluku 20Utara 20Mei 202017_p091.png | F74: 0 | G74: Text-Text Inference | H74: Text | I74: Berapa perkembangan indikator ketenagakerjaan di Maluku Utara pada bulan Februari 2017? | J74: Perkembangan indikator ketenagakerjaan di Maluku Utara menunjukkan pertumbuhan yang baik pada bulan Februari 2017 | K74: pendek | L74: REVISE | M74: Minor | N74: Incomplete | O74: Incomplete | P74: Y | Q74: Text-Text Inference | R74: N | U74: Text: indikator masih tumbuh baik; TPAK naik 67,83% (Feb 2016) -> 69,48% (Feb 2017); TPT naik 3,43% -> 4,82%. | V74: Question asks 'berapa' but answer gives only a qualitative statement without figures. | X74: Indikator ketenagakerjaan Maluku Utara masih tumbuh baik: TPAK Februari 2017 sebesar 69,48% (naik dari 67,83% pada Februari 2016), sedangkan TPT naik menjadi 4,82% dari 3,43%. | Y74: 0 | Z74: 0 | AA74: 0 | AB74: 0 | AC74: 0 | AD74: 0 | AE74: 1 | AF74: 0 | AG74: 0 | AH74: 0
A75: QA0074 | B75: InternVL | C75: KEKR Provinsi Maluku Utara Mei 2017 | D75: 91 | E75: KEKR 20Provinsi 20Maluku 20Utara 20Mei 202017_p091.png | F75: 1 | G75: Chart-Numerical Calculation | H75: Chart | I75: Bagaimana perkembangan indikator ketenagakerjaan di Maluku Utara melibatkan sektor pertanian, perkebunan, dan perikanan? | J75: Perkembangan indikator ketenagakerjaan di sektor pertanian, perkebunan, dan perikanan menunjukkan pertumbuhan yang baik, dengan peningkatan dari 4,43% pada Februari 2016 menjadi 4,82% pada Februari 2017 | K75: panjang | L75: REVISE | M75: Major | N75: Factual/Numerical | O75: Factual/Numerical, Instruction-following | P75: N | Q75: Text-Text Inference | R75: N | U75: Text: penyerapan terbesar di sektor pertanian, perkebunan, kehutanan, perburuan, perikanan; terjadi pergeseran ke sektor sekunder/tersier. 4,82% is TPT Feb 2017 (from 3,43%). | V75: The 4,43%->4,82% figures are a misread of TPT (3,43%->4,82%) and are not agricultural-sector data. The sector info is only in text; no chart calc. | X75: Sektor pertanian, perkebunan, kehutanan, perburuan, dan perikanan menyerap tenaga kerja paling besar, namun sedang terjadi pergeseran penyerapan tenaga kerja dari sektor ini ke sektor sekunder dan tersier seperti industri pengolahan, konstruksi, dan perdagangan. | Y75: 0 | Z75: 1 | AA75: 0 | AB75: 0 | AC75: 0 | AD75: 0 | AE75: 0 | AF75: 1 | AG75: 0 | AH75: 0
A76: QA0075 | B76: InternVL | C76: KEKR Provinsi Maluku Utara Mei 2017 | D76: 91 | E76: KEKR 20Provinsi 20Maluku 20Utara 20Mei 202017_p091.png | F76: 2 | G76: Chart-Information Extraction | H76: Chart | I76: Bagaimana berdasarkan data Tingkat Partisipasi Angkatan Kerja (TPAK) pada bulan Februari 2016 dan 2017? | J76: Tingkat Partisipasi Angkatan Kerja (TPAK) menunjukkan pertumbuhan yang baik, dengan meningkat dari 67,83% pada Februari 2016 menjadi 69,48% pada Februari 2017 | K76: pendek | L76: PASS | M76: None | N76: None | P76: Y | Q76: Chart-Information Extraction | R76: Y | U76: Grafik 6.1 data table: TPAK Feb 2016 67,83%, Feb 2017 69,48%. | V76: Values and direction correct; question slightly awkward but understandable. | Y76: 0 | Z76: 0 | AA76: 0 | AB76: 0 | AC76: 0 | AD76: 0 | AE76: 0 | AF76: 0 | AG76: 0 | AH76: 0
A77: QA0076 | B77: InternVL | C77: KSK-4626_003 | D77: 65 | E77: KSK-4626_003_p065.png | F77: 0 | G77: Text-Text Inference | H77: Text | I77: Bagaimana risiko operasional dari pihak ketiga terhadap sistem keuangan? | J77: Risiko operasional dari pihak ketiga dapat mengakibatkan keamanan sistem keuangan, seperti kejahatan, kelebihan akses, dan penyalahgunaan sistem. | K77: pendek | L77: REVISE | M77: Minor | N77: Typo/Grammar | O77: Typo/Grammar, Incomplete, Factual/Numerical | P77: Y | Q77: Text-Text Inference | R77: N | U77: Text: insiden pihak ketiga berupa serangan siber, penyalahgunaan sistem, fraud; celah unauthorized access; dampak kerugian finansial, gangguan operasional, risiko reputasi, bisa jadi risiko sistemik. | V77: Answer is garbled ('mengakibatkan keamanan', 'kelebihan akses' instead of akses tidak sah) and omits the stated impacts (financial loss, operational disruption, reputational risk, systemic contagion). | X77: Risiko operasional dari pihak ketiga dapat berupa serangan siber, penyalahgunaan sistem, fraud, dan akses tidak sah, yang berpotensi menimbulkan kerugian finansial, gangguan operasional, dan penurunan kepercayaan (risiko reputasi); bila pihak ketiga melayani banyak lembaga, risiko dapat tereskalasi menjadi risiko sistemik. | Y77: 0 | Z77: 1 | AA77: 0 | AB77: 0 | AC77: 0 | AD77: 0 | AE77: 1 | AF77: 0 | AG77: 0 | AH77: 1
A78: QA0077 | B78: InternVL | C78: KSK-4626_003 | D78: 65 | E78: KSK-4626_003_p065.png | F78: 1 | G78: Chart-Information Extraction | H78: Chart | I78: Bagaimana Bank Indonesia mengatasi risiko operasional? | J78: Bank Indonesia menggunakan regulasi dan pengawasan untuk mengurangi risiko operasional, seperti menggunakan PSP dan mengelola keberlanjutan sistem. | K78: panjang | L78: REVISE | M78: Minor | N78: Instruction-following | O78: Instruction-following, Incomplete, Factual/Numerical | P78: N | Q78: Text-Text Inference | R78: N | U78: Text: BI memastikan kerja sama PSP-pihak ketiga patuh ketentuan; penguatan pengawasan onsite (asesmen berbasis kepatuhan dan risiko) dan offsite (pemeriksaan berkala). | V78: Evidence is paragraph text, not chart. 'Pengawasan' is right but 'menggunakan PSP dan mengelola keberlanjutan sistem' misstates it; onsite/offsite supervision details missing. | X78: Bank Indonesia memastikan kerja sama antara PSP dan pihak ketiga mematuhi ketentuan, serta memperkuat pengawasan onsite berbasis asesmen kepatuhan dan risiko (manajemen risiko operasional dan keandalan infrastruktur TI) dan pengawasan offsite melalui pemeriksaan berkala atas PSP. | Y78: 0 | Z78: 1 | AA78: 0 | AB78: 0 | AC78: 0 | AD78: 0 | AE78: 1 | AF78: 1 | AG78: 0 | AH78: 0
A79: QA0078 | B79: InternVL | C79: KSK-4626_003 | D79: 65 | E79: KSK-4626_003_p065.png | F79: 2 | G79: Chart-Numerical Calculation | H79: Chart | I79: Bagaimana berdasarkan data, perbedaan risiko operasional di antara tahun 2021 dan 2022? | J79: Pada tahun 2021, terkait pihak ketiga adalah 1,4%, sementara pada tahun 2022 adalah 2,5%. | K79: pendek | L79: REVISE | M79: Major | N79: Factual/Numerical | O79: Factual/Numerical, Unit, Calculation | P79: Y | Q79: Chart-Numerical Calculation | R79: N | U79: Grafik B3.2.1 (frekuensi): 2021 terkait pihak ketiga 1, total 3; 2022 terkait pihak ketiga 0, total 4. | V79: Chart shows incident counts, not percentages; 1,4% and 2,5% are fabricated. Correct: third-party incidents 1 (2021) vs 0 (2022); total incidents 3 vs 4. | W79: Berdasarkan Grafik B3.2.1, bagaimana perbedaan jumlah insiden siber terkait pihak ketiga dan total insiden antara tahun 2021 dan 2022? | X79: Insiden terkait pihak ketiga turun dari 1 kejadian (2021) menjadi 0 (2022), sedangkan total insiden naik dari 3 menjadi 4 kejadian (bertambah 1). | Y79: 0 | Z79: 1 | AA79: 1 | AB79: 0 | AC79: 0 | AD79: 1 | AE79: 0 | AF79: 0 | AG79: 0 | AH79: 0
A80: QA0079 | B80: InternVL | C80: KSK-4626 | D80: 36 | E80: KSK-4626_p036.png | F80: 0 | G80: Chart-Numerical Calculation | H80: Chart | I80: Bagaimana pertumbuhan kredit di Indonesia pada tahun 2023 dan 2024? | J80: Kredit konsumsi mengalami pertumbuhan sebesar, kredit komersial meningkat, dan kredit korporasi meningkat | K80: pendek | L80: REVISE | M80: Major | N80: Reasoning | O80: Incomplete, Reasoning, Instruction-following | P80: N | Q80: Table-Comparison and Sorting | R80: N | U80: Tabel 2.1.1 (%, yoy) 2023->2024: Industri 10,38->10,39; Konsumsi 9,10->10,61; Komersial 7,99->5,82; Korporasi 13,52->15,59. No chart. | V80: Answer omits the consumption growth number and wrongly says commercial credit rose (it slowed 7,99%->5,82%). Data is from a table, not a chart. | W80: Bagaimana pertumbuhan kredit perbankan per segmen pada tahun 2023 dan 2024? | X80: Kredit industri tumbuh 10,38% (2023) dan 10,39% (2024). Kredit konsumsi naik dari 9,10% ke 10,61%, kredit korporasi naik dari 13,52% ke 15,59%, sedangkan kredit komersial melambat dari 7,99% ke 5,82%. | Y80: 0 | Z80: 0 | AA80: 0 | AB80: 1 | AC80: 0 | AD80: 0 | AE80: 1 | AF80: 1 | AG80: 0 | AH80: 0
A81: QA0080 | B81: InternVL | C81: KSK-4626 | D81: 36 | E81: KSK-4626_p036.png | F81: 1 | G81: Text-Text Inference | H81: Text | I81: Bagaimana kontribusi pertumbuhan kredit di ekonomi Indonesia pada tahun 2023 dan 2024? | J81: Kredit konsumsi memimpin kontribusi pertumbuhan kredit di ekonomi Indonesia, dengan kredit komersial dan korporasi meningkat | K81: panjang | L81: REVISE | M81: Major | N81: Factual/Numerical | O81: Temporal, Factual/Numerical, Instruction-following | P81: N | Q81: Table-Comparison and Sorting | R81: N | U81: Tabel 2.1.1 Kontribusi Pertumbuhan Kredit only for Des 25: Korporasi 7,41, Investasi 5,87, Modal Kerja 2,02, Konsumsi 1,80, Komersial 0,55, UMKM -0,06. | V81: Contribution is only given for Dec 2025, not 2023/2024, and the largest contributor is corporate credit (7,41) / investment credit (5,87), not consumption (1,80). Evidence is table, not text. | W81: Segmen kredit mana yang memberikan kontribusi terbesar terhadap pertumbuhan kredit pada Desember 2025? | X81: Kredit korporasi memberikan kontribusi terbesar (7,41%) dari pertumbuhan kredit 9,69%; menurut penggunaan, kredit investasi terbesar (5,87%), sedangkan kredit konsumsi hanya 1,80%. | Y81: 0 | Z81: 1 | AA81: 0 | AB81: 0 | AC81: 1 | AD81: 0 | AE81: 0 | AF81: 1 | AG81: 0 | AH81: 0
A82: QA0081 | B82: InternVL | C82: KSK-4626 | D82: 36 | E82: KSK-4626_p036.png | F82: 2 | G82: Chart-Information Extraction | H82: Chart | I82: Bagaimana pertumbuhan kredit di industri penguasaan pada tahun 2023 dan 2024? | J82: Kredit konsumsi dan kredit kemerjaan meningkat, kredit investasi meningkat | K82: pendek | L82: REVISE | M82: Major | N82: Reasoning | O82: Reasoning, Typo/Grammar, Incomplete, Instruction-following | P82: N | Q82: Table-Comparison and Sorting | R82: N | U82: Tabel 2.1.1 Penggunaan 2023->2024: Investasi 12,26->13,62; Konsumsi 9,10->10,61; Modal Kerja 10,05->8,35. | V82: Garbled terms ('industri penguasaan', 'kemerjaan'); modal kerja credit actually slowed (10,05%->8,35%), not rose; no figures given. Data is table, not chart. | W82: Bagaimana pertumbuhan kredit berdasarkan penggunaan pada tahun 2023 dan 2024? | X82: Kredit investasi naik dari 12,26% ke 13,62% dan kredit konsumsi dari 9,10% ke 10,61%, sedangkan kredit modal kerja melambat dari 10,05% ke 8,35%. | Y82: 0 | Z82: 0 | AA82: 0 | AB82: 1 | AC82: 0 | AD82: 0 | AE82: 1 | AF82: 1 | AG82: 0 | AH82: 1
A83: QA0082 | B83: InternVL | C83: KSK-4626 | D83: 38 | E83: KSK-4626_p038.png | F83: 0 | G83: Table-Numerical Calculation | H83: Table | I83: Bagaimana kontribusi DPK pada pemerintah di 2025? | J83: 13.71 | K83: pendek | L83: REVISE | M83: Major | N83: Factual/Numerical | O83: Factual/Numerical, Format | P83: Y | Q83: Table-Numerical Calculation | R83: N | U83: Tabel 2.1.2 Kontribusi DPK 2025: Pemerintah BUMN 1,63; Pemerintah Non BUMN 3,77 (total 5,40). 13,71 is Bukan Penduduk growth 2025. | V83: 13,71 is the wrong row/column (Bukan Penduduk growth). Government contribution 2025 = 1,63 + 3,77 = 5,40 pp; bare number without unit. | W83: Berapa total kontribusi DPK golongan pemerintah (BUMN dan Non BUMN) pada 2025? | X83: Kontribusi DPK pemerintah pada 2025 sebesar 5,40% (Pemerintah BUMN 1,63% + Pemerintah Non BUMN 3,77%). | Y83: 0 | Z83: 1 | AA83: 0 | AB83: 0 | AC83: 0 | AD83: 0 | AE83: 0 | AF83: 0 | AG83: 1 | AH83: 0
A84: QA0083 | B84: InternVL | C84: KSK-4626 | D84: 38 | E84: KSK-4626_p038.png | F84: 1 | G84: Chart-Numerical Calculation | H84: Chart | I84: Bagaimana perubahan BIL dan BIL special rate pada bulan Desember 2024? | J84: BIL sebesar 125 bps, BIL special rate sebesar 123 bps | K84: panjang | L84: REVISE | M84: Major | N84: Factual/Numerical | O84: Factual/Numerical, Temporal, Typo/Grammar, Instruction-following | P84: N | Q84: Text-Text Inference | R84: N | U84: Text: penurunan BI-Rate sebesar 125 bps sepanjang 2025; suku bunga DPK special rate turun 123 bps dari 6,19% (Des 2024) menjadi 4,96% (Des 2025). | V84: 'BIL' does not exist; 125 bps is BI-Rate cut and 123 bps is DPK special rate decline, both over 2025 (Dec 2024-Dec 2025), not in Dec 2024. Values stated in text. | W84: Berapa penurunan BI-Rate dan suku bunga DPK special rate sepanjang 2025? | X84: BI-Rate turun 125 bps sepanjang 2025, sedangkan suku bunga DPK special rate turun 123 bps dari 6,19% (Desember 2024) menjadi 4,96% (Desember 2025). | Y84: 0 | Z84: 1 | AA84: 0 | AB84: 0 | AC84: 1 | AD84: 0 | AE84: 0 | AF84: 1 | AG84: 0 | AH84: 1
A85: QA0084 | B85: InternVL | C85: KSK-4626 | D85: 38 | E85: KSK-4626_p038.png | F85: 2 | G85: Chart-Time-Sensitive | H85: Chart | I85: Bagaimana berubah nilai NCG pada bulan Desember 2025? | J85: NCG meningkatkan dari 88.57% pada Desember 2024 menjadi 88.81% pada Desember 2025 | K85: pendek | L85: REVISE | M85: Major | N85: Factual/Numerical | O85: Factual/Numerical, Reasoning | P85: Y | Q85: Chart-Time-Sensitive | R85: N | U85: Grafik 2.1.4 LDR: 'Peingkatan NCG' is only an annotation. Industri LDR 88,57% (Des 2024) -> 85,35% (Des 2025); Bank Penerima SAL ends 88,71. | V85: NCG has no value on the chart; 88,57% is industry LDR and it fell to 85,35%, not rose to 88,81% (no such value). | W85: Bagaimana perubahan LDR industri perbankan dari Desember 2024 ke Desember 2025? | X85: LDR industri menurun dari 88,57% pada Desember 2024 menjadi 85,35% pada Desember 2025. | Y85: 0 | Z85: 1 | AA85: 0 | AB85: 1 | AC85: 0 | AD85: 0 | AE85: 0 | AF85: 0 | AG85: 0 | AH85: 0
A86: QA0085 | B86: InternVL | C86: KSK-4626 | D86: 40 | E86: KSK-4626_p040.png | F86: 0 | G86: Chart-Numerical Calculation | H86: Chart | I86: Bagaimana pertumbuhan penjualan Pertambangan pada tahun 2023? | J86: Pertumbuhan penjualan Pertambangan pada tahun 2023 adalah -4,9% | K86: pendek | L86: REVISE | M86: Major | N86: Factual/Numerical | O86: Factual/Numerical, Temporal, Instruction-following | P86: N | Q86: Table-Comparison and Sorting | R86: N | U86: Tabel 2.2.1 Pertambangan Pertumbuhan Penjualan: 2023 Des = -5,66%; 2025 Sep = -4,94%. | V86: -4,9% is the Sep 2025 value, not 2023 (-5,66%). Data is a table lookup, not a chart calculation. | X86: Pertumbuhan penjualan sektor Pertambangan pada Desember 2023 adalah -5,66% (yoy) (Tabel 2.2.1). | Y86: 0 | Z86: 1 | AA86: 0 | AB86: 0 | AC86: 1 | AD86: 0 | AE86: 0 | AF86: 1 | AG86: 0 | AH86: 0
A87: QA0086 | B87: InternVL | C87: KSK-4626 | D87: 40 | E87: KSK-4626_p040.png | F87: 1 | G87: Chart-Time-Sensitive | H87: Chart | I87: Bagaimana mengukur profitabilitas korporasi pada tahun 2025? | J87: Pada tahun 2025, profitabilitas korporasi mengukur 4,67% (yoy) dengan menggunakan net profit margin. | K87: panjang | L87: REVISE | M87: Major | N87: Factual/Numerical | O87: Factual/Numerical, Typo/Grammar, Instruction-following | P87: N | Q87: Text-Text Inference | R87: N | U87: Text: profitabilitas korporasi tetap terjaga hingga Tw III 2025, tercermin dari ROE 9,24% (Tabel 2.2.1). 4,67% (yoy) is overall sales growth. | V87: Profitability is measured by ROE 9,24%, not 4,67% (that is sales growth); question is garbled. Evidence is text/table, not a chart trend. | W87: Bagaimana profitabilitas korporasi hingga triwulan III 2025? | X87: Profitabilitas korporasi tetap terjaga baik hingga triwulan III 2025, tercermin dari ROE sebesar 9,24%. | Y87: 0 | Z87: 1 | AA87: 0 | AB87: 0 | AC87: 0 | AD87: 0 | AE87: 0 | AF87: 1 | AG87: 0 | AH87: 1
A88: QA0087 | B88: InternVL | C88: KSK-4626 | D88: 40 | E88: KSK-4626_p040.png | F88: 2 | G88: Text-Text Inference | H88: Text | I88: Bagaimana pertumbuhan capex pertambangan pada tahun 2023? | J88: Pertumbuhan capex pertambangan pada tahun 2023 adalah -3,12% | K88: pendek | L88: REVISE | M88: Major | N88: Factual/Numerical | O88: Factual/Numerical, Instruction-following | P88: N | Q88: Table-Comparison and Sorting | R88: N | U88: Tabel 2.2.1 Pertambangan Pertumbuhan Capex 2023 Des = 35,40% (yoy). | V88: -3,12% does not appear; correct value is 35,40%. Value is in the table, not running text. | X88: Pertumbuhan capex sektor Pertambangan pada Desember 2023 adalah 35,40% (yoy). | Y88: 0 | Z88: 1 | AA88: 0 | AB88: 0 | AC88: 0 | AD88: 0 | AE88: 0 | AF88: 1 | AG88: 0 | AH88: 0
A89: QA0088 | B89: InternVL | C89: KSK-4626 | D89: 42 | E89: KSK-4626_p042.png | F89: 0 | G89: Chart-Information Extraction | H89: Chart | I89: Bagaimana perubahan kredit dalam 2023 dan 2024? | J89: Pertumbuhan kredit meningkat dari 4,729,59 miliar rupiah pada tahun 2023 menjadi 4,981,61 miliar rupiah pada tahun 2024. | K89: pendek | L89: REVISE | M89: Major | N89: Factual/Numerical | O89: Factual/Numerical, Unit, Instruction-following | P89: N | Q89: Table-Numerical Calculation | R89: N | U89: Tabel 2.2.2: Total Capital (Rp triliun) 4.729,59 (2023), 4.981,61 (2024); these are total capital, not credit. | V89: Values are corporate Total Capital in Rp triliun, not credit and not miliar; data come from a table, not a chart. | W89: Bagaimana perubahan total capital korporasi dari 2023 ke 2024? | X89: Total capital korporasi meningkat dari Rp4.729,59 triliun (2023) menjadi Rp4.981,61 triliun (2024), naik Rp252,02 triliun atau sekitar 5,33%. | Y89: 0 | Z89: 1 | AA89: 0 | AB89: 0 | AC89: 0 | AD89: 1 | AE89: 0 | AF89: 1 | AG89: 0 | AH89: 0
A90: QA0089 | B90: InternVL | C90: KSK-4626 | D90: 42 | E90: KSK-4626_p042.png | F90: 1 | G90: Chart-Time-Sensitive | H90: Chart | I90: Bagaimana perubahan kredit dalam 2025? | J90: Pertumbuhan kredit meningkat menjadi 5,338,03 miliar rupiah pada tahun 2025. | K90: pendek | L90: REVISE | M90: Major | N90: Factual/Numerical | O90: Factual/Numerical, Unit | P90: Y | Q90: Chart-Time-Sensitive | R90: N | U90: Grafik 2.2.8/text: kredit investasi 13,62% (akhir 2024) -> 21,06% yoy (akhir 2025); kredit modal kerja 8,35% -> 4,52% yoy. 5.338,03 = Total Capital Sep-2025 (Rp triliun). | V90: 5.338,03 is Total Capital (Rp triliun, Sep-2025) from the table, not credit and not miliar. The chart shows 2025 credit growth: investment accelerating, working capital slowing. | X90: Pada akhir 2025 pertumbuhan kredit investasi meningkat dari 13,62% menjadi 21,06% (yoy), sementara kredit modal kerja melambat dari 8,35% menjadi 4,52% (yoy). | Y90: 0 | Z90: 1 | AA90: 0 | AB90: 0 | AC90: 0 | AD90: 1 | AE90: 0 | AF90: 0 | AG90: 0 | AH90: 0
A91: QA0090 | B91: InternVL | C91: KSK-4626 | D91: 42 | E91: KSK-4626_p042.png | F91: 2 | G91: Chart-Numerical Calculation | H91: Chart | I91: Bagaimana perubahan kredit dalam 2023 dan 2024 dalam persen? | J91: Pertumbuhan kredit meningkat 64,4% pada tahun 2024 dibandingkan 63,3% pada tahun 2023. | K91: pendek | L91: REVISE | M91: Major | N91: Factual/Numerical | O91: Factual/Numerical, Instruction-following | P91: N | Q91: Table-Numerical Calculation | R91: N | U91: Tabel 2.2.2: Internal Financing (% Capital) 63,3 (2023), 64,4 (2024); Bank Debt (% Capital) 18,6 (2023), 18,5 (2024). | V91: 63,3% and 64,4% are internal financing shares of capital, not credit growth. Bank credit portion fell slightly 18,6% -> 18,5%. Data are in a table, not chart. | W91: Bagaimana perubahan porsi kredit bank (bank debt) terhadap capital korporasi dari 2023 ke 2024? | X91: Porsi bank debt turun tipis dari 18,6% capital (2023) menjadi 18,5% capital (2024), atau berkurang 0,1 poin persentase. | Y91: 0 | Z91: 1 | AA91: 0 | AB91: 0 | AC91: 0 | AD91: 0 | AE91: 0 | AF91: 1 | AG91: 0 | AH91: 0
A92: QA0091 | B92: InternVL | C92: Kajian Ekonomi dan Keuangan Regional Provinsi Bali November 2016 | D92: 26 | E92: Kajian 20Ekonomi 20dan 20Keuangan 20Regional 20Provinsi 20Bali 20November 202016_p026.png | F92: 0 | G92: Chart-Information Extraction | H92: Chart | I92: Pertumbuhan ekonomi Bali pada triwulan III 2016 sebesar berapa? | J92: 6.17% | K92: pendek | L92: REVISE | M92: Minor | N92: Format | O92: Format, Unit | P92: Y | Q92: Chart-Information Extraction | R92: N | U92: Grafik 1.1/1.2: Bali Tw III-2016 = 6,17 (%, yoy); text also 6,17% (yoy). | V92: The value is correct but given as a bare number with no yoy label or context. | X92: Pertumbuhan ekonomi Bali pada triwulan III 2016 sebesar 6,17% (yoy). | Y92: 0 | Z92: 0 | AA92: 0 | AB92: 0 | AC92: 0 | AD92: 1 | AE92: 0 | AF92: 0 | AG92: 1 | AH92: 0
A93: QA0092 | B93: InternVL | C93: Kajian Ekonomi dan Keuangan Regional Provinsi Bali November 2016 | D93: 26 | E93: Kajian 20Ekonomi 20dan 20Keuangan 20Regional 20Provinsi 20Bali 20November 202016_p026.png | F93: 1 | G93: Chart-Time-Sensitive | H93: Chart | I93: Pertumbuhan ekonomi nasional pada triwulan III 2016 sebesar berapa? | J93: 5.02% | K93: pendek | L93: REVISE | M93: Minor | N93: Instruction-following | O93: Instruction-following, Format, Unit | P93: N | Q93: Chart-Information Extraction | R93: N | U93: Grafik 1.2: NASIONAL Tw III-2016 = 5,02; text: pertumbuhan ekonomi nasional 5,02% (yoy). | V93: The value is correct, but this is a single-point extraction, not a time-sensitive task. It is also a bare number. | X93: Pertumbuhan ekonomi nasional pada triwulan III 2016 sebesar 5,02% (yoy). | Y93: 0 | Z93: 0 | AA93: 0 | AB93: 0 | AC93: 0 | AD93: 1 | AE93: 0 | AF93: 1 | AG93: 1 | AH93: 0
A94: QA0093 | B94: InternVL | C94: Kajian Ekonomi dan Keuangan Regional Provinsi Bali November 2016 | D94: 26 | E94: Kajian 20Ekonomi 20dan 20Keuangan 20Regional 20Provinsi 20Bali 20November 202016_p026.png | F94: 2 | G94: Text-Text Inference | H94: Text | I94: Pertumbuhan ekonomi Bali terhadap pertumbuhan nasional pada triwulan III 2016 sebesar berapa? | J94: 6.17% dibandingkan 5.02% | K94: panjang | L94: REVISE | M94: Minor | N94: Typo/Grammar | O94: Typo/Grammar, Format | P94: Y | Q94: Text-Text Inference | R94: Y | U94: Text: Bali Tw III-2016 tumbuh 6,17% (yoy), masih lebih tinggi dibandingkan nasional 5,02% (yoy). | V94: The values are correct, but the question is awkward ('terhadap ... sebesar berapa') and the answer lacks a comparison statement and the yoy unit. | W94: Bagaimana pertumbuhan ekonomi Bali dibandingkan pertumbuhan nasional pada triwulan III 2016? | X94: Pertumbuhan ekonomi Bali pada triwulan III 2016 sebesar 6,17% (yoy), lebih tinggi dibandingkan pertumbuhan ekonomi nasional yang sebesar 5,02% (yoy). | Y94: 0 | Z94: 0 | AA94: 0 | AB94: 0 | AC94: 0 | AD94: 0 | AE94: 0 | AF94: 0 | AG94: 1 | AH94: 1
A95: QA0094 | B95: InternVL | C95: Kajian Ekonomi dan Keuangan Regional Provinsi Bali November 2016 | D95: 35 | E95: Kajian 20Ekonomi 20dan 20Keuangan 20Regional 20Provinsi 20Bali 20November 202016_p035.png | F95: 0 | G95: Text-Text Inference | H95: Text | I95: Bagaimana pertumbuhan nilai impor Bali pada tahun 2016? | J95: Pertumbuhan nilai impor Bali pada tahun 2016 sebesar 26,95% (yoy). | K95: pendek | L95: REVISE | M95: Major | N95: Temporal | O95: Temporal, Factual/Numerical | P95: Y | Q95: Text-Text Inference | R95: N | U95: Text: nilai impor luar negeri Tw III 2016 tumbuh 38,62% (yoy), lebih tinggi dari Tw II 2016 26,95% (yoy). | V95: 26,95% is the Tw II 2016 figure; latest (Tw III 2016) growth is 38,62%. Question's 'tahun 2016' is imprecise. | W95: Bagaimana pertumbuhan nilai impor luar negeri Bali pada triwulan III 2016? | X95: Pertumbuhan nilai impor luar negeri Bali pada triwulan III 2016 sebesar 38,62% (yoy), lebih tinggi dibanding triwulan II 2016 sebesar 26,95% (yoy). | Y95: 0 | Z95: 1 | AA95: 0 | AB95: 0 | AC95: 1 | AD95: 0 | AE95: 0 | AF95: 0 | AG95: 0 | AH95: 0
A96: QA0095 | B96: InternVL | C96: Kajian Ekonomi dan Keuangan Regional Provinsi Bali November 2016 | D96: 35 | E96: Kajian 20Ekonomi 20dan 20Keuangan 20Regional 20Provinsi 20Bali 20November 202016_p035.png | F96: 1 | G96: Chart-Information Extraction | H96: Chart | I96: Bagaimana kontribusi raw material dan konsumsi pada impor Bali pada tahun 2016? | J96: Raw material dan konsumsi mengkontribusi sebesar 57% dan 5% pada impor Bali pada tahun 2016. | K96: panjang | L96: PASS | M96: None | N96: None | P96: Y | Q96: Chart-Information Extraction | R96: Y | U96: Grafik 1.27 Pangsa Impor BEC: Raw Material & Auxiliary Goods 57%, Consumption Goods 5%, Capital Goods 14%. | V96: Values match the donut chart labels. | Y96: 0 | Z96: 0 | AA96: 0 | AB96: 0 | AC96: 0 | AD96: 0 | AE96: 0 | AF96: 0 | AG96: 0 | AH96: 0
A97: QA0096 | B97: InternVL | C97: Kajian Ekonomi dan Keuangan Regional Provinsi Bali November 2016 | D97: 35 | E97: Kajian 20Ekonomi 20dan 20Keuangan 20Regional 20Provinsi 20Bali 20November 202016_p035.png | F97: 2 | G97: Chart-Numerical Calculation | H97: Chart | I97: Bagaimana pertumbuhan impor raw material dan konsumsi pada tahun 2016? | J97: Pertumbuhan impor raw material sebesar 10,73% (yoy) dan konsumsi sebesar 0,35% (yoy) pada tahun 2016. | K97: pendek | L97: REVISE | M97: Major | N97: Factual/Numerical | O97: Factual/Numerical, Instruction-following | P97: N | Q97: Text-Text Inference | R97: N | U97: Text: raw material tumbuh 10,73% (yoy) Tw III 2016 (Tw II 0,35%); barang konsumsi Tw III 2016 tumbuh 4,18% (yoy) vs -34,36%. | V97: Raw material 10,73% correct, but 0,35% is raw material's Tw II rate; consumption grew 4,18% in Tw III 2016. Values are from text, no calculation. | W97: Bagaimana pertumbuhan impor raw material dan barang konsumsi Bali pada triwulan III 2016? | X97: Impor raw material tumbuh 10,73% (yoy) dan impor barang konsumsi tumbuh 4,18% (yoy) pada triwulan III 2016. | Y97: 0 | Z97: 1 | AA97: 0 | AB97: 0 | AC97: 0 | AD97: 0 | AE97: 0 | AF97: 1 | AG97: 0 | AH97: 0
A98: QA0097 | B98: InternVL | C98: Kajian Ekonomi dan Keuangan Regional Provinsi Bali November 2016 | D98: 39 | E98: Kajian 20Ekonomi 20dan 20Keuangan 20Regional 20Provinsi 20Bali 20November 202016_p039.png | F98: 0 | G98: Text-Text Inference | H98: Text | I98: Bagaimana perkembangan ekonomi Macroeconomi pada triwulan III 2016? | J98: Perkembangan ekonomi Macroeconomi pada triwulan III 2016 menunjukkan perubahan dengan Inggris dan Jerman masuk ke dalam lima negara asal wisman dengan share masing-masing sebesar 5% dan 4%. | K98: pendek | L98: REVISE | M98: Minor | N98: Typo/Grammar | O98: Typo/Grammar | P98: Y | Q98: Text-Text Inference | R98: Y | U98: Text: perkembangan negara asal wisman Tw III 2016 menunjukkan perubahan dengan Inggris dan Jerman masuk lima negara utama asal wisman, share 5% dan 4%. | V98: Answer fact is correct, but the question is garbled ('ekonomi Macroeconomi') and does not match the answer's topic (negara asal wisman). | W98: Bagaimana perkembangan negara asal wisman ke Bali pada triwulan III 2016? | X98: Terjadi perubahan, yaitu Inggris dan Jerman masuk ke dalam lima negara utama asal wisman dengan share masing-masing 5% dan 4%. | Y98: 0 | Z98: 0 | AA98: 0 | AB98: 0 | AC98: 0 | AD98: 0 | AE98: 0 | AF98: 0 | AG98: 0 | AH98: 1
A99: QA0098 | B99: InternVL | C99: Kajian Ekonomi dan Keuangan Regional Provinsi Bali November 2016 | D99: 39 | E99: Kajian 20Ekonomi 20dan 20Keuangan 20Regional 20Provinsi 20Bali 20November 202016_p039.png | F99: 1 | G99: Chart-Time-Sensitive | H99: Chart | I99: Bagaimana perkembangan negara asal wisman pada triwulan IV 2016? | J99: Pertumbuhan negara asal wisman pada triwulan IV 2016 meningkat dengan Amerika Serikat, Jerman, dan Jepang, dengan peningkatan sebesar 5% dan 4%. | K99: panjang | L99: DISCARD | M99: Critical | N99: Hallucination | O99: Hallucination, Temporal, Factual/Numerical | P99: N | Q99: Chart-Time-Sensitive | R99: N | S99: Period/time comparison not on page | T99: Fabricated value/claim (not on page) | U99: Grafik 1.34/1.35 and text cover wisman origins only through Tw III 2016; Tw IV 2016 only mentioned for akomodasi outlook. USA share only 3%. | V99: No Tw IV 2016 wisman-origin data on the page; answer invents a rise for USA/Germany/Japan. | Y99: 1 | Z99: 1 | AA99: 0 | AB99: 0 | AC99: 1 | AD99: 0 | AE99: 0 | AF99: 0 | AG99: 0 | AH99: 0
A100: QA0099 | B100: InternVL | C100: Kajian Ekonomi dan Keuangan Regional Provinsi Bali November 2016 | D100: 39 | E100: Kajian 20Ekonomi 20dan 20Keuangan 20Regional 20Provinsi 20Bali 20November 202016_p039.png | F100: 2 | G100: Chart-Numerical Calculation | H100: Chart | I100: Bagaimana perkembangan negara asal wisman pada triwulan II 2016? | J100: Pertumbuhan negara asal wisman pada triwulan II 2016 meningkat dengan Amerika Serikat, Jerman, dan Jepang, dengan peningkatan sebesar 21,84% (yoy). | K100: pendek | L100: REVISE | M100: Major | N100: Factual/Numerical | O100: Factual/Numerical, Instruction-following | P100: N | Q100: Text-Text Inference | R100: N | U100: Text: total wisman Tw II 2016 tumbuh 21,84% (yoy); Australia 17,97% (yoy) Tw II 2016; Jerman 26,19% (yoy) Tw II 2016. Grafik 1.34 has country series. | V100: 21,84% is total wisman growth, not USA/Germany/Japan; USA is not in Grafik 1.34. No calculation involved. | X100: Pada triwulan II 2016 kunjungan wisman tumbuh 21,84% (yoy); wisman Australia tumbuh 17,97% (yoy) dan wisman Jerman 26,19% (yoy). | Y100: 0 | Z100: 1 | AA100: 0 | AB100: 0 | AC100: 0 | AD100: 0 | AE100: 0 | AF100: 1 | AG100: 0 | AH100: 0
...

Sheet By_Category
A1: Metrics per QA category and modality (Text / Chart / Table)
A2: Category = category assigned by the generator. Rates are % of QA in that row.
A4: Model | B4: Group | C4: Category / Modality | D4: N | E4: PASS | F4: REVISE | G4: DISCARD | H4: Content correct | I4: QA Accuracy | J4: Revision Rate | K4: Discard Rate | L4: FPY | M4: Error Rate | N4: Minor | O4: Major | P4: Critical | Q4: Category label correct % | R4: Top error: Factual/Numerical | S4: Reasoning | T4: Temporal | U4: Calculation | V4: Incomplete | W4: Unit | X4: Instruction-following | Y4: Typo/Grammar | Z4: Format | AA4: Hallucination
A5: InternVL | B5: Modality | C5: Text | D5: =COUNTIFS(QA_Detail!$B$2:$B$988,"InternVL",QA_Detail!$H$2:$H$988,"Text") -> 149 | E5: =COUNTIFS(QA_Detail!$B$2:$B$988,"InternVL",QA_Detail!$H$2:$H$988,"Text",QA_Detail!$L$2:$L$988,"PASS") -> 15 | F5: =COUNTIFS(QA_Detail!$B$2:$B$988,"InternVL",QA_Detail!$H$2:$H$988,"Text",QA_Detail!$L$2:$L$988,"REVISE") -> 119 | G5: =COUNTIFS(QA_Detail!$B$2:$B$988,"InternVL",QA_Detail!$H$2:$H$988,"Text",QA_Detail!$L$2:$L$988,"DISCARD") -> 15 | H5: =COUNTIFS(QA_Detail!$B$2:$B$988,"InternVL",QA_Detail!$H$2:$H$988,"Text",QA_Detail!$R$2:$R$988,"Y") -> 27 | I5: =IFERROR(H5/D5,"-") -> 0.18120805 | J5: =IFERROR(F5/D5,"-") -> 0.79865772 | K5: =IFERROR(G5/D5,"-") -> 0.10067114 | L5: =IFERROR(E5/D5,"-") -> 0.10067114 | M5: =IFERROR((F5+G5)/D5,"-") -> 0.89932886 | N5: =COUNTIFS(QA_Detail!$B$2:$B$988,"InternVL",QA_Detail!$H$2:$H$988,"Text",QA_Detail!$M$2:$M$988,"Minor") -> 31 | O5: =COUNTIFS(QA_Detail!$B$2:$B$988,"InternVL",QA_Detail!$H$2:$H$988,"Text",QA_Detail!$M$2:$M$988,"Major") -> 88 | P5: =COUNTIFS(QA_Detail!$B$2:$B$988,"InternVL",QA_Detail!$H$2:$H$988,"Text",QA_Detail!$M$2:$M$988,"Critical") -> 15 | Q5: =IFERROR(COUNTIFS(QA_Detail!$B$2:$B$988,"InternVL",QA_Detail!$H$2:$H$988,"Text",QA_Detail!$P$2:$P$988,"Y")/D5,"-") -> 0.68456376 | R5: =COUNTIFS(QA_Detail!$B$2:$B$988,"InternVL",QA_Detail!$H$2:$H$988,"Text",QA_Detail!$N$2:$N$988,"Factual/Numerical") -> 65 | S5: =COUNTIFS(QA_Detail!$B$2:$B$988,"InternVL",QA_Detail!$H$2:$H$988,"Text",QA_Detail!$N$2:$N$988,"Reasoning") -> 17 | T5: =COUNTIFS(QA_Detail!$B$2:$B$988,"InternVL",QA_Detail!$H$2:$H$988,"Text",QA_Detail!$N$2:$N$988,"Temporal") -> 11 | U5: =COUNTIFS(QA_Detail!$B$2:$B$988,"InternVL",QA_Detail!$H$2:$H$988,"Text",QA_Detail!$N$2:$N$988,"Calculation") -> 1 | V5: =COUNTIFS(QA_Detail!$B$2:$B$988,"InternVL",QA_Detail!$H$2:$H$988,"Text",QA_Detail!$N$2:$N$988,"Incomplete") -> 3 | W5: =COUNTIFS(QA_Detail!$B$2:$B$988,"InternVL",QA_Detail!$H$2:$H$988,"Text",QA_Detail!$N$2:$N$988,"Unit") -> 1 | X5: =COUNTIFS(QA_Detail!$B$2:$B$988,"InternVL",QA_Detail!$H$2:$H$988,"Text",QA_Detail!$N$2:$N$988,"Instruction-following") -> 1 | Y5: =COUNTIFS(QA_Detail!$B$2:$B$988,"InternVL",QA_Detail!$H$2:$H$988,"Text",QA_Detail!$N$2:$N$988,"Typo/Grammar") -> 18 | Z5: =COUNTIFS(QA_Detail!$B$2:$B$988,"InternVL",QA_Detail!$H$2:$H$988,"Text",QA_Detail!$N$2:$N$988,"Format") -> 2 | AA5: =COUNTIFS(QA_Detail!$B$2:$B$988,"InternVL",QA_Detail!$H$2:$H$988,"Text",QA_Detail!$N$2:$N$988,"Hallucination") -> 15
A6: InternVL | B6: Modality | C6: Chart | D6: =COUNTIFS(QA_Detail!$B$2:$B$988,"InternVL",QA_Detail!$H$2:$H$988,"Chart") -> 307 | E6: =COUNTIFS(QA_Detail!$B$2:$B$988,"InternVL",QA_Detail!$H$2:$H$988,"Chart",QA_Detail!$L$2:$L$988,"PASS") -> 3 | F6: =COUNTIFS(QA_Detail!$B$2:$B$988,"InternVL",QA_Detail!$H$2:$H$988,"Chart",QA_Detail!$L$2:$L$988,"REVISE") -> 269 | G6: =COUNTIFS(QA_Detail!$B$2:$B$988,"InternVL",QA_Detail!$H$2:$H$988,"Chart",QA_Detail!$L$2:$L$988,"DISCARD") -> 35 | H6: =COUNTIFS(QA_Detail!$B$2:$B$988,"InternVL",QA_Detail!$H$2:$H$988,"Chart",QA_Detail!$R$2:$R$988,"Y") -> 30 | I6: =IFERROR(H6/D6,"-") -> 0.09771987 | J6: =IFERROR(F6/D6,"-") -> 0.8762215 | K6: =IFERROR(G6/D6,"-") -> 0.11400651 | L6: =IFERROR(E6/D6,"-") -> 0.009771987 | M6: =IFERROR((F6+G6)/D6,"-") -> 0.99022801 | N6: =COUNTIFS(QA_Detail!$B$2:$B$988,"InternVL",QA_Detail!$H$2:$H$988,"Chart",QA_Detail!$M$2:$M$988,"Minor") -> 68 | O6: =COUNTIFS(QA_Detail!$B$2:$B$988,"InternVL",QA_Detail!$H$2:$H$988,"Chart",QA_Detail!$M$2:$M$988,"Major") -> 201 | P6: =COUNTIFS(QA_Detail!$B$2:$B$988,"InternVL",QA_Detail!$H$2:$H$988,"Chart",QA_Detail!$M$2:$M$988,"Critical") -> 35 | Q6: =IFERROR(COUNTIFS(QA_Detail!$B$2:$B$988,"InternVL",QA_Detail!$H$2:$H$988,"Chart",QA_Detail!$P$2:$P$988,"Y")/D6,"-") -> 0.16612378 | R6: =COUNTIFS(QA_Detail!$B$2:$B$988,"InternVL",QA_Detail!$H$2:$H$988,"Chart",QA_Detail!$N$2:$N$988,"Factual/Numerical") -> 148 | S6: =COUNTIFS(QA_Detail!$B$2:$B$988,"InternVL",QA_Detail!$H$2:$H$988,"Chart",QA_Detail!$N$2:$N$988,"Reasoning") -> 27 | T6: =COUNTIFS(QA_Detail!$B$2:$B$988,"InternVL",QA_Detail!$H$2:$H$988,"Chart",QA_Detail!$N$2:$N$988,"Temporal") -> 24 | U6: =COUNTIFS(QA_Detail!$B$2:$B$988,"InternVL",QA_Detail!$H$2:$H$988,"Chart",QA_Detail!$N$2:$N$988,"Calculation") -> 6 | V6: =COUNTIFS(QA_Detail!$B$2:$B$988,"InternVL",QA_Detail!$H$2:$H$988,"Chart",QA_Detail!$N$2:$N$988,"Incomplete") -> 8 | W6: =COUNTIFS(QA_Detail!$B$2:$B$988,"InternVL",QA_Detail!$H$2:$H$988,"Chart",QA_Detail!$N$2:$N$988,"Unit") -> 3 | X6: =COUNTIFS(QA_Detail!$B$2:$B$988,"InternVL",QA_Detail!$H$2:$H$988,"Chart",QA_Detail!$N$2:$N$988,"Instruction-following") -> 35 | Y6: =COUNTIFS(QA_Detail!$B$2:$B$988,"InternVL",QA_Detail!$H$2:$H$988,"Chart",QA_Detail!$N$2:$N$988,"Typo/Grammar") -> 15 | Z6: =COUNTIFS(QA_Detail!$B$2:$B$988,"InternVL",QA_Detail!$H$2:$H$988,"Chart",QA_Detail!$N$2:$N$988,"Format") -> 3 | AA6: =COUNTIFS(QA_Detail!$B$2:$B$988,"InternVL",QA_Detail!$H$2:$H$988,"Chart",QA_Detail!$N$2:$N$988,"Hallucination") -> 35
A7: InternVL | B7: Modality | C7: Table | D7: =COUNTIFS(QA_Detail!$B$2:$B$988,"InternVL",QA_Detail!$H$2:$H$988,"Table") -> 39 | E7: =COUNTIFS(QA_Detail!$B$2:$B$988,"InternVL",QA_Detail!$H$2:$H$988,"Table",QA_Detail!$L$2:$L$988,"PASS") -> 0 | F7: =COUNTIFS(QA_Detail!$B$2:$B$988,"InternVL",QA_Detail!$H$2:$H$988,"Table",QA_Detail!$L$2:$L$988,"REVISE") -> 35 | G7: =COUNTIFS(QA_Detail!$B$2:$B$988,"InternVL",QA_Detail!$H$2:$H$988,"Table",QA_Detail!$L$2:$L$988,"DISCARD") -> 4 | H7: =COUNTIFS(QA_Detail!$B$2:$B$988,"InternVL",QA_Detail!$H$2:$H$988,"Table",QA_Detail!$R$2:$R$988,"Y") -> 7 | I7: =IFERROR(H7/D7,"-") -> 0.17948718 | J7: =IFERROR(F7/D7,"-") -> 0.8974359 | K7: =IFERROR(G7/D7,"-") -> 0.1025641 | L7: =IFERROR(E7/D7,"-") -> 0 | M7: =IFERROR((F7+G7)/D7,"-") -> 1 | N7: =COUNTIFS(QA_Detail!$B$2:$B$988,"InternVL",QA_Detail!$H$2:$H$988,"Table",QA_Detail!$M$2:$M$988,"Minor") -> 9 | O7: =COUNTIFS(QA_Detail!$B$2:$B$988,"InternVL",QA_Detail!$H$2:$H$988,"Table",QA_Detail!$M$2:$M$988,"Major") -> 26 | P7: =COUNTIFS(QA_Detail!$B$2:$B$988,"InternVL",QA_Detail!$H$2:$H$988,"Table",QA_Detail!$M$2:$M$988,"Critical") -> 4 | Q7: =IFERROR(COUNTIFS(QA_Detail!$B$2:$B$988,"InternVL",QA_Detail!$H$2:$H$988,"Table",QA_Detail!$P$2:$P$988,"Y")/D7,"-") -> 0.43589744 | R7: =COUNTIFS(QA_Detail!$B$2:$B$988,"InternVL",QA_Detail!$H$2:$H$988,"Table",QA_Detail!$N$2:$N$988,"Factual/Numerical") -> 21 | S7: =COUNTIFS(QA_Detail!$B$2:$B$988,"InternVL",QA_Detail!$H$2:$H$988,"Table",QA_Detail!$N$2:$N$988,"Reasoning") -> 2 | T7: =COUNTIFS(QA_Detail!$B$2:$B$988,"InternVL",QA_Detail!$H$2:$H$988,"Table",QA_Detail!$N$2:$N$988,"Temporal") -> 2 | U7: =COUNTIFS(QA_Detail!$B$2:$B$988,"InternVL",QA_Detail!$H$2:$H$988,"Table",QA_Detail!$N$2:$N$988,"Calculation") -> 1 | V7: =COUNTIFS(QA_Detail!$B$2:$B$988,"InternVL",QA_Detail!$H$2:$H$988,"Table",QA_Detail!$N$2:$N$988,"Incomplete") -> 0 | W7: =COUNTIFS(QA_Detail!$B$2:$B$988,"InternVL",QA_Detail!$H$2:$H$988,"Table",QA_Detail!$N$2:$N$988,"Unit") -> 0 | X7: =COUNTIFS(QA_Detail!$B$2:$B$988,"InternVL",QA_Detail!$H$2:$H$988,"Table",QA_Detail!$N$2:$N$988,"Instruction-following") -> 5 | Y7: =COUNTIFS(QA_Detail!$B$2:$B$988,"InternVL",QA_Detail!$H$2:$H$988,"Table",QA_Detail!$N$2:$N$988,"Typo/Grammar") -> 3 | Z7: =COUNTIFS(QA_Detail!$B$2:$B$988,"InternVL",QA_Detail!$H$2:$H$988,"Table",QA_Detail!$N$2:$N$988,"Format") -> 1 | AA7: =COUNTIFS(QA_Detail!$B$2:$B$988,"InternVL",QA_Detail!$H$2:$H$988,"Table",QA_Detail!$N$2:$N$988,"Hallucination") -> 4
A8: InternVL | B8: Category | C8: Text-Text Inference | D8: =COUNTIFS(QA_Detail!$B$2:$B$988,"InternVL",QA_Detail!$G$2:$G$988,"Text-Text Inference") -> 149 | E8: =COUNTIFS(QA_Detail!$B$2:$B$988,"InternVL",QA_Detail!$G$2:$G$988,"Text-Text Inference",QA_Detail!$L$2:$L$988,"PASS") -> 15 | F8: =COUNTIFS(QA_Detail!$B$2:$B$988,"InternVL",QA_Detail!$G$2:$G$988,"Text-Text Inference",QA_Detail!$L$2:$L$988,"REVISE") -> 119 | G8: =COUNTIFS(QA_Detail!$B$2:$B$988,"InternVL",QA_Detail!$G$2:$G$988,"Text-Text Inference",QA_Detail!$L$2:$L$988,"DISCARD") -> 15 | H8: =COUNTIFS(QA_Detail!$B$2:$B$988,"InternVL",QA_Detail!$G$2:$G$988,"Text-Text Inference",QA_Detail!$R$2:$R$988,"Y") -> 27 | I8: =IFERROR(H8/D8,"-") -> 0.18120805 | J8: =IFERROR(F8/D8,"-") -> 0.79865772 | K8: =IFERROR(G8/D8,"-") -> 0.10067114 | L8: =IFERROR(E8/D8,"-") -> 0.10067114 | M8: =IFERROR((F8+G8)/D8,"-") -> 0.89932886 | N8: =COUNTIFS(QA_Detail!$B$2:$B$988,"InternVL",QA_Detail!$G$2:$G$988,"Text-Text Inference",QA_Detail!$M$2:$M$988,"Minor") -> 31 | O8: =COUNTIFS(QA_Detail!$B$2:$B$988,"InternVL",QA_Detail!$G$2:$G$988,"Text-Text Inference",QA_Detail!$M$2:$M$988,"Major") -> 88 | P8: =COUNTIFS(QA_Detail!$B$2:$B$988,"InternVL",QA_Detail!$G$2:$G$988,"Text-Text Inference",QA_Detail!$M$2:$M$988,"Critical") -> 15 | Q8: =IFERROR(COUNTIFS(QA_Detail!$B$2:$B$988,"InternVL",QA_Detail!$G$2:$G$988,"Text-Text Inference",QA_Detail!$P$2:$P$988,"Y")/D8,"-") -> 0.68456376 | R8: =COUNTIFS(QA_Detail!$B$2:$B$988,"InternVL",QA_Detail!$G$2:$G$988,"Text-Text Inference",QA_Detail!$N$2:$N$988,"Factual/Numerical") -> 65 | S8: =COUNTIFS(QA_Detail!$B$2:$B$988,"InternVL",QA_Detail!$G$2:$G$988,"Text-Text Inference",QA_Detail!$N$2:$N$988,"Reasoning") -> 17 | T8: =COUNTIFS(QA_Detail!$B$2:$B$988,"InternVL",QA_Detail!$G$2:$G$988,"Text-Text Inference",QA_Detail!$N$2:$N$988,"Temporal") -> 11 | U8: =COUNTIFS(QA_Detail!$B$2:$B$988,"InternVL",QA_Detail!$G$2:$G$988,"Text-Text Inference",QA_Detail!$N$2:$N$988,"Calculation") -> 1 | V8: =COUNTIFS(QA_Detail!$B$2:$B$988,"InternVL",QA_Detail!$G$2:$G$988,"Text-Text Inference",QA_Detail!$N$2:$N$988,"Incomplete") -> 3 | W8: =COUNTIFS(QA_Detail!$B$2:$B$988,"InternVL",QA_Detail!$G$2:$G$988,"Text-Text Inference",QA_Detail!$N$2:$N$988,"Unit") -> 1 | X8: =COUNTIFS(QA_Detail!$B$2:$B$988,"InternVL",QA_Detail!$G$2:$G$988,"Text-Text Inference",QA_Detail!$N$2:$N$988,"Instruction-following") -> 1 | Y8: =COUNTIFS(QA_Detail!$B$2:$B$988,"InternVL",QA_Detail!$G$2:$G$988,"Text-Text Inference",QA_Detail!$N$2:$N$988,"Typo/Grammar") -> 18 | Z8: =COUNTIFS(QA_Detail!$B$2:$B$988,"InternVL",QA_Detail!$G$2:$G$988,"Text-Text Inference",QA_Detail!$N$2:$N$988,"Format") -> 2 | AA8: =COUNTIFS(QA_Detail!$B$2:$B$988,"InternVL",QA_Detail!$G$2:$G$988,"Text-Text Inference",QA_Detail!$N$2:$N$988,"Hallucination") -> 15
A9: InternVL | B9: Category | C9: Chart-Information Extraction | D9: =COUNTIFS(QA_Detail!$B$2:$B$988,"InternVL",QA_Detail!$G$2:$G$988,"Chart-Information Extraction") -> 113 | E9: =COUNTIFS(QA_Detail!$B$2:$B$988,"InternVL",QA_Detail!$G$2:$G$988,"Chart-Information Extraction",QA_Detail!$L$2:$L$988,"PASS") -> 2 | F9: =COUNTIFS(QA_Detail!$B$2:$B$988,"InternVL",QA_Detail!$G$2:$G$988,"Chart-Information Extraction",QA_Detail!$L$2:$L$988,"REVISE") -> 94 | G9: =COUNTIFS(QA_Detail!$B$2:$B$988,"InternVL",QA_Detail!$G$2:$G$988,"Chart-Information Extraction",QA_Detail!$L$2:$L$988,"DISCARD") -> 17 | H9: =COUNTIFS(QA_Detail!$B$2:$B$988,"InternVL",QA_Detail!$G$2:$G$988,"Chart-Information Extraction",QA_Detail!$R$2:$R$988,"Y") -> 13 | I9: =IFERROR(H9/D9,"-") -> 0.11504425 | J9: =IFERROR(F9/D9,"-") -> 0.83185841 | K9: =IFERROR(G9/D9,"-") -> 0.15044248 | L9: =IFERROR(E9/D9,"-") -> 0.017699115 | M9: =IFERROR((F9+G9)/D9,"-") -> 0.98230088 | N9: =COUNTIFS(QA_Detail!$B$2:$B$988,"InternVL",QA_Detail!$G$2:$G$988,"Chart-Information Extraction",QA_Detail!$M$2:$M$988,"Minor") -> 27 | O9: =COUNTIFS(QA_Detail!$B$2:$B$988,"InternVL",QA_Detail!$G$2:$G$988,"Chart-Information Extraction",QA_Detail!$M$2:$M$988,"Major") -> 67 | P9: =COUNTIFS(QA_Detail!$B$2:$B$988,"InternVL",QA_Detail!$G$2:$G$988,"Chart-Information Extraction",QA_Detail!$M$2:$M$988,"Critical") -> 17 | Q9: =IFERROR(COUNTIFS(QA_Detail!$B$2:$B$988,"InternVL",QA_Detail!$G$2:$G$988,"Chart-Information Extraction",QA_Detail!$P$2:$P$988,"Y")/D9,"-") -> 0.21238938 | R9: =COUNTIFS(QA_Detail!$B$2:$B$988,"InternVL",QA_Detail!$G$2:$G$988,"Chart-Information Extraction",QA_Detail!$N$2:$N$988,"Factual/Numerical") -> 53 | S9: =COUNTIFS(QA_Detail!$B$2:$B$988,"InternVL",QA_Detail!$G$2:$G$988,"Chart-Information Extraction",QA_Detail!$N$2:$N$988,"Reasoning") -> 8 | T9: =COUNTIFS(QA_Detail!$B$2:$B$988,"InternVL",QA_Detail!$G$2:$G$988,"Chart-Information Extraction",QA_Detail!$N$2:$N$988,"Temporal") -> 4 | U9: =COUNTIFS(QA_Detail!$B$2:$B$988,"InternVL",QA_Detail!$G$2:$G$988,"Chart-Information Extraction",QA_Detail!$N$2:$N$988,"Calculation") -> 1 | V9: =COUNTIFS(QA_Detail!$B$2:$B$988,"InternVL",QA_Detail!$G$2:$G$988,"Chart-Information Extraction",QA_Detail!$N$2:$N$988,"Incomplete") -> 5 | W9: =COUNTIFS(QA_Detail!$B$2:$B$988,"InternVL",QA_Detail!$G$2:$G$988,"Chart-Information Extraction",QA_Detail!$N$2:$N$988,"Unit") -> 1 | X9: =COUNTIFS(QA_Detail!$B$2:$B$988,"InternVL",QA_Detail!$G$2:$G$988,"Chart-Information Extraction",QA_Detail!$N$2:$N$988,"Instruction-following") -> 13 | Y9: =COUNTIFS(QA_Detail!$B$2:$B$988,"InternVL",QA_Detail!$G$2:$G$988,"Chart-Information Extraction",QA_Detail!$N$2:$N$988,"Typo/Grammar") -> 6 | Z9: =COUNTIFS(QA_Detail!$B$2:$B$988,"InternVL",QA_Detail!$G$2:$G$988,"Chart-Information Extraction",QA_Detail!$N$2:$N$988,"Format") -> 3 | AA9: =COUNTIFS(QA_Detail!$B$2:$B$988,"InternVL",QA_Detail!$G$2:$G$988,"Chart-Information Extraction",QA_Detail!$N$2:$N$988,"Hallucination") -> 17
A10: InternVL | B10: Category | C10: Chart-Numerical Calculation | D10: =COUNTIFS(QA_Detail!$B$2:$B$988,"InternVL",QA_Detail!$G$2:$G$988,"Chart-Numerical Calculation") -> 128 | E10: =COUNTIFS(QA_Detail!$B$2:$B$988,"InternVL",QA_Detail!$G$2:$G$988,"Chart-Numerical Calculation",QA_Detail!$L$2:$L$988,"PASS") -> 0 | F10: =COUNTIFS(QA_Detail!$B$2:$B$988,"InternVL",QA_Detail!$G$2:$G$988,"Chart-Numerical Calculation",QA_Detail!$L$2:$L$988,"REVISE") -> 118 | G10: =COUNTIFS(QA_Detail!$B$2:$B$988,"InternVL",QA_Detail!$G$2:$G$988,"Chart-Numerical Calculation",QA_Detail!$L$2:$L$988,"DISCARD") -> 10 | H10: =COUNTIFS(QA_Detail!$B$2:$B$988,"InternVL",QA_Detail!$G$2:$G$988,"Chart-Numerical Calculation",QA_Detail!$R$2:$R$988,"Y") -> 15 | I10: =IFERROR(H10/D10,"-") -> 0.1171875 | J10: =IFERROR(F10/D10,"-") -> 0.921875 | K10: =IFERROR(G10/D10,"-") -> 0.078125 | L10: =IFERROR(E10/D10,"-") -> 0 | M10: =IFERROR((F10+G10)/D10,"-") -> 1 | N10: =COUNTIFS(QA_Detail!$B$2:$B$988,"InternVL",QA_Detail!$G$2:$G$988,"Chart-Numerical Calculation",QA_Detail!$M$2:$M$988,"Minor") -> 33 | O10: =COUNTIFS(QA_Detail!$B$2:$B$988,"InternVL",QA_Detail!$G$2:$G$988,"Chart-Numerical Calculation",QA_Detail!$M$2:$M$988,"Major") -> 85 | P10: =COUNTIFS(QA_Detail!$B$2:$B$988,"InternVL",QA_Detail!$G$2:$G$988,"Chart-Numerical Calculation",QA_Detail!$M$2:$M$988,"Critical") -> 10 | Q10: =IFERROR(COUNTIFS(QA_Detail!$B$2:$B$988,"InternVL",QA_Detail!$G$2:$G$988,"Chart-Numerical Calculation",QA_Detail!$P$2:$P$988,"Y")/D10,"-") -> 0.0703125 | R10: =COUNTIFS(QA_Detail!$B$2:$B$988,"InternVL",QA_Detail!$G$2:$G$988,"Chart-Numerical Calculation",QA_Detail!$N$2:$N$988,"Factual/Numerical") -> 58 | S10: =COUNTIFS(QA_Detail!$B$2:$B$988,"InternVL",QA_Detail!$G$2:$G$988,"Chart-Numerical Calculation",QA_Detail!$N$2:$N$988,"Reasoning") -> 15 | T10: =COUNTIFS(QA_Detail!$B$2:$B$988,"InternVL",QA_Detail!$G$2:$G$988,"Chart-Numerical Calculation",QA_Detail!$N$2:$N$988,"Temporal") -> 13 | U10: =COUNTIFS(QA_Detail!$B$2:$B$988,"InternVL",QA_Detail!$G$2:$G$988,"Chart-Numerical Calculation",QA_Detail!$N$2:$N$988,"Calculation") -> 3 | V10: =COUNTIFS(QA_Detail!$B$2:$B$988,"InternVL",QA_Detail!$G$2:$G$988,"Chart-Numerical Calculation",QA_Detail!$N$2:$N$988,"Incomplete") -> 2 | W10: =COUNTIFS(QA_Detail!$B$2:$B$988,"InternVL",QA_Detail!$G$2:$G$988,"Chart-Numerical Calculation",QA_Detail!$N$2:$N$988,"Unit") -> 2 | X10: =COUNTIFS(QA_Detail!$B$2:$B$988,"InternVL",QA_Detail!$G$2:$G$988,"Chart-Numerical Calculation",QA_Detail!$N$2:$N$988,"Instruction-following") -> 17 | Y10: =COUNTIFS(QA_Detail!$B$2:$B$988,"InternVL",QA_Detail!$G$2:$G$988,"Chart-Numerical Calculation",QA_Detail!$N$2:$N$988,"Typo/Grammar") -> 8 | Z10: =COUNTIFS(QA_Detail!$B$2:$B$988,"InternVL",QA_Detail!$G$2:$G$988,"Chart-Numerical Calculation",QA_Detail!$N$2:$N$988,"Format") -> 0 | AA10: =COUNTIFS(QA_Detail!$B$2:$B$988,"InternVL",QA_Detail!$G$2:$G$988,"Chart-Numerical Calculation",QA_Detail!$N$2:$N$988,"Hallucination") -> 10
A11: InternVL | B11: Category | C11: Chart-Time-Sensitive | D11: =COUNTIFS(QA_Detail!$B$2:$B$988,"InternVL",QA_Detail!$G$2:$G$988,"Chart-Time-Sensitive") -> 66 | E11: =COUNTIFS(QA_Detail!$B$2:$B$988,"InternVL",QA_Detail!$G$2:$G$988,"Chart-Time-Sensitive",QA_Detail!$L$2:$L$988,"PASS") -> 1 | F11: =COUNTIFS(QA_Detail!$B$2:$B$988,"InternVL",QA_Detail!$G$2:$G$988,"Chart-Time-Sensitive",QA_Detail!$L$2:$L$988,"REVISE") -> 57 | G11: =COUNTIFS(QA_Detail!$B$2:$B$988,"InternVL",QA_Detail!$G$2:$G$988,"Chart-Time-Sensitive",QA_Detail!$L$2:$L$988,"DISCARD") -> 8 | H11: =COUNTIFS(QA_Detail!$B$2:$B$988,"InternVL",QA_Detail!$G$2:$G$988,"Chart-Time-Sensitive",QA_Detail!$R$2:$R$988,"Y") -> 2 | I11: =IFERROR(H11/D11,"-") -> 0.03030303 | J11: =IFERROR(F11/D11,"-") -> 0.86363636 | K11: =IFERROR(G11/D11,"-") -> 0.12121212 | L11: =IFERROR(E11/D11,"-") -> 0.015151515 | M11: =IFERROR((F11+G11)/D11,"-") -> 0.98484848 | N11: =COUNTIFS(QA_Detail!$B$2:$B$988,"InternVL",QA_Detail!$G$2:$G$988,"Chart-Time-Sensitive",QA_Detail!$M$2:$M$988,"Minor") -> 8 | O11: =COUNTIFS(QA_Detail!$B$2:$B$988,"InternVL",QA_Detail!$G$2:$G$988,"Chart-Time-Sensitive",QA_Detail!$M$2:$M$988,"Major") -> 49 | P11: =COUNTIFS(QA_Detail!$B$2:$B$988,"InternVL",QA_Detail!$G$2:$G$988,"Chart-Time-Sensitive",QA_Detail!$M$2:$M$988,"Critical") -> 8 | Q11: =IFERROR(COUNTIFS(QA_Detail!$B$2:$B$988,"InternVL",QA_Detail!$G$2:$G$988,"Chart-Time-Sensitive",QA_Detail!$P$2:$P$988,"Y")/D11,"-") -> 0.27272727 | R11: =COUNTIFS(QA_Detail!$B$2:$B$988,"InternVL",QA_Detail!$G$2:$G$988,"Chart-Time-Sensitive",QA_Detail!$N$2:$N$988,"Factual/Numerical") -> 37 | S11: =COUNTIFS(QA_Detail!$B$2:$B$988,"InternVL",QA_Detail!$G$2:$G$988,"Chart-Time-Sensitive",QA_Detail!$N$2:$N$988,"Reasoning") -> 4 | T11: =COUNTIFS(QA_Detail!$B$2:$B$988,"InternVL",QA_Detail!$G$2:$G$988,"Chart-Time-Sensitive",QA_Detail!$N$2:$N$988,"Temporal") -> 7 | U11: =COUNTIFS(QA_Detail!$B$2:$B$988,"InternVL",QA_Detail!$G$2:$G$988,"Chart-Time-Sensitive",QA_Detail!$N$2:$N$988,"Calculation") -> 2 | V11: =COUNTIFS(QA_Detail!$B$2:$B$988,"InternVL",QA_Detail!$G$2:$G$988,"Chart-Time-Sensitive",QA_Detail!$N$2:$N$988,"Incomplete") -> 1 | W11: =COUNTIFS(QA_Detail!$B$2:$B$988,"InternVL",QA_Detail!$G$2:$G$988,"Chart-Time-Sensitive",QA_Detail!$N$2:$N$988,"Unit") -> 0 | X11: =COUNTIFS(QA_Detail!$B$2:$B$988,"InternVL",QA_Detail!$G$2:$G$988,"Chart-Time-Sensitive",QA_Detail!$N$2:$N$988,"Instruction-following") -> 5 | Y11: =COUNTIFS(QA_Detail!$B$2:$B$988,"InternVL",QA_Detail!$G$2:$G$988,"Chart-Time-Sensitive",QA_Detail!$N$2:$N$988,"Typo/Grammar") -> 1 | Z11: =COUNTIFS(QA_Detail!$B$2:$B$988,"InternVL",QA_Detail!$G$2:$G$988,"Chart-Time-Sensitive",QA_Detail!$N$2:$N$988,"Format") -> 0 | AA11: =COUNTIFS(QA_Detail!$B$2:$B$988,"InternVL",QA_Detail!$G$2:$G$988,"Chart-Time-Sensitive",QA_Detail!$N$2:$N$988,"Hallucination") -> 8
A12: InternVL | B12: Category | C12: Table-Numerical Calculation | D12: =COUNTIFS(QA_Detail!$B$2:$B$988,"InternVL",QA_Detail!$G$2:$G$988,"Table-Numerical Calculation") -> 26 | E12: =COUNTIFS(QA_Detail!$B$2:$B$988,"InternVL",QA_Detail!$G$2:$G$988,"Table-Numerical Calculation",QA_Detail!$L$2:$L$988,"PASS") -> 0 | F12: =COUNTIFS(QA_Detail!$B$2:$B$988,"InternVL",QA_Detail!$G$2:$G$988,"Table-Numerical Calculation",QA_Detail!$L$2:$L$988,"REVISE") -> 23 | G12: =COUNTIFS(QA_Detail!$B$2:$B$988,"InternVL",QA_Detail!$G$2:$G$988,"Table-Numerical Calculation",QA_Detail!$L$2:$L$988,"DISCARD") -> 3 | H12: =COUNTIFS(QA_Detail!$B$2:$B$988,"InternVL",QA_Detail!$G$2:$G$988,"Table-Numerical Calculation",QA_Detail!$R$2:$R$988,"Y") -> 5 | I12: =IFERROR(H12/D12,"-") -> 0.19230769 | J12: =IFERROR(F12/D12,"-") -> 0.88461538 | K12: =IFERROR(G12/D12,"-") -> 0.11538462 | L12: =IFERROR(E12/D12,"-") -> 0 | M12: =IFERROR((F12+G12)/D12,"-") -> 1 | N12: =COUNTIFS(QA_Detail!$B$2:$B$988,"InternVL",QA_Detail!$G$2:$G$988,"Table-Numerical Calculation",QA_Detail!$M$2:$M$988,"Minor") -> 7 | O12: =COUNTIFS(QA_Detail!$B$2:$B$988,"InternVL",QA_Detail!$G$2:$G$988,"Table-Numerical Calculation",QA_Detail!$M$2:$M$988,"Major") -> 16 | P12: =COUNTIFS(QA_Detail!$B$2:$B$988,"InternVL",QA_Detail!$G$2:$G$988,"Table-Numerical Calculation",QA_Detail!$M$2:$M$988,"Critical") -> 3 | Q12: =IFERROR(COUNTIFS(QA_Detail!$B$2:$B$988,"InternVL",QA_Detail!$G$2:$G$988,"Table-Numerical Calculation",QA_Detail!$P$2:$P$988,"Y")/D12,"-") -> 0.34615385 | R12: =COUNTIFS(QA_Detail!$B$2:$B$988,"InternVL",QA_Detail!$G$2:$G$988,"Table-Numerical Calculation",QA_Detail!$N$2:$N$988,"Factual/Numerical") -> 12 | S12: =COUNTIFS(QA_Detail!$B$2:$B$988,"InternVL",QA_Detail!$G$2:$G$988,"Table-Numerical Calculation",QA_Detail!$N$2:$N$988,"Reasoning") -> 2 | T12: =COUNTIFS(QA_Detail!$B$2:$B$988,"InternVL",QA_Detail!$G$2:$G$988,"Table-Numerical Calculation",QA_Detail!$N$2:$N$988,"Temporal") -> 1 | U12: =COUNTIFS(QA_Detail!$B$2:$B$988,"InternVL",QA_Detail!$G$2:$G$988,"Table-Numerical Calculation",QA_Detail!$N$2:$N$988,"Calculation") -> 1 | V12: =COUNTIFS(QA_Detail!$B$2:$B$988,"InternVL",QA_Detail!$G$2:$G$988,"Table-Numerical Calculation",QA_Detail!$N$2:$N$988,"Incomplete") -> 0 | W12: =COUNTIFS(QA_Detail!$B$2:$B$988,"InternVL",QA_Detail!$G$2:$G$988,"Table-Numerical Calculation",QA_Detail!$N$2:$N$988,"Unit") -> 0 | X12: =COUNTIFS(QA_Detail!$B$2:$B$988,"InternVL",QA_Detail!$G$2:$G$988,"Table-Numerical Calculation",QA_Detail!$N$2:$N$988,"Instruction-following") -> 4 | Y12: =COUNTIFS(QA_Detail!$B$2:$B$988,"InternVL",QA_Detail!$G$2:$G$988,"Table-Numerical Calculation",QA_Detail!$N$2:$N$988,"Typo/Grammar") -> 3 | Z12: =COUNTIFS(QA_Detail!$B$2:$B$988,"InternVL",QA_Detail!$G$2:$G$988,"Table-Numerical Calculation",QA_Detail!$N$2:$N$988,"Format") -> 0 | AA12: =COUNTIFS(QA_Detail!$B$2:$B$988,"InternVL",QA_Detail!$G$2:$G$988,"Table-Numerical Calculation",QA_Detail!$N$2:$N$988,"Hallucination") -> 3
A13: InternVL | B13: Category | C13: Table-Comparison and Sorting | D13: =COUNTIFS(QA_Detail!$B$2:$B$988,"InternVL",QA_Detail!$G$2:$G$988,"Table-Comparison and Sorting") -> 13 | E13: =COUNTIFS(QA_Detail!$B$2:$B$988,"InternVL",QA_Detail!$G$2:$G$988,"Table-Comparison and Sorting",QA_Detail!$L$2:$L$988,"PASS") -> 0 | F13: =COUNTIFS(QA_Detail!$B$2:$B$988,"InternVL",QA_Detail!$G$2:$G$988,"Table-Comparison and Sorting",QA_Detail!$L$2:$L$988,"REVISE") -> 12 | G13: =COUNTIFS(QA_Detail!$B$2:$B$988,"InternVL",QA_Detail!$G$2:$G$988,"Table-Comparison and Sorting",QA_Detail!$L$2:$L$988,"DISCARD") -> 1 | H13: =COUNTIFS(QA_Detail!$B$2:$B$988,"InternVL",QA_Detail!$G$2:$G$988,"Table-Comparison and Sorting",QA_Detail!$R$2:$R$988,"Y") -> 2 | I13: =IFERROR(H13/D13,"-") -> 0.15384615 | J13: =IFERROR(F13/D13,"-") -> 0.92307692 | K13: =IFERROR(G13/D13,"-") -> 0.076923077 | L13: =IFERROR(E13/D13,"-") -> 0 | M13: =IFERROR((F13+G13)/D13,"-") -> 1 | N13: =COUNTIFS(QA_Detail!$B$2:$B$988,"InternVL",QA_Detail!$G$2:$G$988,"Table-Comparison and Sorting",QA_Detail!$M$2:$M$988,"Minor") -> 2 | O13: =COUNTIFS(QA_Detail!$B$2:$B$988,"InternVL",QA_Detail!$G$2:$G$988,"Table-Comparison and Sorting",QA_Detail!$M$2:$M$988,"Major") -> 10 | P13: =COUNTIFS(QA_Detail!$B$2:$B$988,"InternVL",QA_Detail!$G$2:$G$988,"Table-Comparison and Sorting",QA_Detail!$M$2:$M$988,"Critical") -> 1 | Q13: =IFERROR(COUNTIFS(QA_Detail!$B$2:$B$988,"InternVL",QA_Detail!$G$2:$G$988,"Table-Comparison and Sorting",QA_Detail!$P$2:$P$988,"Y")/D13,"-") -> 0.61538462 | R13: =COUNTIFS(QA_Detail!$B$2:$B$988,"InternVL",QA_Detail!$G$2:$G$988,"Table-Comparison and Sorting",QA_Detail!$N$2:$N$988,"Factual/Numerical") -> 9 | S13: =COUNTIFS(QA_Detail!$B$2:$B$988,"InternVL",QA_Detail!$G$2:$G$988,"Table-Comparison and Sorting",QA_Detail!$N$2:$N$988,"Reasoning") -> 0 | T13: =COUNTIFS(QA_Detail!$B$2:$B$988,"InternVL",QA_Detail!$G$2:$G$988,"Table-Comparison and Sorting",QA_Detail!$N$2:$N$988,"Temporal") -> 1 | U13: =COUNTIFS(QA_Detail!$B$2:$B$988,"InternVL",QA_Detail!$G$2:$G$988,"Table-Comparison and Sorting",QA_Detail!$N$2:$N$988,"Calculation") -> 0 | V13: =COUNTIFS(QA_Detail!$B$2:$B$988,"InternVL",QA_Detail!$G$2:$G$988,"Table-Comparison and Sorting",QA_Detail!$N$2:$N$988,"Incomplete") -> 0 | W13: =COUNTIFS(QA_Detail!$B$2:$B$988,"InternVL",QA_Detail!$G$2:$G$988,"Table-Comparison and Sorting",QA_Detail!$N$2:$N$988,"Unit") -> 0 | X13: =COUNTIFS(QA_Detail!$B$2:$B$988,"InternVL",QA_Detail!$G$2:$G$988,"Table-Comparison and Sorting",QA_Detail!$N$2:$N$988,"Instruction-following") -> 1 | Y13: =COUNTIFS(QA_Detail!$B$2:$B$988,"InternVL",QA_Detail!$G$2:$G$988,"Table-Comparison and Sorting",QA_Detail!$N$2:$N$988,"Typo/Grammar") -> 0 | Z13: =COUNTIFS(QA_Detail!$B$2:$B$988,"InternVL",QA_Detail!$G$2:$G$988,"Table-Comparison and Sorting",QA_Detail!$N$2:$N$988,"Format") -> 1 | AA13: =COUNTIFS(QA_Detail!$B$2:$B$988,"InternVL",QA_Detail!$G$2:$G$988,"Table-Comparison and Sorting",QA_Detail!$N$2:$N$988,"Hallucination") -> 1
A15: Qwen2.5-VL | B15: Modality | C15: Text | D15: =COUNTIFS(QA_Detail!$B$2:$B$988,"Qwen2.5-VL",QA_Detail!$H$2:$H$988,"Text") -> 163 | E15: =COUNTIFS(QA_Detail!$B$2:$B$988,"Qwen2.5-VL",QA_Detail!$H$2:$H$988,"Text",QA_Detail!$L$2:$L$988,"PASS") -> 89 | F15: =COUNTIFS(QA_Detail!$B$2:$B$988,"Qwen2.5-VL",QA_Detail!$H$2:$H$988,"Text",QA_Detail!$L$2:$L$988,"REVISE") -> 68 | G15: =COUNTIFS(QA_Detail!$B$2:$B$988,"Qwen2.5-VL",QA_Detail!$H$2:$H$988,"Text",QA_Detail!$L$2:$L$988,"DISCARD") -> 6 | H15: =COUNTIFS(QA_Detail!$B$2:$B$988,"Qwen2.5-VL",QA_Detail!$H$2:$H$988,"Text",QA_Detail!$R$2:$R$988,"Y") -> 106 | I15: =IFERROR(H15/D15,"-") -> 0.65030675 | J15: =IFERROR(F15/D15,"-") -> 0.41717791 | K15: =IFERROR(G15/D15,"-") -> 0.036809816 | L15: =IFERROR(E15/D15,"-") -> 0.54601227 | M15: =IFERROR((F15+G15)/D15,"-") -> 0.45398773 | N15: =COUNTIFS(QA_Detail!$B$2:$B$988,"Qwen2.5-VL",QA_Detail!$H$2:$H$988,"Text",QA_Detail!$M$2:$M$988,"Minor") -> 32 | O15: =COUNTIFS(QA_Detail!$B$2:$B$988,"Qwen2.5-VL",QA_Detail!$H$2:$H$988,"Text",QA_Detail!$M$2:$M$988,"Major") -> 36 | P15: =COUNTIFS(QA_Detail!$B$2:$B$988,"Qwen2.5-VL",QA_Detail!$H$2:$H$988,"Text",QA_Detail!$M$2:$M$988,"Critical") -> 6 | Q15: =IFERROR(COUNTIFS(QA_Detail!$B$2:$B$988,"Qwen2.5-VL",QA_Detail!$H$2:$H$988,"Text",QA_Detail!$P$2:$P$988,"Y")/D15,"-") -> 0.85889571 | R15: =COUNTIFS(QA_Detail!$B$2:$B$988,"Qwen2.5-VL",QA_Detail!$H$2:$H$988,"Text",QA_Detail!$N$2:$N$988,"Factual/Numerical") -> 21 | S15: =COUNTIFS(QA_Detail!$B$2:$B$988,"Qwen2.5-VL",QA_Detail!$H$2:$H$988,"Text",QA_Detail!$N$2:$N$988,"Reasoning") -> 9 | T15: =COUNTIFS(QA_Detail!$B$2:$B$988,"Qwen2.5-VL",QA_Detail!$H$2:$H$988,"Text",QA_Detail!$N$2:$N$988,"Temporal") -> 3 | U15: =COUNTIFS(QA_Detail!$B$2:$B$988,"Qwen2.5-VL",QA_Detail!$H$2:$H$988,"Text",QA_Detail!$N$2:$N$988,"Calculation") -> 0 | V15: =COUNTIFS(QA_Detail!$B$2:$B$988,"Qwen2.5-VL",QA_Detail!$H$2:$H$988,"Text",QA_Detail!$N$2:$N$988,"Incomplete") -> 6 | W15: =COUNTIFS(QA_Detail!$B$2:$B$988,"Qwen2.5-VL",QA_Detail!$H$2:$H$988,"Text",QA_Detail!$N$2:$N$988,"Unit") -> 2 | X15: =COUNTIFS(QA_Detail!$B$2:$B$988,"Qwen2.5-VL",QA_Detail!$H$2:$H$988,"Text",QA_Detail!$N$2:$N$988,"Instruction-following") -> 8 | Y15: =COUNTIFS(QA_Detail!$B$2:$B$988,"Qwen2.5-VL",QA_Detail!$H$2:$H$988,"Text",QA_Detail!$N$2:$N$988,"Typo/Grammar") -> 17 | Z15: =COUNTIFS(QA_Detail!$B$2:$B$988,"Qwen2.5-VL",QA_Detail!$H$2:$H$988,"Text",QA_Detail!$N$2:$N$988,"Format") -> 2 | AA15: =COUNTIFS(QA_Detail!$B$2:$B$988,"Qwen2.5-VL",QA_Detail!$H$2:$H$988,"Text",QA_Detail!$N$2:$N$988,"Hallucination") -> 6
A16: Qwen2.5-VL | B16: Modality | C16: Chart | D16: =COUNTIFS(QA_Detail!$B$2:$B$988,"Qwen2.5-VL",QA_Detail!$H$2:$H$988,"Chart") -> 303 | E16: =COUNTIFS(QA_Detail!$B$2:$B$988,"Qwen2.5-VL",QA_Detail!$H$2:$H$988,"Chart",QA_Detail!$L$2:$L$988,"PASS") -> 14 | F16: =COUNTIFS(QA_Detail!$B$2:$B$988,"Qwen2.5-VL",QA_Detail!$H$2:$H$988,"Chart",QA_Detail!$L$2:$L$988,"REVISE") -> 273 | G16: =COUNTIFS(QA_Detail!$B$2:$B$988,"Qwen2.5-VL",QA_Detail!$H$2:$H$988,"Chart",QA_Detail!$L$2:$L$988,"DISCARD") -> 16 | H16: =COUNTIFS(QA_Detail!$B$2:$B$988,"Qwen2.5-VL",QA_Detail!$H$2:$H$988,"Chart",QA_Detail!$R$2:$R$988,"Y") -> 115 | I16: =IFERROR(H16/D16,"-") -> 0.37953795 | J16: =IFERROR(F16/D16,"-") -> 0.9009901 | K16: =IFERROR(G16/D16,"-") -> 0.052805281 | L16: =IFERROR(E16/D16,"-") -> 0.04620462 | M16: =IFERROR((F16+G16)/D16,"-") -> 0.95379538 | N16: =COUNTIFS(QA_Detail!$B$2:$B$988,"Qwen2.5-VL",QA_Detail!$H$2:$H$988,"Chart",QA_Detail!$M$2:$M$988,"Minor") -> 161 | O16: =COUNTIFS(QA_Detail!$B$2:$B$988,"Qwen2.5-VL",QA_Detail!$H$2:$H$988,"Chart",QA_Detail!$M$2:$M$988,"Major") -> 112 | P16: =COUNTIFS(QA_Detail!$B$2:$B$988,"Qwen2.5-VL",QA_Detail!$H$2:$H$988,"Chart",QA_Detail!$M$2:$M$988,"Critical") -> 16 | Q16: =IFERROR(COUNTIFS(QA_Detail!$B$2:$B$988,"Qwen2.5-VL",QA_Detail!$H$2:$H$988,"Chart",QA_Detail!$P$2:$P$988,"Y")/D16,"-") -> 0.12541254 | R16: =COUNTIFS(QA_Detail!$B$2:$B$988,"Qwen2.5-VL",QA_Detail!$H$2:$H$988,"Chart",QA_Detail!$N$2:$N$988,"Factual/Numerical") -> 58 | S16: =COUNTIFS(QA_Detail!$B$2:$B$988,"Qwen2.5-VL",QA_Detail!$H$2:$H$988,"Chart",QA_Detail!$N$2:$N$988,"Reasoning") -> 25 | T16: =COUNTIFS(QA_Detail!$B$2:$B$988,"Qwen2.5-VL",QA_Detail!$H$2:$H$988,"Chart",QA_Detail!$N$2:$N$988,"Temporal") -> 12 | U16: =COUNTIFS(QA_Detail!$B$2:$B$988,"Qwen2.5-VL",QA_Detail!$H$2:$H$988,"Chart",QA_Detail!$N$2:$N$988,"Calculation") -> 9 | V16: =COUNTIFS(QA_Detail!$B$2:$B$988,"Qwen2.5-VL",QA_Detail!$H$2:$H$988,"Chart",QA_Detail!$N$2:$N$988,"Incomplete") -> 19 | W16: =COUNTIFS(QA_Detail!$B$2:$B$988,"Qwen2.5-VL",QA_Detail!$H$2:$H$988,"Chart",QA_Detail!$N$2:$N$988,"Unit") -> 3 | X16: =COUNTIFS(QA_Detail!$B$2:$B$988,"Qwen2.5-VL",QA_Detail!$H$2:$H$988,"Chart",QA_Detail!$N$2:$N$988,"Instruction-following") -> 137 | Y16: =COUNTIFS(QA_Detail!$B$2:$B$988,"Qwen2.5-VL",QA_Detail!$H$2:$H$988,"Chart",QA_Detail!$N$2:$N$988,"Typo/Grammar") -> 7 | Z16: =COUNTIFS(QA_Detail!$B$2:$B$988,"Qwen2.5-VL",QA_Detail!$H$2:$H$988,"Chart",QA_Detail!$N$2:$N$988,"Format") -> 3 | AA16: =COUNTIFS(QA_Detail!$B$2:$B$988,"Qwen2.5-VL",QA_Detail!$H$2:$H$988,"Chart",QA_Detail!$N$2:$N$988,"Hallucination") -> 16
A17: Qwen2.5-VL | B17: Modality | C17: Table | D17: =COUNTIFS(QA_Detail!$B$2:$B$988,"Qwen2.5-VL",QA_Detail!$H$2:$H$988,"Table") -> 26 | E17: =COUNTIFS(QA_Detail!$B$2:$B$988,"Qwen2.5-VL",QA_Detail!$H$2:$H$988,"Table",QA_Detail!$L$2:$L$988,"PASS") -> 1 | F17: =COUNTIFS(QA_Detail!$B$2:$B$988,"Qwen2.5-VL",QA_Detail!$H$2:$H$988,"Table",QA_Detail!$L$2:$L$988,"REVISE") -> 24 | G17: =COUNTIFS(QA_Detail!$B$2:$B$988,"Qwen2.5-VL",QA_Detail!$H$2:$H$988,"Table",QA_Detail!$L$2:$L$988,"DISCARD") -> 1 | H17: =COUNTIFS(QA_Detail!$B$2:$B$988,"Qwen2.5-VL",QA_Detail!$H$2:$H$988,"Table",QA_Detail!$R$2:$R$988,"Y") -> 11 | I17: =IFERROR(H17/D17,"-") -> 0.42307692 | J17: =IFERROR(F17/D17,"-") -> 0.92307692 | K17: =IFERROR(G17/D17,"-") -> 0.038461538 | L17: =IFERROR(E17/D17,"-") -> 0.038461538 | M17: =IFERROR((F17+G17)/D17,"-") -> 0.96153846 | N17: =COUNTIFS(QA_Detail!$B$2:$B$988,"Qwen2.5-VL",QA_Detail!$H$2:$H$988,"Table",QA_Detail!$M$2:$M$988,"Minor") -> 15 | O17: =COUNTIFS(QA_Detail!$B$2:$B$988,"Qwen2.5-VL",QA_Detail!$H$2:$H$988,"Table",QA_Detail!$M$2:$M$988,"Major") -> 9 | P17: =COUNTIFS(QA_Detail!$B$2:$B$988,"Qwen2.5-VL",QA_Detail!$H$2:$H$988,"Table",QA_Detail!$M$2:$M$988,"Critical") -> 1 | Q17: =IFERROR(COUNTIFS(QA_Detail!$B$2:$B$988,"Qwen2.5-VL",QA_Detail!$H$2:$H$988,"Table",QA_Detail!$P$2:$P$988,"Y")/D17,"-") -> 0.15384615 | R17: =COUNTIFS(QA_Detail!$B$2:$B$988,"Qwen2.5-VL",QA_Detail!$H$2:$H$988,"Table",QA_Detail!$N$2:$N$988,"Factual/Numerical") -> 5 | S17: =COUNTIFS(QA_Detail!$B$2:$B$988,"Qwen2.5-VL",QA_Detail!$H$2:$H$988,"Table",QA_Detail!$N$2:$N$988,"Reasoning") -> 0 | T17: =COUNTIFS(QA_Detail!$B$2:$B$988,"Qwen2.5-VL",QA_Detail!$H$2:$H$988,"Table",QA_Detail!$N$2:$N$988,"Temporal") -> 2 | U17: =COUNTIFS(QA_Detail!$B$2:$B$988,"Qwen2.5-VL",QA_Detail!$H$2:$H$988,"Table",QA_Detail!$N$2:$N$988,"Calculation") -> 1 | V17: =COUNTIFS(QA_Detail!$B$2:$B$988,"Qwen2.5-VL",QA_Detail!$H$2:$H$988,"Table",QA_Detail!$N$2:$N$988,"Incomplete") -> 3 | W17: =COUNTIFS(QA_Detail!$B$2:$B$988,"Qwen2.5-VL",QA_Detail!$H$2:$H$988,"Table",QA_Detail!$N$2:$N$988,"Unit") -> 0 | X17: =COUNTIFS(QA_Detail!$B$2:$B$988,"Qwen2.5-VL",QA_Detail!$H$2:$H$988,"Table",QA_Detail!$N$2:$N$988,"Instruction-following") -> 12 | Y17: =COUNTIFS(QA_Detail!$B$2:$B$988,"Qwen2.5-VL",QA_Detail!$H$2:$H$988,"Table",QA_Detail!$N$2:$N$988,"Typo/Grammar") -> 1 | Z17: =COUNTIFS(QA_Detail!$B$2:$B$988,"Qwen2.5-VL",QA_Detail!$H$2:$H$988,"Table",QA_Detail!$N$2:$N$988,"Format") -> 0 | AA17: =COUNTIFS(QA_Detail!$B$2:$B$988,"Qwen2.5-VL",QA_Detail!$H$2:$H$988,"Table",QA_Detail!$N$2:$N$988,"Hallucination") -> 1
A18: Qwen2.5-VL | B18: Category | C18: Text-Text Inference | D18: =COUNTIFS(QA_Detail!$B$2:$B$988,"Qwen2.5-VL",QA_Detail!$G$2:$G$988,"Text-Text Inference") -> 163 | E18: =COUNTIFS(QA_Detail!$B$2:$B$988,"Qwen2.5-VL",QA_Detail!$G$2:$G$988,"Text-Text Inference",QA_Detail!$L$2:$L$988,"PASS") -> 89 | F18: =COUNTIFS(QA_Detail!$B$2:$B$988,"Qwen2.5-VL",QA_Detail!$G$2:$G$988,"Text-Text Inference",QA_Detail!$L$2:$L$988,"REVISE") -> 68 | G18: =COUNTIFS(QA_Detail!$B$2:$B$988,"Qwen2.5-VL",QA_Detail!$G$2:$G$988,"Text-Text Inference",QA_Detail!$L$2:$L$988,"DISCARD") -> 6 | H18: =COUNTIFS(QA_Detail!$B$2:$B$988,"Qwen2.5-VL",QA_Detail!$G$2:$G$988,"Text-Text Inference",QA_Detail!$R$2:$R$988,"Y") -> 106 | I18: =IFERROR(H18/D18,"-") -> 0.65030675 | J18: =IFERROR(F18/D18,"-") -> 0.41717791 | K18: =IFERROR(G18/D18,"-") -> 0.036809816 | L18: =IFERROR(E18/D18,"-") -> 0.54601227 | M18: =IFERROR((F18+G18)/D18,"-") -> 0.45398773 | N18: =COUNTIFS(QA_Detail!$B$2:$B$988,"Qwen2.5-VL",QA_Detail!$G$2:$G$988,"Text-Text Inference",QA_Detail!$M$2:$M$988,"Minor") -> 32 | O18: =COUNTIFS(QA_Detail!$B$2:$B$988,"Qwen2.5-VL",QA_Detail!$G$2:$G$988,"Text-Text Inference",QA_Detail!$M$2:$M$988,"Major") -> 36 | P18: =COUNTIFS(QA_Detail!$B$2:$B$988,"Qwen2.5-VL",QA_Detail!$G$2:$G$988,"Text-Text Inference",QA_Detail!$M$2:$M$988,"Critical") -> 6 | Q18: =IFERROR(COUNTIFS(QA_Detail!$B$2:$B$988,"Qwen2.5-VL",QA_Detail!$G$2:$G$988,"Text-Text Inference",QA_Detail!$P$2:$P$988,"Y")/D18,"-") -> 0.85889571 | R18: =COUNTIFS(QA_Detail!$B$2:$B$988,"Qwen2.5-VL",QA_Detail!$G$2:$G$988,"Text-Text Inference",QA_Detail!$N$2:$N$988,"Factual/Numerical") -> 21 | S18: =COUNTIFS(QA_Detail!$B$2:$B$988,"Qwen2.5-VL",QA_Detail!$G$2:$G$988,"Text-Text Inference",QA_Detail!$N$2:$N$988,"Reasoning") -> 9 | T18: =COUNTIFS(QA_Detail!$B$2:$B$988,"Qwen2.5-VL",QA_Detail!$G$2:$G$988,"Text-Text Inference",QA_Detail!$N$2:$N$988,"Temporal") -> 3 | U18: =COUNTIFS(QA_Detail!$B$2:$B$988,"Qwen2.5-VL",QA_Detail!$G$2:$G$988,"Text-Text Inference",QA_Detail!$N$2:$N$988,"Calculation") -> 0 | V18: =COUNTIFS(QA_Detail!$B$2:$B$988,"Qwen2.5-VL",QA_Detail!$G$2:$G$988,"Text-Text Inference",QA_Detail!$N$2:$N$988,"Incomplete") -> 6 | W18: =COUNTIFS(QA_Detail!$B$2:$B$988,"Qwen2.5-VL",QA_Detail!$G$2:$G$988,"Text-Text Inference",QA_Detail!$N$2:$N$988,"Unit") -> 2 | X18: =COUNTIFS(QA_Detail!$B$2:$B$988,"Qwen2.5-VL",QA_Detail!$G$2:$G$988,"Text-Text Inference",QA_Detail!$N$2:$N$988,"Instruction-following") -> 8 | Y18: =COUNTIFS(QA_Detail!$B$2:$B$988,"Qwen2.5-VL",QA_Detail!$G$2:$G$988,"Text-Text Inference",QA_Detail!$N$2:$N$988,"Typo/Grammar") -> 17 | Z18: =COUNTIFS(QA_Detail!$B$2:$B$988,"Qwen2.5-VL",QA_Detail!$G$2:$G$988,"Text-Text Inference",QA_Detail!$N$2:$N$988,"Format") -> 2 | AA18: =COUNTIFS(QA_Detail!$B$2:$B$988,"Qwen2.5-VL",QA_Detail!$G$2:$G$988,"Text-Text Inference",QA_Detail!$N$2:$N$988,"Hallucination") -> 6
A19: Qwen2.5-VL | B19: Category | C19: Chart-Information Extraction | D19: =COUNTIFS(QA_Detail!$B$2:$B$988,"Qwen2.5-VL",QA_Detail!$G$2:$G$988,"Chart-Information Extraction") -> 155 | E19: =COUNTIFS(QA_Detail!$B$2:$B$988,"Qwen2.5-VL",QA_Detail!$G$2:$G$988,"Chart-Information Extraction",QA_Detail!$L$2:$L$988,"PASS") -> 11 | F19: =COUNTIFS(QA_Detail!$B$2:$B$988,"Qwen2.5-VL",QA_Detail!$G$2:$G$988,"Chart-Information Extraction",QA_Detail!$L$2:$L$988,"REVISE") -> 134 | G19: =COUNTIFS(QA_Detail!$B$2:$B$988,"Qwen2.5-VL",QA_Detail!$G$2:$G$988,"Chart-Information Extraction",QA_Detail!$L$2:$L$988,"DISCARD") -> 10 | H19: =COUNTIFS(QA_Detail!$B$2:$B$988,"Qwen2.5-VL",QA_Detail!$G$2:$G$988,"Chart-Information Extraction",QA_Detail!$R$2:$R$988,"Y") -> 56 | I19: =IFERROR(H19/D19,"-") -> 0.36129032 | J19: =IFERROR(F19/D19,"-") -> 0.86451613 | K19: =IFERROR(G19/D19,"-") -> 0.064516129 | L19: =IFERROR(E19/D19,"-") -> 0.070967742 | M19: =IFERROR((F19+G19)/D19,"-") -> 0.92903226 | N19: =COUNTIFS(QA_Detail!$B$2:$B$988,"Qwen2.5-VL",QA_Detail!$G$2:$G$988,"Chart-Information Extraction",QA_Detail!$M$2:$M$988,"Minor") -> 76 | O19: =COUNTIFS(QA_Detail!$B$2:$B$988,"Qwen2.5-VL",QA_Detail!$G$2:$G$988,"Chart-Information Extraction",QA_Detail!$M$2:$M$988,"Major") -> 58 | P19: =COUNTIFS(QA_Detail!$B$2:$B$988,"Qwen2.5-VL",QA_Detail!$G$2:$G$988,"Chart-Information Extraction",QA_Detail!$M$2:$M$988,"Critical") -> 10 | Q19: =IFERROR(COUNTIFS(QA_Detail!$B$2:$B$988,"Qwen2.5-VL",QA_Detail!$G$2:$G$988,"Chart-Information Extraction",QA_Detail!$P$2:$P$988,"Y")/D19,"-") -> 0.18709677 | R19: =COUNTIFS(QA_Detail!$B$2:$B$988,"Qwen2.5-VL",QA_Detail!$G$2:$G$988,"Chart-Information Extraction",QA_Detail!$N$2:$N$988,"Factual/Numerical") -> 27 | S19: =COUNTIFS(QA_Detail!$B$2:$B$988,"Qwen2.5-VL",QA_Detail!$G$2:$G$988,"Chart-Information Extraction",QA_Detail!$N$2:$N$988,"Reasoning") -> 13 | T19: =COUNTIFS(QA_Detail!$B$2:$B$988,"Qwen2.5-VL",QA_Detail!$G$2:$G$988,"Chart-Information Extraction",QA_Detail!$N$2:$N$988,"Temporal") -> 6 | U19: =COUNTIFS(QA_Detail!$B$2:$B$988,"Qwen2.5-VL",QA_Detail!$G$2:$G$988,"Chart-Information Extraction",QA_Detail!$N$2:$N$988,"Calculation") -> 5 | V19: =COUNTIFS(QA_Detail!$B$2:$B$988,"Qwen2.5-VL",QA_Detail!$G$2:$G$988,"Chart-Information Extraction",QA_Detail!$N$2:$N$988,"Incomplete") -> 13 | W19: =COUNTIFS(QA_Detail!$B$2:$B$988,"Qwen2.5-VL",QA_Detail!$G$2:$G$988,"Chart-Information Extraction",QA_Detail!$N$2:$N$988,"Unit") -> 3 | X19: =COUNTIFS(QA_Detail!$B$2:$B$988,"Qwen2.5-VL",QA_Detail!$G$2:$G$988,"Chart-Information Extraction",QA_Detail!$N$2:$N$988,"Instruction-following") -> 62 | Y19: =COUNTIFS(QA_Detail!$B$2:$B$988,"Qwen2.5-VL",QA_Detail!$G$2:$G$988,"Chart-Information Extraction",QA_Detail!$N$2:$N$988,"Typo/Grammar") -> 2 | Z19: =COUNTIFS(QA_Detail!$B$2:$B$988,"Qwen2.5-VL",QA_Detail!$G$2:$G$988,"Chart-Information Extraction",QA_Detail!$N$2:$N$988,"Format") -> 3 | AA19: =COUNTIFS(QA_Detail!$B$2:$B$988,"Qwen2.5-VL",QA_Detail!$G$2:$G$988,"Chart-Information Extraction",QA_Detail!$N$2:$N$988,"Hallucination") -> 10
A20: Qwen2.5-VL | B20: Category | C20: Chart-Numerical Calculation | D20: =COUNTIFS(QA_Detail!$B$2:$B$988,"Qwen2.5-VL",QA_Detail!$G$2:$G$988,"Chart-Numerical Calculation") -> 131 | E20: =COUNTIFS(QA_Detail!$B$2:$B$988,"Qwen2.5-VL",QA_Detail!$G$2:$G$988,"Chart-Numerical Calculation",QA_Detail!$L$2:$L$988,"PASS") -> 1 | F20: =COUNTIFS(QA_Detail!$B$2:$B$988,"Qwen2.5-VL",QA_Detail!$G$2:$G$988,"Chart-Numerical Calculation",QA_Detail!$L$2:$L$988,"REVISE") -> 127 | G20: =COUNTIFS(QA_Detail!$B$2:$B$988,"Qwen2.5-VL",QA_Detail!$G$2:$G$988,"Chart-Numerical Calculation",QA_Detail!$L$2:$L$988,"DISCARD") -> 3 | H20: =COUNTIFS(QA_Detail!$B$2:$B$988,"Qwen2.5-VL",QA_Detail!$G$2:$G$988,"Chart-Numerical Calculation",QA_Detail!$R$2:$R$988,"Y") -> 53 | I20: =IFERROR(H20/D20,"-") -> 0.40458015 | J20: =IFERROR(F20/D20,"-") -> 0.96946565 | K20: =IFERROR(G20/D20,"-") -> 0.022900763 | L20: =IFERROR(E20/D20,"-") -> 0.0076335878 | M20: =IFERROR((F20+G20)/D20,"-") -> 0.99236641 | N20: =COUNTIFS(QA_Detail!$B$2:$B$988,"Qwen2.5-VL",QA_Detail!$G$2:$G$988,"Chart-Numerical Calculation",QA_Detail!$M$2:$M$988,"Minor") -> 80 | O20: =COUNTIFS(QA_Detail!$B$2:$B$988,"Qwen2.5-VL",QA_Detail!$G$2:$G$988,"Chart-Numerical Calculation",QA_Detail!$M$2:$M$988,"Major") -> 47 | P20: =COUNTIFS(QA_Detail!$B$2:$B$988,"Qwen2.5-VL",QA_Detail!$G$2:$G$988,"Chart-Numerical Calculation",QA_Detail!$M$2:$M$988,"Critical") -> 3 | Q20: =IFERROR(COUNTIFS(QA_Detail!$B$2:$B$988,"Qwen2.5-VL",QA_Detail!$G$2:$G$988,"Chart-Numerical Calculation",QA_Detail!$P$2:$P$988,"Y")/D20,"-") -> 0.030534351 | R20: =COUNTIFS(QA_Detail!$B$2:$B$988,"Qwen2.5-VL",QA_Detail!$G$2:$G$988,"Chart-Numerical Calculation",QA_Detail!$N$2:$N$988,"Factual/Numerical") -> 29 | S20: =COUNTIFS(QA_Detail!$B$2:$B$988,"Qwen2.5-VL",QA_Detail!$G$2:$G$988,"Chart-Numerical Calculation",QA_Detail!$N$2:$N$988,"Reasoning") -> 11 | T20: =COUNTIFS(QA_Detail!$B$2:$B$988,"Qwen2.5-VL",QA_Detail!$G$2:$G$988,"Chart-Numerical Calculation",QA_Detail!$N$2:$N$988,"Temporal") -> 6 | U20: =COUNTIFS(QA_Detail!$B$2:$B$988,"Qwen2.5-VL",QA_Detail!$G$2:$G$988,"Chart-Numerical Calculation",QA_Detail!$N$2:$N$988,"Calculation") -> 4 | V20: =COUNTIFS(QA_Detail!$B$2:$B$988,"Qwen2.5-VL",QA_Detail!$G$2:$G$988,"Chart-Numerical Calculation",QA_Detail!$N$2:$N$988,"Incomplete") -> 3 | W20: =COUNTIFS(QA_Detail!$B$2:$B$988,"Qwen2.5-VL",QA_Detail!$G$2:$G$988,"Chart-Numerical Calculation",QA_Detail!$N$2:$N$988,"Unit") -> 0 | X20: =COUNTIFS(QA_Detail!$B$2:$B$988,"Qwen2.5-VL",QA_Detail!$G$2:$G$988,"Chart-Numerical Calculation",QA_Detail!$N$2:$N$988,"Instruction-following") -> 70 | Y20: =COUNTIFS(QA_Detail!$B$2:$B$988,"Qwen2.5-VL",QA_Detail!$G$2:$G$988,"Chart-Numerical Calculation",QA_Detail!$N$2:$N$988,"Typo/Grammar") -> 4 | Z20: =COUNTIFS(QA_Detail!$B$2:$B$988,"Qwen2.5-VL",QA_Detail!$G$2:$G$988,"Chart-Numerical Calculation",QA_Detail!$N$2:$N$988,"Format") -> 0 | AA20: =COUNTIFS(QA_Detail!$B$2:$B$988,"Qwen2.5-VL",QA_Detail!$G$2:$G$988,"Chart-Numerical Calculation",QA_Detail!$N$2:$N$988,"Hallucination") -> 3
A21: Qwen2.5-VL | B21: Category | C21: Chart-Time-Sensitive | D21: =COUNTIFS(QA_Detail!$B$2:$B$988,"Qwen2.5-VL",QA_Detail!$G$2:$G$988,"Chart-Time-Sensitive") -> 17 | E21: =COUNTIFS(QA_Detail!$B$2:$B$988,"Qwen2.5-VL",QA_Detail!$G$2:$G$988,"Chart-Time-Sensitive",QA_Detail!$L$2:$L$988,"PASS") -> 2 | F21: =COUNTIFS(QA_Detail!$B$2:$B$988,"Qwen2.5-VL",QA_Detail!$G$2:$G$988,"Chart-Time-Sensitive",QA_Detail!$L$2:$L$988,"REVISE") -> 12 | G21: =COUNTIFS(QA_Detail!$B$2:$B$988,"Qwen2.5-VL",QA_Detail!$G$2:$G$988,"Chart-Time-Sensitive",QA_Detail!$L$2:$L$988,"DISCARD") -> 3 | H21: =COUNTIFS(QA_Detail!$B$2:$B$988,"Qwen2.5-VL",QA_Detail!$G$2:$G$988,"Chart-Time-Sensitive",QA_Detail!$R$2:$R$988,"Y") -> 6 | I21: =IFERROR(H21/D21,"-") -> 0.35294118 | J21: =IFERROR(F21/D21,"-") -> 0.70588235 | K21: =IFERROR(G21/D21,"-") -> 0.17647059 | L21: =IFERROR(E21/D21,"-") -> 0.11764706 | M21: =IFERROR((F21+G21)/D21,"-") -> 0.88235294 | N21: =COUNTIFS(QA_Detail!$B$2:$B$988,"Qwen2.5-VL",QA_Detail!$G$2:$G$988,"Chart-Time-Sensitive",QA_Detail!$M$2:$M$988,"Minor") -> 5 | O21: =COUNTIFS(QA_Detail!$B$2:$B$988,"Qwen2.5-VL",QA_Detail!$G$2:$G$988,"Chart-Time-Sensitive",QA_Detail!$M$2:$M$988,"Major") -> 7 | P21: =COUNTIFS(QA_Detail!$B$2:$B$988,"Qwen2.5-VL",QA_Detail!$G$2:$G$988,"Chart-Time-Sensitive",QA_Detail!$M$2:$M$988,"Critical") -> 3 | Q21: =IFERROR(COUNTIFS(QA_Detail!$B$2:$B$988,"Qwen2.5-VL",QA_Detail!$G$2:$G$988,"Chart-Time-Sensitive",QA_Detail!$P$2:$P$988,"Y")/D21,"-") -> 0.29411765 | R21: =COUNTIFS(QA_Detail!$B$2:$B$988,"Qwen2.5-VL",QA_Detail!$G$2:$G$988,"Chart-Time-Sensitive",QA_Detail!$N$2:$N$988,"Factual/Numerical") -> 2 | S21: =COUNTIFS(QA_Detail!$B$2:$B$988,"Qwen2.5-VL",QA_Detail!$G$2:$G$988,"Chart-Time-Sensitive",QA_Detail!$N$2:$N$988,"Reasoning") -> 1 | T21: =COUNTIFS(QA_Detail!$B$2:$B$988,"Qwen2.5-VL",QA_Detail!$G$2:$G$988,"Chart-Time-Sensitive",QA_Detail!$N$2:$N$988,"Temporal") -> 0 | U21: =COUNTIFS(QA_Detail!$B$2:$B$988,"Qwen2.5-VL",QA_Detail!$G$2:$G$988,"Chart-Time-Sensitive",QA_Detail!$N$2:$N$988,"Calculation") -> 0 | V21: =COUNTIFS(QA_Detail!$B$2:$B$988,"Qwen2.5-VL",QA_Detail!$G$2:$G$988,"Chart-Time-Sensitive",QA_Detail!$N$2:$N$988,"Incomplete") -> 3 | W21: =COUNTIFS(QA_Detail!$B$2:$B$988,"Qwen2.5-VL",QA_Detail!$G$2:$G$988,"Chart-Time-Sensitive",QA_Detail!$N$2:$N$988,"Unit") -> 0 | X21: =COUNTIFS(QA_Detail!$B$2:$B$988,"Qwen2.5-VL",QA_Detail!$G$2:$G$988,"Chart-Time-Sensitive",QA_Detail!$N$2:$N$988,"Instruction-following") -> 5 | Y21: =COUNTIFS(QA_Detail!$B$2:$B$988,"Qwen2.5-VL",QA_Detail!$G$2:$G$988,"Chart-Time-Sensitive",QA_Detail!$N$2:$N$988,"Typo/Grammar") -> 1 | Z21: =COUNTIFS(QA_Detail!$B$2:$B$988,"Qwen2.5-VL",QA_Detail!$G$2:$G$988,"Chart-Time-Sensitive",QA_Detail!$N$2:$N$988,"Format") -> 0 | AA21: =COUNTIFS(QA_Detail!$B$2:$B$988,"Qwen2.5-VL",QA_Detail!$G$2:$G$988,"Chart-Time-Sensitive",QA_Detail!$N$2:$N$988,"Hallucination") -> 3
A22: Qwen2.5-VL | B22: Category | C22: Table-Numerical Calculation | D22: =COUNTIFS(QA_Detail!$B$2:$B$988,"Qwen2.5-VL",QA_Detail!$G$2:$G$988,"Table-Numerical Calculation") -> 24 | E22: =COUNTIFS(QA_Detail!$B$2:$B$988,"Qwen2.5-VL",QA_Detail!$G$2:$G$988,"Table-Numerical Calculation",QA_Detail!$L$2:$L$988,"PASS") -> 1 | F22: =COUNTIFS(QA_Detail!$B$2:$B$988,"Qwen2.5-VL",QA_Detail!$G$2:$G$988,"Table-Numerical Calculation",QA_Detail!$L$2:$L$988,"REVISE") -> 22 | G22: =COUNTIFS(QA_Detail!$B$2:$B$988,"Qwen2.5-VL",QA_Detail!$G$2:$G$988,"Table-Numerical Calculation",QA_Detail!$L$2:$L$988,"DISCARD") -> 1 | H22: =COUNTIFS(QA_Detail!$B$2:$B$988,"Qwen2.5-VL",QA_Detail!$G$2:$G$988,"Table-Numerical Calculation",QA_Detail!$R$2:$R$988,"Y") -> 10 | I22: =IFERROR(H22/D22,"-") -> 0.41666667 | J22: =IFERROR(F22/D22,"-") -> 0.91666667 | K22: =IFERROR(G22/D22,"-") -> 0.041666667 | L22: =IFERROR(E22/D22,"-") -> 0.041666667 | M22: =IFERROR((F22+G22)/D22,"-") -> 0.95833333 | N22: =COUNTIFS(QA_Detail!$B$2:$B$988,"Qwen2.5-VL",QA_Detail!$G$2:$G$988,"Table-Numerical Calculation",QA_Detail!$M$2:$M$988,"Minor") -> 14 | O22: =COUNTIFS(QA_Detail!$B$2:$B$988,"Qwen2.5-VL",QA_Detail!$G$2:$G$988,"Table-Numerical Calculation",QA_Detail!$M$2:$M$988,"Major") -> 8 | P22: =COUNTIFS(QA_Detail!$B$2:$B$988,"Qwen2.5-VL",QA_Detail!$G$2:$G$988,"Table-Numerical Calculation",QA_Detail!$M$2:$M$988,"Critical") -> 1 | Q22: =IFERROR(COUNTIFS(QA_Detail!$B$2:$B$988,"Qwen2.5-VL",QA_Detail!$G$2:$G$988,"Table-Numerical Calculation",QA_Detail!$P$2:$P$988,"Y")/D22,"-") -> 0.125 | R22: =COUNTIFS(QA_Detail!$B$2:$B$988,"Qwen2.5-VL",QA_Detail!$G$2:$G$988,"Table-Numerical Calculation",QA_Detail!$N$2:$N$988,"Factual/Numerical") -> 5 | S22: =COUNTIFS(QA_Detail!$B$2:$B$988,"Qwen2.5-VL",QA_Detail!$G$2:$G$988,"Table-Numerical Calculation",QA_Detail!$N$2:$N$988,"Reasoning") -> 0 | T22: =COUNTIFS(QA_Detail!$B$2:$B$988,"Qwen2.5-VL",QA_Detail!$G$2:$G$988,"Table-Numerical Calculation",QA_Detail!$N$2:$N$988,"Temporal") -> 2 | U22: =COUNTIFS(QA_Detail!$B$2:$B$988,"Qwen2.5-VL",QA_Detail!$G$2:$G$988,"Table-Numerical Calculation",QA_Detail!$N$2:$N$988,"Calculation") -> 1 | V22: =COUNTIFS(QA_Detail!$B$2:$B$988,"Qwen2.5-VL",QA_Detail!$G$2:$G$988,"Table-Numerical Calculation",QA_Detail!$N$2:$N$988,"Incomplete") -> 2 | W22: =COUNTIFS(QA_Detail!$B$2:$B$988,"Qwen2.5-VL",QA_Detail!$G$2:$G$988,"Table-Numerical Calculation",QA_Detail!$N$2:$N$988,"Unit") -> 0 | X22: =COUNTIFS(QA_Detail!$B$2:$B$988,"Qwen2.5-VL",QA_Detail!$G$2:$G$988,"Table-Numerical Calculation",QA_Detail!$N$2:$N$988,"Instruction-following") -> 11 | Y22: =COUNTIFS(QA_Detail!$B$2:$B$988,"Qwen2.5-VL",QA_Detail!$G$2:$G$988,"Table-Numerical Calculation",QA_Detail!$N$2:$N$988,"Typo/Grammar") -> 1 | Z22: =COUNTIFS(QA_Detail!$B$2:$B$988,"Qwen2.5-VL",QA_Detail!$G$2:$G$988,"Table-Numerical Calculation",QA_Detail!$N$2:$N$988,"Format") -> 0 | AA22: =COUNTIFS(QA_Detail!$B$2:$B$988,"Qwen2.5-VL",QA_Detail!$G$2:$G$988,"Table-Numerical Calculation",QA_Detail!$N$2:$N$988,"Hallucination") -> 1
A23: Qwen2.5-VL | B23: Category | C23: Table-Comparison and Sorting | D23: =COUNTIFS(QA_Detail!$B$2:$B$988,"Qwen2.5-VL",QA_Detail!$G$2:$G$988,"Table-Comparison and Sorting") -> 2 | E23: =COUNTIFS(QA_Detail!$B$2:$B$988,"Qwen2.5-VL",QA_Detail!$G$2:$G$988,"Table-Comparison and Sorting",QA_Detail!$L$2:$L$988,"PASS") -> 0 | F23: =COUNTIFS(QA_Detail!$B$2:$B$988,"Qwen2.5-VL",QA_Detail!$G$2:$G$988,"Table-Comparison and Sorting",QA_Detail!$L$2:$L$988,"REVISE") -> 2 | G23: =COUNTIFS(QA_Detail!$B$2:$B$988,"Qwen2.5-VL",QA_Detail!$G$2:$G$988,"Table-Comparison and Sorting",QA_Detail!$L$2:$L$988,"DISCARD") -> 0 | H23: =COUNTIFS(QA_Detail!$B$2:$B$988,"Qwen2.5-VL",QA_Detail!$G$2:$G$988,"Table-Comparison and Sorting",QA_Detail!$R$2:$R$988,"Y") -> 1 | I23: =IFERROR(H23/D23,"-") -> 0.5 | J23: =IFERROR(F23/D23,"-") -> 1 | K23: =IFERROR(G23/D23,"-") -> 0 | L23: =IFERROR(E23/D23,"-") -> 0 | M23: =IFERROR((F23+G23)/D23,"-") -> 1 | N23: =COUNTIFS(QA_Detail!$B$2:$B$988,"Qwen2.5-VL",QA_Detail!$G$2:$G$988,"Table-Comparison and Sorting",QA_Detail!$M$2:$M$988,"Minor") -> 1 | O23: =COUNTIFS(QA_Detail!$B$2:$B$988,"Qwen2.5-VL",QA_Detail!$G$2:$G$988,"Table-Comparison and Sorting",QA_Detail!$M$2:$M$988,"Major") -> 1 | P23: =COUNTIFS(QA_Detail!$B$2:$B$988,"Qwen2.5-VL",QA_Detail!$G$2:$G$988,"Table-Comparison and Sorting",QA_Detail!$M$2:$M$988,"Critical") -> 0 | Q23: =IFERROR(COUNTIFS(QA_Detail!$B$2:$B$988,"Qwen2.5-VL",QA_Detail!$G$2:$G$988,"Table-Comparison and Sorting",QA_Detail!$P$2:$P$988,"Y")/D23,"-") -> 0.5 | R23: =COUNTIFS(QA_Detail!$B$2:$B$988,"Qwen2.5-VL",QA_Detail!$G$2:$G$988,"Table-Comparison and Sorting",QA_Detail!$N$2:$N$988,"Factual/Numerical") -> 0 | S23: =COUNTIFS(QA_Detail!$B$2:$B$988,"Qwen2.5-VL",QA_Detail!$G$2:$G$988,"Table-Comparison and Sorting",QA_Detail!$N$2:$N$988,"Reasoning") -> 0 | T23: =COUNTIFS(QA_Detail!$B$2:$B$988,"Qwen2.5-VL",QA_Detail!$G$2:$G$988,"Table-Comparison and Sorting",QA_Detail!$N$2:$N$988,"Temporal") -> 0 | U23: =COUNTIFS(QA_Detail!$B$2:$B$988,"Qwen2.5-VL",QA_Detail!$G$2:$G$988,"Table-Comparison and Sorting",QA_Detail!$N$2:$N$988,"Calculation") -> 0 | V23: =COUNTIFS(QA_Detail!$B$2:$B$988,"Qwen2.5-VL",QA_Detail!$G$2:$G$988,"Table-Comparison and Sorting",QA_Detail!$N$2:$N$988,"Incomplete") -> 1 | W23: =COUNTIFS(QA_Detail!$B$2:$B$988,"Qwen2.5-VL",QA_Detail!$G$2:$G$988,"Table-Comparison and Sorting",QA_Detail!$N$2:$N$988,"Unit") -> 0 | X23: =COUNTIFS(QA_Detail!$B$2:$B$988,"Qwen2.5-VL",QA_Detail!$G$2:$G$988,"Table-Comparison and Sorting",QA_Detail!$N$2:$N$988,"Instruction-following") -> 1 | Y23: =COUNTIFS(QA_Detail!$B$2:$B$988,"Qwen2.5-VL",QA_Detail!$G$2:$G$988,"Table-Comparison and Sorting",QA_Detail!$N$2:$N$988,"Typo/Grammar") -> 0 | Z23: =COUNTIFS(QA_Detail!$B$2:$B$988,"Qwen2.5-VL",QA_Detail!$G$2:$G$988,"Table-Comparison and Sorting",QA_Detail!$N$2:$N$988,"Format") -> 0 | AA23: =COUNTIFS(QA_Detail!$B$2:$B$988,"Qwen2.5-VL",QA_Detail!$G$2:$G$988,"Table-Comparison and Sorting",QA_Detail!$N$2:$N$988,"Hallucination") -> 0
A25: Overall | B25: Modality | C25: Text | D25: =COUNTIFS(QA_Detail!$B$2:$B$988,"*",QA_Detail!$H$2:$H$988,"Text") -> 312 | E25: =COUNTIFS(QA_Detail!$B$2:$B$988,"*",QA_Detail!$H$2:$H$988,"Text",QA_Detail!$L$2:$L$988,"PASS") -> 104 | F25: =COUNTIFS(QA_Detail!$B$2:$B$988,"*",QA_Detail!$H$2:$H$988,"Text",QA_Detail!$L$2:$L$988,"REVISE") -> 187 | G25: =COUNTIFS(QA_Detail!$B$2:$B$988,"*",QA_Detail!$H$2:$H$988,"Text",QA_Detail!$L$2:$L$988,"DISCARD") -> 21 | H25: =COUNTIFS(QA_Detail!$B$2:$B$988,"*",QA_Detail!$H$2:$H$988,"Text",QA_Detail!$R$2:$R$988,"Y") -> 133 | I25: =IFERROR(H25/D25,"-") -> 0.42628205 | J25: =IFERROR(F25/D25,"-") -> 0.59935897 | K25: =IFERROR(G25/D25,"-") -> 0.067307692 | L25: =IFERROR(E25/D25,"-") -> 0.33333333 | M25: =IFERROR((F25+G25)/D25,"-") -> 0.66666667 | N25: =COUNTIFS(QA_Detail!$B$2:$B$988,"*",QA_Detail!$H$2:$H$988,"Text",QA_Detail!$M$2:$M$988,"Minor") -> 63 | O25: =COUNTIFS(QA_Detail!$B$2:$B$988,"*",QA_Detail!$H$2:$H$988,"Text",QA_Detail!$M$2:$M$988,"Major") -> 124 | P25: =COUNTIFS(QA_Detail!$B$2:$B$988,"*",QA_Detail!$H$2:$H$988,"Text",QA_Detail!$M$2:$M$988,"Critical") -> 21 | Q25: =IFERROR(COUNTIFS(QA_Detail!$B$2:$B$988,"*",QA_Detail!$H$2:$H$988,"Text",QA_Detail!$P$2:$P$988,"Y")/D25,"-") -> 0.77564103 | R25: =COUNTIFS(QA_Detail!$B$2:$B$988,"*",QA_Detail!$H$2:$H$988,"Text",QA_Detail!$N$2:$N$988,"Factual/Numerical") -> 86 | S25: =COUNTIFS(QA_Detail!$B$2:$B$988,"*",QA_Detail!$H$2:$H$988,"Text",QA_Detail!$N$2:$N$988,"Reasoning") -> 26 | T25: =COUNTIFS(QA_Detail!$B$2:$B$988,"*",QA_Detail!$H$2:$H$988,"Text",QA_Detail!$N$2:$N$988,"Temporal") -> 14 | U25: =COUNTIFS(QA_Detail!$B$2:$B$988,"*",QA_Detail!$H$2:$H$988,"Text",QA_Detail!$N$2:$N$988,"Calculation") -> 1 | V25: =COUNTIFS(QA_Detail!$B$2:$B$988,"*",QA_Detail!$H$2:$H$988,"Text",QA_Detail!$N$2:$N$988,"Incomplete") -> 9 | W25: =COUNTIFS(QA_Detail!$B$2:$B$988,"*",QA_Detail!$H$2:$H$988,"Text",QA_Detail!$N$2:$N$988,"Unit") -> 3 | X25: =COUNTIFS(QA_Detail!$B$2:$B$988,"*",QA_Detail!$H$2:$H$988,"Text",QA_Detail!$N$2:$N$988,"Instruction-following") -> 9 | Y25: =COUNTIFS(QA_Detail!$B$2:$B$988,"*",QA_Detail!$H$2:$H$988,"Text",QA_Detail!$N$2:$N$988,"Typo/Grammar") -> 35 | Z25: =COUNTIFS(QA_Detail!$B$2:$B$988,"*",QA_Detail!$H$2:$H$988,"Text",QA_Detail!$N$2:$N$988,"Format") -> 4 | AA25: =COUNTIFS(QA_Detail!$B$2:$B$988,"*",QA_Detail!$H$2:$H$988,"Text",QA_Detail!$N$2:$N$988,"Hallucination") -> 21
A26: Overall | B26: Modality | C26: Chart | D26: =COUNTIFS(QA_Detail!$B$2:$B$988,"*",QA_Detail!$H$2:$H$988,"Chart") -> 610 | E26: =COUNTIFS(QA_Detail!$B$2:$B$988,"*",QA_Detail!$H$2:$H$988,"Chart",QA_Detail!$L$2:$L$988,"PASS") -> 17 | F26: =COUNTIFS(QA_Detail!$B$2:$B$988,"*",QA_Detail!$H$2:$H$988,"Chart",QA_Detail!$L$2:$L$988,"REVISE") -> 542 | G26: =COUNTIFS(QA_Detail!$B$2:$B$988,"*",QA_Detail!$H$2:$H$988,"Chart",QA_Detail!$L$2:$L$988,"DISCARD") -> 51 | H26: =COUNTIFS(QA_Detail!$B$2:$B$988,"*",QA_Detail!$H$2:$H$988,"Chart",QA_Detail!$R$2:$R$988,"Y") -> 145 | I26: =IFERROR(H26/D26,"-") -> 0.23770492 | J26: =IFERROR(F26/D26,"-") -> 0.88852459 | K26: =IFERROR(G26/D26,"-") -> 0.083606557 | L26: =IFERROR(E26/D26,"-") -> 0.027868852 | M26: =IFERROR((F26+G26)/D26,"-") -> 0.97213115 | N26: =COUNTIFS(QA_Detail!$B$2:$B$988,"*",QA_Detail!$H$2:$H$988,"Chart",QA_Detail!$M$2:$M$988,"Minor") -> 229 | O26: =COUNTIFS(QA_Detail!$B$2:$B$988,"*",QA_Detail!$H$2:$H$988,"Chart",QA_Detail!$M$2:$M$988,"Major") -> 313 | P26: =COUNTIFS(QA_Detail!$B$2:$B$988,"*",QA_Detail!$H$2:$H$988,"Chart",QA_Detail!$M$2:$M$988,"Critical") -> 51 | Q26: =IFERROR(COUNTIFS(QA_Detail!$B$2:$B$988,"*",QA_Detail!$H$2:$H$988,"Chart",QA_Detail!$P$2:$P$988,"Y")/D26,"-") -> 0.14590164 | R26: =COUNTIFS(QA_Detail!$B$2:$B$988,"*",QA_Detail!$H$2:$H$988,"Chart",QA_Detail!$N$2:$N$988,"Factual/Numerical") -> 206 | S26: =COUNTIFS(QA_Detail!$B$2:$B$988,"*",QA_Detail!$H$2:$H$988,"Chart",QA_Detail!$N$2:$N$988,"Reasoning") -> 52 | T26: =COUNTIFS(QA_Detail!$B$2:$B$988,"*",QA_Detail!$H$2:$H$988,"Chart",QA_Detail!$N$2:$N$988,"Temporal") -> 36 | U26: =COUNTIFS(QA_Detail!$B$2:$B$988,"*",QA_Detail!$H$2:$H$988,"Chart",QA_Detail!$N$2:$N$988,"Calculation") -> 15 | V26: =COUNTIFS(QA_Detail!$B$2:$B$988,"*",QA_Detail!$H$2:$H$988,"Chart",QA_Detail!$N$2:$N$988,"Incomplete") -> 27 | W26: =COUNTIFS(QA_Detail!$B$2:$B$988,"*",QA_Detail!$H$2:$H$988,"Chart",QA_Detail!$N$2:$N$988,"Unit") -> 6 | X26: =COUNTIFS(QA_Detail!$B$2:$B$988,"*",QA_Detail!$H$2:$H$988,"Chart",QA_Detail!$N$2:$N$988,"Instruction-following") -> 172 | Y26: =COUNTIFS(QA_Detail!$B$2:$B$988,"*",QA_Detail!$H$2:$H$988,"Chart",QA_Detail!$N$2:$N$988,"Typo/Grammar") -> 22 | Z26: =COUNTIFS(QA_Detail!$B$2:$B$988,"*",QA_Detail!$H$2:$H$988,"Chart",QA_Detail!$N$2:$N$988,"Format") -> 6 | AA26: =COUNTIFS(QA_Detail!$B$2:$B$988,"*",QA_Detail!$H$2:$H$988,"Chart",QA_Detail!$N$2:$N$988,"Hallucination") -> 51
A27: Overall | B27: Modality | C27: Table | D27: =COUNTIFS(QA_Detail!$B$2:$B$988,"*",QA_Detail!$H$2:$H$988,"Table") -> 65 | E27: =COUNTIFS(QA_Detail!$B$2:$B$988,"*",QA_Detail!$H$2:$H$988,"Table",QA_Detail!$L$2:$L$988,"PASS") -> 1 | F27: =COUNTIFS(QA_Detail!$B$2:$B$988,"*",QA_Detail!$H$2:$H$988,"Table",QA_Detail!$L$2:$L$988,"REVISE") -> 59 | G27: =COUNTIFS(QA_Detail!$B$2:$B$988,"*",QA_Detail!$H$2:$H$988,"Table",QA_Detail!$L$2:$L$988,"DISCARD") -> 5 | H27: =COUNTIFS(QA_Detail!$B$2:$B$988,"*",QA_Detail!$H$2:$H$988,"Table",QA_Detail!$R$2:$R$988,"Y") -> 18 | I27: =IFERROR(H27/D27,"-") -> 0.27692308 | J27: =IFERROR(F27/D27,"-") -> 0.90769231 | K27: =IFERROR(G27/D27,"-") -> 0.076923077 | L27: =IFERROR(E27/D27,"-") -> 0.015384615 | M27: =IFERROR((F27+G27)/D27,"-") -> 0.98461538 | N27: =COUNTIFS(QA_Detail!$B$2:$B$988,"*",QA_Detail!$H$2:$H$988,"Table",QA_Detail!$M$2:$M$988,"Minor") -> 24 | O27: =COUNTIFS(QA_Detail!$B$2:$B$988,"*",QA_Detail!$H$2:$H$988,"Table",QA_Detail!$M$2:$M$988,"Major") -> 35 | P27: =COUNTIFS(QA_Detail!$B$2:$B$988,"*",QA_Detail!$H$2:$H$988,"Table",QA_Detail!$M$2:$M$988,"Critical") -> 5 | Q27: =IFERROR(COUNTIFS(QA_Detail!$B$2:$B$988,"*",QA_Detail!$H$2:$H$988,"Table",QA_Detail!$P$2:$P$988,"Y")/D27,"-") -> 0.32307692 | R27: =COUNTIFS(QA_Detail!$B$2:$B$988,"*",QA_Detail!$H$2:$H$988,"Table",QA_Detail!$N$2:$N$988,"Factual/Numerical") -> 26 | S27: =COUNTIFS(QA_Detail!$B$2:$B$988,"*",QA_Detail!$H$2:$H$988,"Table",QA_Detail!$N$2:$N$988,"Reasoning") -> 2 | T27: =COUNTIFS(QA_Detail!$B$2:$B$988,"*",QA_Detail!$H$2:$H$988,"Table",QA_Detail!$N$2:$N$988,"Temporal") -> 4 | U27: =COUNTIFS(QA_Detail!$B$2:$B$988,"*",QA_Detail!$H$2:$H$988,"Table",QA_Detail!$N$2:$N$988,"Calculation") -> 2 | V27: =COUNTIFS(QA_Detail!$B$2:$B$988,"*",QA_Detail!$H$2:$H$988,"Table",QA_Detail!$N$2:$N$988,"Incomplete") -> 3 | W27: =COUNTIFS(QA_Detail!$B$2:$B$988,"*",QA_Detail!$H$2:$H$988,"Table",QA_Detail!$N$2:$N$988,"Unit") -> 0 | X27: =COUNTIFS(QA_Detail!$B$2:$B$988,"*",QA_Detail!$H$2:$H$988,"Table",QA_Detail!$N$2:$N$988,"Instruction-following") -> 17 | Y27: =COUNTIFS(QA_Detail!$B$2:$B$988,"*",QA_Detail!$H$2:$H$988,"Table",QA_Detail!$N$2:$N$988,"Typo/Grammar") -> 4 | Z27: =COUNTIFS(QA_Detail!$B$2:$B$988,"*",QA_Detail!$H$2:$H$988,"Table",QA_Detail!$N$2:$N$988,"Format") -> 1 | AA27: =COUNTIFS(QA_Detail!$B$2:$B$988,"*",QA_Detail!$H$2:$H$988,"Table",QA_Detail!$N$2:$N$988,"Hallucination") -> 5
A28: Overall | B28: Category | C28: Text-Text Inference | D28: =COUNTIFS(QA_Detail!$B$2:$B$988,"*",QA_Detail!$G$2:$G$988,"Text-Text Inference") -> 312 | E28: =COUNTIFS(QA_Detail!$B$2:$B$988,"*",QA_Detail!$G$2:$G$988,"Text-Text Inference",QA_Detail!$L$2:$L$988,"PASS") -> 104 | F28: =COUNTIFS(QA_Detail!$B$2:$B$988,"*",QA_Detail!$G$2:$G$988,"Text-Text Inference",QA_Detail!$L$2:$L$988,"REVISE") -> 187 | G28: =COUNTIFS(QA_Detail!$B$2:$B$988,"*",QA_Detail!$G$2:$G$988,"Text-Text Inference",QA_Detail!$L$2:$L$988,"DISCARD") -> 21 | H28: =COUNTIFS(QA_Detail!$B$2:$B$988,"*",QA_Detail!$G$2:$G$988,"Text-Text Inference",QA_Detail!$R$2:$R$988,"Y") -> 133 | I28: =IFERROR(H28/D28,"-") -> 0.42628205 | J28: =IFERROR(F28/D28,"-") -> 0.59935897 | K28: =IFERROR(G28/D28,"-") -> 0.067307692 | L28: =IFERROR(E28/D28,"-") -> 0.33333333 | M28: =IFERROR((F28+G28)/D28,"-") -> 0.66666667 | N28: =COUNTIFS(QA_Detail!$B$2:$B$988,"*",QA_Detail!$G$2:$G$988,"Text-Text Inference",QA_Detail!$M$2:$M$988,"Minor") -> 63 | O28: =COUNTIFS(QA_Detail!$B$2:$B$988,"*",QA_Detail!$G$2:$G$988,"Text-Text Inference",QA_Detail!$M$2:$M$988,"Major") -> 124 | P28: =COUNTIFS(QA_Detail!$B$2:$B$988,"*",QA_Detail!$G$2:$G$988,"Text-Text Inference",QA_Detail!$M$2:$M$988,"Critical") -> 21 | Q28: =IFERROR(COUNTIFS(QA_Detail!$B$2:$B$988,"*",QA_Detail!$G$2:$G$988,"Text-Text Inference",QA_Detail!$P$2:$P$988,"Y")/D28,"-") -> 0.77564103 | R28: =COUNTIFS(QA_Detail!$B$2:$B$988,"*",QA_Detail!$G$2:$G$988,"Text-Text Inference",QA_Detail!$N$2:$N$988,"Factual/Numerical") -> 86 | S28: =COUNTIFS(QA_Detail!$B$2:$B$988,"*",QA_Detail!$G$2:$G$988,"Text-Text Inference",QA_Detail!$N$2:$N$988,"Reasoning") -> 26 | T28: =COUNTIFS(QA_Detail!$B$2:$B$988,"*",QA_Detail!$G$2:$G$988,"Text-Text Inference",QA_Detail!$N$2:$N$988,"Temporal") -> 14 | U28: =COUNTIFS(QA_Detail!$B$2:$B$988,"*",QA_Detail!$G$2:$G$988,"Text-Text Inference",QA_Detail!$N$2:$N$988,"Calculation") -> 1 | V28: =COUNTIFS(QA_Detail!$B$2:$B$988,"*",QA_Detail!$G$2:$G$988,"Text-Text Inference",QA_Detail!$N$2:$N$988,"Incomplete") -> 9 | W28: =COUNTIFS(QA_Detail!$B$2:$B$988,"*",QA_Detail!$G$2:$G$988,"Text-Text Inference",QA_Detail!$N$2:$N$988,"Unit") -> 3 | X28: =COUNTIFS(QA_Detail!$B$2:$B$988,"*",QA_Detail!$G$2:$G$988,"Text-Text Inference",QA_Detail!$N$2:$N$988,"Instruction-following") -> 9 | Y28: =COUNTIFS(QA_Detail!$B$2:$B$988,"*",QA_Detail!$G$2:$G$988,"Text-Text Inference",QA_Detail!$N$2:$N$988,"Typo/Grammar") -> 35 | Z28: =COUNTIFS(QA_Detail!$B$2:$B$988,"*",QA_Detail!$G$2:$G$988,"Text-Text Inference",QA_Detail!$N$2:$N$988,"Format") -> 4 | AA28: =COUNTIFS(QA_Detail!$B$2:$B$988,"*",QA_Detail!$G$2:$G$988,"Text-Text Inference",QA_Detail!$N$2:$N$988,"Hallucination") -> 21
A29: Overall | B29: Category | C29: Chart-Information Extraction | D29: =COUNTIFS(QA_Detail!$B$2:$B$988,"*",QA_Detail!$G$2:$G$988,"Chart-Information Extraction") -> 268 | E29: =COUNTIFS(QA_Detail!$B$2:$B$988,"*",QA_Detail!$G$2:$G$988,"Chart-Information Extraction",QA_Detail!$L$2:$L$988,"PASS") -> 13 | F29: =COUNTIFS(QA_Detail!$B$2:$B$988,"*",QA_Detail!$G$2:$G$988,"Chart-Information Extraction",QA_Detail!$L$2:$L$988,"REVISE") -> 228 | G29: =COUNTIFS(QA_Detail!$B$2:$B$988,"*",QA_Detail!$G$2:$G$988,"Chart-Information Extraction",QA_Detail!$L$2:$L$988,"DISCARD") -> 27 | H29: =COUNTIFS(QA_Detail!$B$2:$B$988,"*",QA_Detail!$G$2:$G$988,"Chart-Information Extraction",QA_Detail!$R$2:$R$988,"Y") -> 69 | I29: =IFERROR(H29/D29,"-") -> 0.25746269 | J29: =IFERROR(F29/D29,"-") -> 0.85074627 | K29: =IFERROR(G29/D29,"-") -> 0.10074627 | L29: =IFERROR(E29/D29,"-") -> 0.048507463 | M29: =IFERROR((F29+G29)/D29,"-") -> 0.95149254 | N29: =COUNTIFS(QA_Detail!$B$2:$B$988,"*",QA_Detail!$G$2:$G$988,"Chart-Information Extraction",QA_Detail!$M$2:$M$988,"Minor") -> 103 | O29: =COUNTIFS(QA_Detail!$B$2:$B$988,"*",QA_Detail!$G$2:$G$988,"Chart-Information Extraction",QA_Detail!$M$2:$M$988,"Major") -> 125 | P29: =COUNTIFS(QA_Detail!$B$2:$B$988,"*",QA_Detail!$G$2:$G$988,"Chart-Information Extraction",QA_Detail!$M$2:$M$988,"Critical") -> 27 | Q29: =IFERROR(COUNTIFS(QA_Detail!$B$2:$B$988,"*",QA_Detail!$G$2:$G$988,"Chart-Information Extraction",QA_Detail!$P$2:$P$988,"Y")/D29,"-") -> 0.19776119 | R29: =COUNTIFS(QA_Detail!$B$2:$B$988,"*",QA_Detail!$G$2:$G$988,"Chart-Information Extraction",QA_Detail!$N$2:$N$988,"Factual/Numerical") -> 80 | S29: =COUNTIFS(QA_Detail!$B$2:$B$988,"*",QA_Detail!$G$2:$G$988,"Chart-Information Extraction",QA_Detail!$N$2:$N$988,"Reasoning") -> 21 | T29: =COUNTIFS(QA_Detail!$B$2:$B$988,"*",QA_Detail!$G$2:$G$988,"Chart-Information Extraction",QA_Detail!$N$2:$N$988,"Temporal") -> 10 | U29: =COUNTIFS(QA_Detail!$B$2:$B$988,"*",QA_Detail!$G$2:$G$988,"Chart-Information Extraction",QA_Detail!$N$2:$N$988,"Calculation") -> 6 | V29: =COUNTIFS(QA_Detail!$B$2:$B$988,"*",QA_Detail!$G$2:$G$988,"Chart-Information Extraction",QA_Detail!$N$2:$N$988,"Incomplete") -> 18 | W29: =COUNTIFS(QA_Detail!$B$2:$B$988,"*",QA_Detail!$G$2:$G$988,"Chart-Information Extraction",QA_Detail!$N$2:$N$988,"Unit") -> 4 | X29: =COUNTIFS(QA_Detail!$B$2:$B$988,"*",QA_Detail!$G$2:$G$988,"Chart-Information Extraction",QA_Detail!$N$2:$N$988,"Instruction-following") -> 75 | Y29: =COUNTIFS(QA_Detail!$B$2:$B$988,"*",QA_Detail!$G$2:$G$988,"Chart-Information Extraction",QA_Detail!$N$2:$N$988,"Typo/Grammar") -> 8 | Z29: =COUNTIFS(QA_Detail!$B$2:$B$988,"*",QA_Detail!$G$2:$G$988,"Chart-Information Extraction",QA_Detail!$N$2:$N$988,"Format") -> 6 | AA29: =COUNTIFS(QA_Detail!$B$2:$B$988,"*",QA_Detail!$G$2:$G$988,"Chart-Information Extraction",QA_Detail!$N$2:$N$988,"Hallucination") -> 27
A30: Overall | B30: Category | C30: Chart-Numerical Calculation | D30: =COUNTIFS(QA_Detail!$B$2:$B$988,"*",QA_Detail!$G$2:$G$988,"Chart-Numerical Calculation") -> 259 | E30: =COUNTIFS(QA_Detail!$B$2:$B$988,"*",QA_Detail!$G$2:$G$988,"Chart-Numerical Calculation",QA_Detail!$L$2:$L$988,"PASS") -> 1 | F30: =COUNTIFS(QA_Detail!$B$2:$B$988,"*",QA_Detail!$G$2:$G$988,"Chart-Numerical Calculation",QA_Detail!$L$2:$L$988,"REVISE") -> 245 | G30: =COUNTIFS(QA_Detail!$B$2:$B$988,"*",QA_Detail!$G$2:$G$988,"Chart-Numerical Calculation",QA_Detail!$L$2:$L$988,"DISCARD") -> 13 | H30: =COUNTIFS(QA_Detail!$B$2:$B$988,"*",QA_Detail!$G$2:$G$988,"Chart-Numerical Calculation",QA_Detail!$R$2:$R$988,"Y") -> 68 | I30: =IFERROR(H30/D30,"-") -> 0.26254826 | J30: =IFERROR(F30/D30,"-") -> 0.94594595 | K30: =IFERROR(G30/D30,"-") -> 0.05019305 | L30: =IFERROR(E30/D30,"-") -> 0.0038610039 | M30: =IFERROR((F30+G30)/D30,"-") -> 0.996139 | N30: =COUNTIFS(QA_Detail!$B$2:$B$988,"*",QA_Detail!$G$2:$G$988,"Chart-Numerical Calculation",QA_Detail!$M$2:$M$988,"Minor") -> 113 | O30: =COUNTIFS(QA_Detail!$B$2:$B$988,"*",QA_Detail!$G$2:$G$988,"Chart-Numerical Calculation",QA_Detail!$M$2:$M$988,"Major") -> 132 | P30: =COUNTIFS(QA_Detail!$B$2:$B$988,"*",QA_Detail!$G$2:$G$988,"Chart-Numerical Calculation",QA_Detail!$M$2:$M$988,"Critical") -> 13 | Q30: =IFERROR(COUNTIFS(QA_Detail!$B$2:$B$988,"*",QA_Detail!$G$2:$G$988,"Chart-Numerical Calculation",QA_Detail!$P$2:$P$988,"Y")/D30,"-") -> 0.05019305 | R30: =COUNTIFS(QA_Detail!$B$2:$B$988,"*",QA_Detail!$G$2:$G$988,"Chart-Numerical Calculation",QA_Detail!$N$2:$N$988,"Factual/Numerical") -> 87 | S30: =COUNTIFS(QA_Detail!$B$2:$B$988,"*",QA_Detail!$G$2:$G$988,"Chart-Numerical Calculation",QA_Detail!$N$2:$N$988,"Reasoning") -> 26 | T30: =COUNTIFS(QA_Detail!$B$2:$B$988,"*",QA_Detail!$G$2:$G$988,"Chart-Numerical Calculation",QA_Detail!$N$2:$N$988,"Temporal") -> 19 | U30: =COUNTIFS(QA_Detail!$B$2:$B$988,"*",QA_Detail!$G$2:$G$988,"Chart-Numerical Calculation",QA_Detail!$N$2:$N$988,"Calculation") -> 7 | V30: =COUNTIFS(QA_Detail!$B$2:$B$988,"*",QA_Detail!$G$2:$G$988,"Chart-Numerical Calculation",QA_Detail!$N$2:$N$988,"Incomplete") -> 5 | W30: =COUNTIFS(QA_Detail!$B$2:$B$988,"*",QA_Detail!$G$2:$G$988,"Chart-Numerical Calculation",QA_Detail!$N$2:$N$988,"Unit") -> 2 | X30: =COUNTIFS(QA_Detail!$B$2:$B$988,"*",QA_Detail!$G$2:$G$988,"Chart-Numerical Calculation",QA_Detail!$N$2:$N$988,"Instruction-following") -> 87 | Y30: =COUNTIFS(QA_Detail!$B$2:$B$988,"*",QA_Detail!$G$2:$G$988,"Chart-Numerical Calculation",QA_Detail!$N$2:$N$988,"Typo/Grammar") -> 12 | Z30: =COUNTIFS(QA_Detail!$B$2:$B$988,"*",QA_Detail!$G$2:$G$988,"Chart-Numerical Calculation",QA_Detail!$N$2:$N$988,"Format") -> 0 | AA30: =COUNTIFS(QA_Detail!$B$2:$B$988,"*",QA_Detail!$G$2:$G$988,"Chart-Numerical Calculation",QA_Detail!$N$2:$N$988,"Hallucination") -> 13
A31: Overall | B31: Category | C31: Chart-Time-Sensitive | D31: =COUNTIFS(QA_Detail!$B$2:$B$988,"*",QA_Detail!$G$2:$G$988,"Chart-Time-Sensitive") -> 83 | E31: =COUNTIFS(QA_Detail!$B$2:$B$988,"*",QA_Detail!$G$2:$G$988,"Chart-Time-Sensitive",QA_Detail!$L$2:$L$988,"PASS") -> 3 | F31: =COUNTIFS(QA_Detail!$B$2:$B$988,"*",QA_Detail!$G$2:$G$988,"Chart-Time-Sensitive",QA_Detail!$L$2:$L$988,"REVISE") -> 69 | G31: =COUNTIFS(QA_Detail!$B$2:$B$988,"*",QA_Detail!$G$2:$G$988,"Chart-Time-Sensitive",QA_Detail!$L$2:$L$988,"DISCARD") -> 11 | H31: =COUNTIFS(QA_Detail!$B$2:$B$988,"*",QA_Detail!$G$2:$G$988,"Chart-Time-Sensitive",QA_Detail!$R$2:$R$988,"Y") -> 8 | I31: =IFERROR(H31/D31,"-") -> 0.096385542 | J31: =IFERROR(F31/D31,"-") -> 0.8313253 | K31: =IFERROR(G31/D31,"-") -> 0.13253012 | L31: =IFERROR(E31/D31,"-") -> 0.036144578 | M31: =IFERROR((F31+G31)/D31,"-") -> 0.96385542 | N31: =COUNTIFS(QA_Detail!$B$2:$B$988,"*",QA_Detail!$G$2:$G$988,"Chart-Time-Sensitive",QA_Detail!$M$2:$M$988,"Minor") -> 13 | O31: =COUNTIFS(QA_Detail!$B$2:$B$988,"*",QA_Detail!$G$2:$G$988,"Chart-Time-Sensitive",QA_Detail!$M$2:$M$988,"Major") -> 56 | P31: =COUNTIFS(QA_Detail!$B$2:$B$988,"*",QA_Detail!$G$2:$G$988,"Chart-Time-Sensitive",QA_Detail!$M$2:$M$988,"Critical") -> 11 | Q31: =IFERROR(COUNTIFS(QA_Detail!$B$2:$B$988,"*",QA_Detail!$G$2:$G$988,"Chart-Time-Sensitive",QA_Detail!$P$2:$P$988,"Y")/D31,"-") -> 0.27710843 | R31: =COUNTIFS(QA_Detail!$B$2:$B$988,"*",QA_Detail!$G$2:$G$988,"Chart-Time-Sensitive",QA_Detail!$N$2:$N$988,"Factual/Numerical") -> 39 | S31: =COUNTIFS(QA_Detail!$B$2:$B$988,"*",QA_Detail!$G$2:$G$988,"Chart-Time-Sensitive",QA_Detail!$N$2:$N$988,"Reasoning") -> 5 | T31: =COUNTIFS(QA_Detail!$B$2:$B$988,"*",QA_Detail!$G$2:$G$988,"Chart-Time-Sensitive",QA_Detail!$N$2:$N$988,"Temporal") -> 7 | U31: =COUNTIFS(QA_Detail!$B$2:$B$988,"*",QA_Detail!$G$2:$G$988,"Chart-Time-Sensitive",QA_Detail!$N$2:$N$988,"Calculation") -> 2 | V31: =COUNTIFS(QA_Detail!$B$2:$B$988,"*",QA_Detail!$G$2:$G$988,"Chart-Time-Sensitive",QA_Detail!$N$2:$N$988,"Incomplete") -> 4 | W31: =COUNTIFS(QA_Detail!$B$2:$B$988,"*",QA_Detail!$G$2:$G$988,"Chart-Time-Sensitive",QA_Detail!$N$2:$N$988,"Unit") -> 0 | X31: =COUNTIFS(QA_Detail!$B$2:$B$988,"*",QA_Detail!$G$2:$G$988,"Chart-Time-Sensitive",QA_Detail!$N$2:$N$988,"Instruction-following") -> 10 | Y31: =COUNTIFS(QA_Detail!$B$2:$B$988,"*",QA_Detail!$G$2:$G$988,"Chart-Time-Sensitive",QA_Detail!$N$2:$N$988,"Typo/Grammar") -> 2 | Z31: =COUNTIFS(QA_Detail!$B$2:$B$988,"*",QA_Detail!$G$2:$G$988,"Chart-Time-Sensitive",QA_Detail!$N$2:$N$988,"Format") -> 0 | AA31: =COUNTIFS(QA_Detail!$B$2:$B$988,"*",QA_Detail!$G$2:$G$988,"Chart-Time-Sensitive",QA_Detail!$N$2:$N$988,"Hallucination") -> 11
A32: Overall | B32: Category | C32: Table-Numerical Calculation | D32: =COUNTIFS(QA_Detail!$B$2:$B$988,"*",QA_Detail!$G$2:$G$988,"Table-Numerical Calculation") -> 50 | E32: =COUNTIFS(QA_Detail!$B$2:$B$988,"*",QA_Detail!$G$2:$G$988,"Table-Numerical Calculation",QA_Detail!$L$2:$L$988,"PASS") -> 1 | F32: =COUNTIFS(QA_Detail!$B$2:$B$988,"*",QA_Detail!$G$2:$G$988,"Table-Numerical Calculation",QA_Detail!$L$2:$L$988,"REVISE") -> 45 | G32: =COUNTIFS(QA_Detail!$B$2:$B$988,"*",QA_Detail!$G$2:$G$988,"Table-Numerical Calculation",QA_Detail!$L$2:$L$988,"DISCARD") -> 4 | H32: =COUNTIFS(QA_Detail!$B$2:$B$988,"*",QA_Detail!$G$2:$G$988,"Table-Numerical Calculation",QA_Detail!$R$2:$R$988,"Y") -> 15 | I32: =IFERROR(H32/D32,"-") -> 0.3 | J32: =IFERROR(F32/D32,"-") -> 0.9 | K32: =IFERROR(G32/D32,"-") -> 0.08 | L32: =IFERROR(E32/D32,"-") -> 0.02 | M32: =IFERROR((F32+G32)/D32,"-") -> 0.98 | N32: =COUNTIFS(QA_Detail!$B$2:$B$988,"*",QA_Detail!$G$2:$G$988,"Table-Numerical Calculation",QA_Detail!$M$2:$M$988,"Minor") -> 21 | O32: =COUNTIFS(QA_Detail!$B$2:$B$988,"*",QA_Detail!$G$2:$G$988,"Table-Numerical Calculation",QA_Detail!$M$2:$M$988,"Major") -> 24 | P32: =COUNTIFS(QA_Detail!$B$2:$B$988,"*",QA_Detail!$G$2:$G$988,"Table-Numerical Calculation",QA_Detail!$M$2:$M$988,"Critical") -> 4 | Q32: =IFERROR(COUNTIFS(QA_Detail!$B$2:$B$988,"*",QA_Detail!$G$2:$G$988,"Table-Numerical Calculation",QA_Detail!$P$2:$P$988,"Y")/D32,"-") -> 0.24 | R32: =COUNTIFS(QA_Detail!$B$2:$B$988,"*",QA_Detail!$G$2:$G$988,"Table-Numerical Calculation",QA_Detail!$N$2:$N$988,"Factual/Numerical") -> 17 | S32: =COUNTIFS(QA_Detail!$B$2:$B$988,"*",QA_Detail!$G$2:$G$988,"Table-Numerical Calculation",QA_Detail!$N$2:$N$988,"Reasoning") -> 2 | T32: =COUNTIFS(QA_Detail!$B$2:$B$988,"*",QA_Detail!$G$2:$G$988,"Table-Numerical Calculation",QA_Detail!$N$2:$N$988,"Temporal") -> 3 | U32: =COUNTIFS(QA_Detail!$B$2:$B$988,"*",QA_Detail!$G$2:$G$988,"Table-Numerical Calculation",QA_Detail!$N$2:$N$988,"Calculation") -> 2 | V32: =COUNTIFS(QA_Detail!$B$2:$B$988,"*",QA_Detail!$G$2:$G$988,"Table-Numerical Calculation",QA_Detail!$N$2:$N$988,"Incomplete") -> 2 | W32: =COUNTIFS(QA_Detail!$B$2:$B$988,"*",QA_Detail!$G$2:$G$988,"Table-Numerical Calculation",QA_Detail!$N$2:$N$988,"Unit") -> 0 | X32: =COUNTIFS(QA_Detail!$B$2:$B$988,"*",QA_Detail!$G$2:$G$988,"Table-Numerical Calculation",QA_Detail!$N$2:$N$988,"Instruction-following") -> 15 | Y32: =COUNTIFS(QA_Detail!$B$2:$B$988,"*",QA_Detail!$G$2:$G$988,"Table-Numerical Calculation",QA_Detail!$N$2:$N$988,"Typo/Grammar") -> 4 | Z32: =COUNTIFS(QA_Detail!$B$2:$B$988,"*",QA_Detail!$G$2:$G$988,"Table-Numerical Calculation",QA_Detail!$N$2:$N$988,"Format") -> 0 | AA32: =COUNTIFS(QA_Detail!$B$2:$B$988,"*",QA_Detail!$G$2:$G$988,"Table-Numerical Calculation",QA_Detail!$N$2:$N$988,"Hallucination") -> 4
A33: Overall | B33: Category | C33: Table-Comparison and Sorting | D33: =COUNTIFS(QA_Detail!$B$2:$B$988,"*",QA_Detail!$G$2:$G$988,"Table-Comparison and Sorting") -> 15 | E33: =COUNTIFS(QA_Detail!$B$2:$B$988,"*",QA_Detail!$G$2:$G$988,"Table-Comparison and Sorting",QA_Detail!$L$2:$L$988,"PASS") -> 0 | F33: =COUNTIFS(QA_Detail!$B$2:$B$988,"*",QA_Detail!$G$2:$G$988,"Table-Comparison and Sorting",QA_Detail!$L$2:$L$988,"REVISE") -> 14 | G33: =COUNTIFS(QA_Detail!$B$2:$B$988,"*",QA_Detail!$G$2:$G$988,"Table-Comparison and Sorting",QA_Detail!$L$2:$L$988,"DISCARD") -> 1 | H33: =COUNTIFS(QA_Detail!$B$2:$B$988,"*",QA_Detail!$G$2:$G$988,"Table-Comparison and Sorting",QA_Detail!$R$2:$R$988,"Y") -> 3 | I33: =IFERROR(H33/D33,"-") -> 0.2 | J33: =IFERROR(F33/D33,"-") -> 0.93333333 | K33: =IFERROR(G33/D33,"-") -> 0.066666667 | L33: =IFERROR(E33/D33,"-") -> 0 | M33: =IFERROR((F33+G33)/D33,"-") -> 1 | N33: =COUNTIFS(QA_Detail!$B$2:$B$988,"*",QA_Detail!$G$2:$G$988,"Table-Comparison and Sorting",QA_Detail!$M$2:$M$988,"Minor") -> 3 | O33: =COUNTIFS(QA_Detail!$B$2:$B$988,"*",QA_Detail!$G$2:$G$988,"Table-Comparison and Sorting",QA_Detail!$M$2:$M$988,"Major") -> 11 | P33: =COUNTIFS(QA_Detail!$B$2:$B$988,"*",QA_Detail!$G$2:$G$988,"Table-Comparison and Sorting",QA_Detail!$M$2:$M$988,"Critical") -> 1 | Q33: =IFERROR(COUNTIFS(QA_Detail!$B$2:$B$988,"*",QA_Detail!$G$2:$G$988,"Table-Comparison and Sorting",QA_Detail!$P$2:$P$988,"Y")/D33,"-") -> 0.6 | R33: =COUNTIFS(QA_Detail!$B$2:$B$988,"*",QA_Detail!$G$2:$G$988,"Table-Comparison and Sorting",QA_Detail!$N$2:$N$988,"Factual/Numerical") -> 9 | S33: =COUNTIFS(QA_Detail!$B$2:$B$988,"*",QA_Detail!$G$2:$G$988,"Table-Comparison and Sorting",QA_Detail!$N$2:$N$988,"Reasoning") -> 0 | T33: =COUNTIFS(QA_Detail!$B$2:$B$988,"*",QA_Detail!$G$2:$G$988,"Table-Comparison and Sorting",QA_Detail!$N$2:$N$988,"Temporal") -> 1 | U33: =COUNTIFS(QA_Detail!$B$2:$B$988,"*",QA_Detail!$G$2:$G$988,"Table-Comparison and Sorting",QA_Detail!$N$2:$N$988,"Calculation") -> 0 | V33: =COUNTIFS(QA_Detail!$B$2:$B$988,"*",QA_Detail!$G$2:$G$988,"Table-Comparison and Sorting",QA_Detail!$N$2:$N$988,"Incomplete") -> 1 | W33: =COUNTIFS(QA_Detail!$B$2:$B$988,"*",QA_Detail!$G$2:$G$988,"Table-Comparison and Sorting",QA_Detail!$N$2:$N$988,"Unit") -> 0 | X33: =COUNTIFS(QA_Detail!$B$2:$B$988,"*",QA_Detail!$G$2:$G$988,"Table-Comparison and Sorting",QA_Detail!$N$2:$N$988,"Instruction-following") -> 2 | Y33: =COUNTIFS(QA_Detail!$B$2:$B$988,"*",QA_Detail!$G$2:$G$988,"Table-Comparison and Sorting",QA_Detail!$N$2:$N$988,"Typo/Grammar") -> 0 | Z33: =COUNTIFS(QA_Detail!$B$2:$B$988,"*",QA_Detail!$G$2:$G$988,"Table-Comparison and Sorting",QA_Detail!$N$2:$N$988,"Format") -> 1 | AA33: =COUNTIFS(QA_Detail!$B$2:$B$988,"*",QA_Detail!$G$2:$G$988,"Table-Comparison and Sorting",QA_Detail!$N$2:$N$988,"Hallucination") -> 1
A35: Top-error columns count the PRIMARY error type of each REVISE/DISCARD QA. "-" = no QA of that category for the model.

Sheet ErrorType_x_Category
A1: Error type × QA category (any occurrence, one QA can have several)
A2: Counts of QA containing each error type. Use with By_Category N to get rates.
A4: InternVL
A5: Error Type | B5: Text-Text Inference | C5: Chart-Information Extraction | D5: Chart-Numerical Calculation | E5: Chart-Time-Sensitive | F5: Table-Numerical Calculation | G5: Table-Comparison and Sorting | H5: Total
A6: Hallucination | B6: =COUNTIFS(QA_Detail!$B$2:$B$988,"InternVL",QA_Detail!$G$2:$G$988,"Text-Text Inference",QA_Detail!$Y$2:$Y$988,1) -> 15 | C6: =COUNTIFS(QA_Detail!$B$2:$B$988,"InternVL",QA_Detail!$G$2:$G$988,"Chart-Information Extraction",QA_Detail!$Y$2:$Y$988,1) -> 18 | D6: =COUNTIFS(QA_Detail!$B$2:$B$988,"InternVL",QA_Detail!$G$2:$G$988,"Chart-Numerical Calculation",QA_Detail!$Y$2:$Y$988,1) -> 10 | E6: =COUNTIFS(QA_Detail!$B$2:$B$988,"InternVL",QA_Detail!$G$2:$G$988,"Chart-Time-Sensitive",QA_Detail!$Y$2:$Y$988,1) -> 8 | F6: =COUNTIFS(QA_Detail!$B$2:$B$988,"InternVL",QA_Detail!$G$2:$G$988,"Table-Numerical Calculation",QA_Detail!$Y$2:$Y$988,1) -> 3 | G6: =COUNTIFS(QA_Detail!$B$2:$B$988,"InternVL",QA_Detail!$G$2:$G$988,"Table-Comparison and Sorting",QA_Detail!$Y$2:$Y$988,1) -> 1 | H6: =SUM(B6:G6) -> 55
